Workbook

Sheet Product Tier Matrix
A1: SECTION A: PRODUCT TIER CLASSIFICATION
A2: Product Category | B2: Commission Range | C2: Tier | D2: DST Credit % | E2: Non-Direct Referral Rate
A3: Life Regular 10yr+ | B3: >30% | C3: Tier 1 | D3: 100 | E3: 15
A4: Life Regular <10yr | B4: 15-30% | C4: Tier 2 | D4: 75 | E4: 10
A5: Life ULIP | B5: <15% | C5: Tier 3 | D5: 50 | E5: 5
A6: Life Single Premium | B6: <15% | C6: Tier 3 | D6: 50 | E6: 5
A7: Health Fresh (Annual) | B7: >30% | C7: Tier 1 | D7: 100 | E7: 10
A8: Health Port/Renewal | B8: 15-30% | C8: Tier 2 | D8: 75 | E8: 7.5
A9: Health Long-Term 2yr | B9: >30% | C9: Tier 1 | D9: 100 | E9: 10
A10: Health Long-Term 3yr | B10: >30% | C10: Tier 1 | D10: 100 | E10: 10
A11: Health Quarterly/HY | B11: <15% | C11: Tier 3 | D11: 50 | E11: 5
A12: MF SIP (Monthly) | B12: <15% | C12: Tier 3 | D12: 50 | E12: 5
A13: MF LS Equity | B13: <15% | C13: Tier 3 | D13: 50 | E13: 5
A14: MF LS Debt | B14: <15% | C14: Tier 3 | D14: 50 | E14: 5
... A21: FP Route (any) | B21: >30% | C21: Tier 1 | D21: 125 | E21: 15
A24: SECTION B: CHANNEL MARGIN RULES
A25: Channel Type | B25: Typical Payout to Channel | C25: Company Margin | D25: RM Credit Basis | E25: Target Multiplier Factor
A26: Direct Sales Team (DST) | B26: 0% | C26: 100% | D26: Full credit per tier | E26: 1.0x (base)
A27: POSP Normal (70/30) | B27: 70% | C27: 30% | D27: 30% of tier credit | E27: 1.0x
A28: POSP Higher Pay (80/20) | B28: 80% | C28: 20% | D28: 20% of tier credit | E28: 1.5x
A29: POSP Very High (90/10) | B29: 90% | C29: 10% | D29: 10% of tier credit | E29: 3.0x
A30: POSP Extreme (95/5) | B30: 95% | C30: 5% | D30: 5% of tier credit | E30: 6.0x
A31: Franchise Sub-broker | B31: 10% | C31: 90% | D31: 90% of tier credit | E31: 0.33x
A32: Digital Platform (80%) | B32: 80% | C32: 20% | D32: 20% of tier credit | E32: 1.5x
A33: NOTE: Target Multiplier Factor = (30% / Company Margin %). Base is 70/30 ratio. If margin shrinks by 50%, target doubles.
A35: SECTION C: INCENTIVE SLABS — DST (DIRECT SALES TEAM)
A36: Achievement % | B36: Rate % | C36: Multiplier | D36: Status
A37: Below 80% | B37: 0 | C37: 0 | D37: No Incentive
A38: 80-100% | B38: 4 | C38: 1 | D38: Base
A39: 101-110% | B39: 5 | C39: 1.25 | D39: Standard
A40: 111-130% | B40: 6 | C40: 1.5 | D40: Enhanced
A41: 131-150% | B41: 7 | C41: 1.75 | D41: Super
A42: 151%+ | B42: 8 | C42: 2 | D42: Champion
A44: SECTION D: INCENTIVE SLABS — POSP/SUB-BROKER RM (70/30 base)
A45: Achievement % | B45: Rate % | C45: Multiplier | D45: Status
A46: Below 80% | B46: 0 | C46: 0 | D46: No Incentive
A47: 80-100% | B47: 1.2 | C47: 1 | D47: Base
A48: 101-110% | B48: 1.5 | C48: 1.25 | D48: Standard
A49: 111-130% | B49: 1.8 | C49: 1.5 | D49: Enhanced
A50: 131-150% | B50: 2.1 | C50: 1.75 | D50: Super
A51: 151%+ | B51: 2 | C51: 2 | D51: Champion
A52: NOTE: For margins other than 70/30: Scale slab rates proportionally. If margin = 20% instead of 30%, multiply rates by (20/30).
A54: SECTION E: NON-DIRECT SALES REFERRAL CREDITS
A55: Product | B55: Condition | C55: Referral Credit %
A56: Life Insurance | B56: Premium credit ≥100% for sales team | C56: 15
A57: Fresh Health Insurance | B57: New policy | C57: 10
A58: Health Port/Renewal Business | B58: Portfolio transfer | C58: 7.5
A59: General Insurance | B59: Based on company earning from product | C59: 5-10
A60: Tier 1 Products (>30% commission) | B60: Any | C60: 10
A61: Tier 2 Products (15-30% commission) | B61: Any | C61: 7.5
A62: Tier 3 Products (<15% commission) | B62: Any | C62: 5

Sheet Trail Income Model
A1: SECTION A: TRAIL CALCULATION PARAMETERS
A2: Base Trail Rate (Self-Sourced, New PAN) | B2: 0.25
A3: Base Trail Rate (Existing Client, Incremental) | B3: 0.15
A4: Sub-broker Trail Factor | B4: 0.3
A5: Management Share (Self-Sourced) | B5: 0.1
A6: Management Share (Assigned + New Biz) | B6: 0.075
A7: Management Share (Assigned + No New Biz) | B7: 0.05
A8: Management Share (Office/Walk-in) | B8: 0.1
A14: SECTION B: INDIVIDUAL TRAIL CALCULATOR
A15: RM Name | B15: Starting AUM (₹) | C15: Current Total AUM (₹) | D15: Incremental AUM (₹) | E15: Client Type | F15: Channel Type | G15: Channel Payout % | H15: Company Margin % | I15: Eligible Trail Rate % | J15: Actual RM Trail % | K15: Annual Trail Income (₹) | L15: Monthly Trail Income (₹) | M15: Mgmt Share % | N15: Mgmt Trail Income (₹)
B16: 0 | C16: 0 | D16: =MAX(C16-B16,0) -> 0 | G16: 0 | H16: =1-G16 -> 1 | I16: =IF(E16="New PAN",$B$2,IF(E16="Existing Client",$B$3,0)) -> 0 | J16: =IF(F16="Direct",I16,IF(F16="Franchise",I16*0.1,I16*H16)) -> 0 | K16: =D16*J16 -> 0 | L16: =K16/12 -> 0 | M16: 0 | N16: =D16*J16*M16 -> 0
B17: 0 | C17: 0 | D17: =MAX(C17-B17,0) -> 0 | G17: 0 | H17: =1-G17 -> 1 | I17: =IF(E17="New PAN",$B$2,IF(E17="Existing Client",$B$3,0)) -> 0 | J17: =IF(F17="Direct",I17,IF(F17="Franchise",I17*0.1,I17*H17)) -> 0 | K17: =D17*J17 -> 0 | L17: =K17/12 -> 0 | M17: 0 | N17: =D17*J17*M17 -> 0
B18: 0 | C18: 0 | D18: =MAX(C18-B18,0) -> 0 | G18: 0 | H18: =1-G18 -> 1 | I18: =IF(E18="New PAN",$B$2,IF(E18="Existing Client",$B$3,0)) -> 0 | J18: =IF(F18="Direct",I18,IF(F18="Franchise",I18*0.1,I18*H18)) -> 0 | K18: =D18*J18 -> 0 | L18: =K18/12 -> 0 | M18: 0 | N18: =D18*J18*M18 -> 0
B19: 0 | C19: 0 | D19: =MAX(C19-B19,0) -> 0 | G19: 0 | H19: =1-G19 -> 1 | I19: =IF(E19="New PAN",$B$2,IF(E19="Existing Client",$B$3,0)) -> 0 | J19: =IF(F19="Direct",I19,IF(F19="Franchise",I19*0.1,I19*H19)) -> 0 | K19: =D19*J19 -> 0 | L19: =K19/12 -> 0 | M19: 0 | N19: =D19*J19*M19 -> 0
B20: 0 | C20: 0 | D20: =MAX(C20-B20,0) -> 0 | G20: 0 | H20: =1-G20 -> 1 | I20: =IF(E20="New PAN",$B$2,IF(E20="Existing Client",$B$3,0)) -> 0 | J20: =IF(F20="Direct",I20,IF(F20="Franchise",I20*0.1,I20*H20)) -> 0 | K20: =D20*J20 -> 0 | L20: =K20/12 -> 0 | M20: 0 | N20: =D20*J20*M20 -> 0
B21: 0 | C21: 0 | D21: =MAX(C21-B21,0) -> 0 | G21: 0 | H21: =1-G21 -> 1 | I21: =IF(E21="New PAN",$B$2,IF(E21="Existing Client",$B$3,0)) -> 0 | J21: =IF(F21="Direct",I21,IF(F21="Franchise",I21*0.1,I21*H21)) -> 0 | K21: =D21*J21 -> 0 | L21: =K21/12 -> 0 | M21: 0 | N21: =D21*J21*M21 -> 0
B22: 0 | C22: 0 | D22: =MAX(C22-B22,0) -> 0 | G22: 0 | H22: =1-G22 -> 1 | I22: =IF(E22="New PAN",$B$2,IF(E22="Existing Client",$B$3,0)) -> 0 | J22: =IF(F22="Direct",I22,IF(F22="Franchise",I22*0.1,I22*H22)) -> 0 | K22: =D22*J22 -> 0 | L22: =K22/12 -> 0 | M22: 0 | N22: =D22*J22*M22 -> 0
B23: 0 | C23: 0 | D23: =MAX(C23-B23,0) -> 0 | G23: 0 | H23: =1-G23 -> 1 | I23: =IF(E23="New PAN",$B$2,IF(E23="Existing Client",$B$3,0)) -> 0 | J23: =IF(F23="Direct",I23,IF(F23="Franchise",I23*0.1,I23*H23)) -> 0 | K23: =D23*J23 -> 0 | L23: =K23/12 -> 0 | M23: 0 | N23: =D23*J23*M23 -> 0
B24: 0 | C24: 0 | D24: =MAX(C24-B24,0) -> 0 | G24: 0 | H24: =1-G24 -> 1 | I24: =IF(E24="New PAN",$B$2,IF(E24="Existing Client",$B$3,0)) -> 0 | J24: =IF(F24="Direct",I24,IF(F24="Franchise",I24*0.1,I24*H24)) -> 0 | K24: =D24*J24 -> 0 | L24: =K24/12 -> 0 | M24: 0 | N24: =D24*J24*M24 -> 0
B25: 0 | C25: 0 | D25: =MAX(C25-B25,0) -> 0 | G25: 0 | H25: =1-G25 -> 1 | I25: =IF(E25="New PAN",$B$2,IF(E25="Existing Client",$B$3,0)) -> 0 | J25: =IF(F25="Direct",I25,IF(F25="Franchise",I25*0.1,I25*H25)) -> 0 | K25: =D25*J25 -> 0 | L25: =K25/12 -> 0 | M25: 0 | N25: =D25*J25*M25 -> 0
B26: 0 | C26: 0 | D26: =MAX(C26-B26,0) -> 0 | G26: 0 | H26: =1-G26 -> 1 | I26: =IF(E26="New PAN",$B$2,IF(E26="Existing Client",$B$3,0)) -> 0 | J26: =IF(F26="Direct",I26,IF(F26="Franchise",I26*0.1,I26*H26)) -> 0 | K26: =D26*J26 -> 0 | L26: =K26/12 -> 0 | M26: 0 | N26: =D26*J26*M26 -> 0
B27: 0 | C27: 0 | D27: =MAX(C27-B27,0) -> 0 | G27: 0 | H27: =1-G27 -> 1 | I27: =IF(E27="New PAN",$B$2,IF(E27="Existing Client",$B$3,0)) -> 0 | J27: =IF(F27="Direct",I27,IF(F27="Franchise",I27*0.1,I27*H27)) -> 0 | K27: =D27*J27 -> 0 | L27: =K27/12 -> 0 | M27: 0 | N27: =D27*J27*M27 -> 0
... B35: 0 | C35: 0 | D35: =MAX(C35-B35,0) -> 0 | G35: 0 | H35: =1-G35 -> 1 | I35: =IF(E35="New PAN",$B$2,IF(E35="Existing Client",$B$3,0)) -> 0 | J35: =IF(F35="Direct",I35,IF(F35="Franchise",I35*0.1,I35*H35)) -> 0 | K35: =D35*J35 -> 0 | L35: =K35/12 -> 0 | M35: 0 | N35: =D35*J35*M35 -> 0

Sheet Channel Margin Calc
A1: CHANNEL MARGIN CALCULATION & TARGET ADJUSTMENT
A2: RM Name | B2: Segment | C2: Base Salary | D2: Channel Type | E2: Avg Channel Payout % | F2: Company Margin % | G2: Base Target (DST=6×, POSP=20×) | H2: Target Multiplier Factor | I2: Adjusted Monthly Target | J2: Applicable Slab Table | K2: Notes
A3: Balbinder Kaur | C3: 0 | D3: Direct | E3: 0 | F3: =1-E3 -> 1 | G3: 0 | H3: =IF(F3=0,1,0.3/F3) -> 0.3 | I3: =G3*H3/12 -> 0 | J3: =IF(D3="Direct","DST Slabs","POSP RM Slabs") -> DST Slabs
A4: Pranab Kumar Barman | C4: 0 | D4: Direct | E4: 0 | F4: =1-E4 -> 1 | G4: 0 | H4: =IF(F4=0,1,0.3/F4) -> 0.3 | I4: =G4*H4/12 -> 0 | J4: =IF(D4="Direct","DST Slabs","POSP RM Slabs") -> DST Slabs
A5: Ajanta Saikia | C5: 0 | D5: Direct | E5: 0 | F5: =1-E5 -> 1 | G5: 0 | H5: =IF(F5=0,1,0.3/F5) -> 0.3 | I5: =G5*H5/12 -> 0 | J5: =IF(D5="Direct","DST Slabs","POSP RM Slabs") -> DST Slabs
A6: Akash Kumar | C6: 0 | D6: Direct | E6: 0 | F6: =1-E6 -> 1 | G6: 0 | H6: =IF(F6=0,1,0.3/F6) -> 0.3 | I6: =G6*H6/12 -> 0 | J6: =IF(D6="Direct","DST Slabs","POSP RM Slabs") -> DST Slabs
A7: Nipa Das | C7: 0 | D7: Direct | E7: 0 | F7: =1-E7 -> 1 | G7: 0 | H7: =IF(F7=0,1,0.3/F7) -> 0.3 | I7: =G7*H7/12 -> 0 | J7: =IF(D7="Direct","DST Slabs","POSP RM Slabs") -> DST Slabs
A8: Jitender Roy | C8: 0 | D8: Direct | E8: 0 | F8: =1-E8 -> 1 | G8: 0 | H8: =IF(F8=0,1,0.3/F8) -> 0.3 | I8: =G8*H8/12 -> 0 | J8: =IF(D8="Direct","DST Slabs","POSP RM Slabs") -> DST Slabs
A9: Rafiqueddin Ahmed | C9: 0 | D9: Direct | E9: 0 | F9: =1-E9 -> 1 | G9: 0 | H9: =IF(F9=0,1,0.3/F9) -> 0.3 | I9: =G9*H9/12 -> 0 | J9: =IF(D9="Direct","DST Slabs","POSP RM Slabs") -> DST Slabs
A10: Pranita Saikia | C10: 0 | D10: Direct | E10: 0 | F10: =1-E10 -> 1 | G10: 0 | H10: =IF(F10=0,1,0.3/F10) -> 0.3 | I10: =G10*H10/12 -> 0 | J10: =IF(D10="Direct","DST Slabs","POSP RM Slabs") -> DST Slabs
A11: Tamanna Kejriwal | C11: 0 | D11: Direct | E11: 0 | F11: =1-E11 -> 1 | G11: 0 | H11: =IF(F11=0,1,0.3/F11) -> 0.3 | I11: =G11*H11/12 -> 0 | J11: =IF(D11="Direct","DST Slabs","POSP RM Slabs") -> DST Slabs
A12: Shivani Kumari | C12: 0 | D12: Direct | E12: 0 | F12: =1-E12 -> 1 | G12: 0 | H12: =IF(F12=0,1,0.3/F12) -> 0.3 | I12: =G12*H12/12 -> 0 | J12: =IF(D12="Direct","DST Slabs","POSP RM Slabs") -> DST Slabs
A13: Rinjima Pathak Das | C13: 0 | D13: Direct | E13: 0 | F13: =1-E13 -> 1 | G13: 0 | H13: =IF(F13=0,1,0.3/F13) -> 0.3 | I13: =G13*H13/12 -> 0 | J13: =IF(D13="Direct","DST Slabs","POSP RM Slabs") -> DST Slabs
A14: Nayanjyoti Handique | C14: 0 | D14: Direct | E14: 0 | F14: =1-E14 -> 1 | G14: 0 | H14: =IF(F14=0,1,0.3/F14) -> 0.3 | I14: =G14*H14/12 -> 0 | J14: =IF(D14="Direct","DST Slabs","POSP RM Slabs") -> DST Slabs
... A22: Raj Das | C22: 0 | D22: Direct | E22: 0 | F22: =1-E22 -> 1 | G22: 0 | H22: =IF(F22=0,1,0.3/F22) -> 0.3 | I22: =G22*H22/12 -> 0 | J22: =IF(D22="Direct","DST Slabs","POSP RM Slabs") -> DST Slabs

Sheet Employee Master
A1: Sl No | B1: Name | C1: Code | D1: DOJ | E1: Designation | F1: Department | G1: Job Responsibility | H1: Gross Salary | I1: Entity | J1: Annual CTC | K1: Tenure Years | L1: Level Code | M1: Target Multiplier | N1: Monthly Target | O1: Annual Target | P1: Cost Recovery Min | Q1: Segment | R1: Target Notes
A2: 1 | B2: Balbinder Kaur | C2: TAS001 | D2: 41334 | E2: Inhouse Sales Manager | F2: OPERATION | G2: SALES | H2: 36017 | I2: TAS | J2: =H2*12 -> 432204 | K2: =YEARFRAC(D2,TODAY(),1) -> 13.077254 | M2: 6 | N2: =H2*M2 -> 216102 | O2: =N2*12 -> 2593224 | P2: =H2*1.6 -> 57627.2 | Q2: Direct | R2: Monthly target = 6× monthly salary
A3: 2 | B3: Pranab Kumar Barman | C3: TAS002 | D3: 41897 | E3: Office Assistant | F3: OPERATION | G3: ADMIN | H3: 21429 | I3: TAS | J3: =H3*12 -> 257148 | K3: =YEARFRAC(D3,TODAY(),1) -> 11.535173 | P3: =H3*1.6 -> 34286.4 | Q3: Support | R3: No sales target
A4: 3 | B4: Ajanta Saikia | C4: TAS003 | D4: 43496 | E4: Field Force Multiplier | F4: LIFE | G4: SALES | H4: 99751 | I4: TIB | J4: =H4*12 -> 1197012 | K4: =YEARFRAC(D4,TODAY(),1) -> 7.156742 | M4: 6 | N4: =H4*M4 -> 598506 | O4: =N4*12 -> 7182072 | P4: =H4*1.6 -> 159601.6 | Q4: Direct | R4: Monthly target = 6× monthly salary
A5: 4 | B5: Akash Kumar | C5: TAS004 | D5: 44075 | E5: Executive | F5: HEALTH | G5: SALES | H5: 22449 | I5: TIB | J5: =H5*12 -> 269388 | K5: =YEARFRAC(D5,TODAY(),1) -> 5.5709816 | M5: 20 | N5: =H5*M5 -> 448980 | O5: =N5*12 -> 5387760 | P5: =H5*1.6 -> 35918.4 | Q5: POSP | R5: Monthly target = 20× monthly salary
A6: 5 | B6: Nipa Das | C6: TAS005 | D6: 44151 | E6: Back Office Executive | F6: OPERATION | G6: Back Office | H6: 22263 | I6: TAS | J6: =H6*12 -> 267156 | K6: =YEARFRAC(D6,TODAY(),1) -> 5.3629253 | P6: =H6*1.6 -> 35620.8 | Q6: Support | R6: No sales target
A7: 6 | B7: Jitender Roy | C7: TAS006 | D7: 44383 | E7: Relationship Manager | F7: HEALTH | G7: SALES | H7: 40440 | I7: TIB | J7: =H7*12 -> 485280 | K7: =YEARFRAC(D7,TODAY(),1) -> 4.7293473 | M7: 20 | N7: =H7*M7 -> 808800 | O7: =N7*12 -> 9705600 | P7: =H7*1.6 -> 64704 | Q7: POSP | R7: Monthly target = 20× monthly salary
A8: 7 | B8: Rafiqueddin Ahmed | C8: TAS051 | D8: 44386 | E8: Mentor | F8: OPERATION | G8: SALES | H8: 30000 | I8: TAS | J8: =H8*12 -> 360000 | K8: =YEARFRAC(D8,TODAY(),1) -> 4.7211319 | M8: 6 | N8: =H8*M8 -> 180000 | O8: =N8*12 -> 2160000 | P8: =H8*1.6 -> 48000 | Q8: Direct | R8: Monthly target = 6× monthly salary
A9: 8 | B9: Pranita Saikia | C9: TAS008 | D9: 44406 | E9: Back Office Executive | F9: G.I. | G9: Back Office | H9: 34500 | I9: TIB | J9: =H9*12 -> 414000 | K9: =YEARFRAC(D9,TODAY(),1) -> 4.6663624 | P9: =H9*1.6 -> 55200 | Q9: Support | R9: No sales target
A10: 9 | B10: Tamanna Kejriwal | C10: TAS009 | D10: 44734 | E10: Sales Head | F10: F.P. | G10: SALES | H10: 90000 | I10: TAS | J10: =H10*12 -> 1080000 | K10: =YEARFRAC(D10,TODAY(),1) -> 3.7677985 | M10: 6 | N10: =H10*M10 -> 540000 | O10: =N10*12 -> 6480000 | P10: =H10*1.6 -> 144000 | Q10: Direct | R10: Monthly target = 6× monthly salary
A11: 10 | B11: Shivani Kumari | C11: TAS013 | D11: 44805 | E11: Back Office Executive | F11: OPERATION | G11: Back Office | H11: 16749 | I11: TAS | J11: =H11*12 -> 200988 | K11: =YEARFRAC(D11,TODAY(),1) -> 3.5733844 | P11: =H11*1.6 -> 26798.4 | Q11: Support | R11: No sales target
A12: 11 | B12: Rinjima Pathak Das | C12: TAS014 | D12: 44929 | E12: HR Manager | F12: ADMIN | G12: HR & ADMIN | H12: 46876 | I12: TIB | J12: =H12*12 -> 562512 | K12: =YEARFRAC(D12,TODAY(),1) -> 3.2334018 | P12: =H12*1.6 -> 75001.6 | Q12: Support | R12: No sales target
A13: 12 | B13: Nayanjyoti Handique | C13: TAS016 | D13: 44977 | E13: Operation Manager | F13: HEALTH | G13: Claims | H13: 29700 | I13: TIB | J13: =H13*12 -> 356400 | K13: =YEARFRAC(D13,TODAY(),1) -> 3.1019849 | P13: =H13*1.6 -> 47520 | Q13: Support | R13: No sales target
A14: 13 | B14: Laxman Sharma | C14: TAS018 | D14: 45078 | E14: Relationship Manager | F14: LIFE | G14: SALES | H14: 43700 | I14: TIB | J14: =H14*12 -> 524400 | K14: =YEARFRAC(D14,TODAY(),1) -> 2.825462 | M14: 20 | N14: =H14*M14 -> 874000 | O14: =N14*12 -> 10488000 | P14: =H14*1.6 -> 69920 | Q14: POSP | R14: Monthly target = 20× monthly salary
A15: 14 | B15: Mayurakshi Goswami | C15: TAS021 | D15: 45202 | E15: Back Office Executive | F15: OPERATION | G15: Back Office | H15: 14858 | I15: TAS | J15: =H15*12 -> 178296 | K15: =YEARFRAC(D15,TODAY(),1) -> 2.4859685 | P15: =H15*1.6 -> 23772.8 | Q15: Support | R15: No sales target
A16: 15 | B16: Bhola Singh | C16: TAS019 | D16: 45204 | E16: Area Manager GI | F16: G.I. | G16: SALES | H16: 103500 | I16: TIB | J16: =H16*12 -> 1242000 | K16: =YEARFRAC(D16,TODAY(),1) -> 2.4804928 | M16: 23 | N16: =H16*M16 -> 2380500 | O16: =N16*12 -> 28566000 | P16: =H16*1.6 -> 165600 | Q16: Area Manager | R16: Monthly target = 20× (salary+15% variable). 15% added for rent/support staff.
A17: 16 | B17: Ranjan Jyoti DC | C17: TAS022 | D17: 45337 | E17: Account Manager | F17: ACCOUNTS | G17: ADMIN | H17: 54000 | I17: TAS | J17: =H17*12 -> 648000 | K17: =YEARFRAC(D17,TODAY(),1) -> 2.1158759 | P17: =H17*1.6 -> 86400 | Q17: Support | R17: No sales target
A18: 17 | B18: Pinki Rani Kalita | C18: TAS027 | D18: 45444 | E18: Back Office Executive | F18: G.I. | G18: Back Office | H18: 15691 | I18: TIB | J18: =H18*12 -> 188292 | K18: =YEARFRAC(D18,TODAY(),1) -> 1.8229927 | P18: =H18*1.6 -> 25105.6 | Q18: Support | R18: No sales target
A19: 18 | B19: Harshita Jalan | C19: TAS032 | D19: 45474 | E19: Back Office Executive | F19: OPERATION | G19: SALES | H19: 18011 | I19: TAS | J19: =H19*12 -> 216132 | K19: =YEARFRAC(D19,TODAY(),1) -> 1.7408759 | M19: 6 | N19: =H19*M19 -> 108066 | O19: =N19*12 -> 1296792 | P19: =H19*1.6 -> 28817.6 | Q19: Direct | R19: Monthly target = 6× monthly salary
A20: 19 | B20: Lucky Pathak | C20: TAS034 | D20: 45474 | E20: Back Office Executive | F20: OPERATION | G20: Back Office | H20: 22449 | I20: TAS | J20: =H20*12 -> 269388 | K20: =YEARFRAC(D20,TODAY(),1) -> 1.7408759 | P20: =H20*1.6 -> 35918.4 | Q20: Support | R20: No sales target
A21: 20 | B21: Raj Das | C21: TAS031 | D21: 45474 | E21: Financial Planner Officer | F21: DEMAT | G21: SALES | H21: 27008 | I21: TAS | J21: =H21*12 -> 324096 | K21: =YEARFRAC(D21,TODAY(),1) -> 1.7408759 | M21: 6 | N21: =H21*M21 -> 162048 | O21: =N21*12 -> 1944576 | P21: =H21*1.6 -> 43212.8 | Q21: Direct | R21: Monthly target = 6× monthly salary
A22: 21 | B22: Vinita Kabra | C22: TAS030 | D22: 45474 | E22: Relationship Manager | F22: F.P. | G22: SALES | H22: 43200 | I22: TIB | J22: =H22*12 -> 518400 | K22: =YEARFRAC(D22,TODAY(),1) -> 1.7408759 | M22: 6 | N22: =H22*M22 -> 259200 | O22: =N22*12 -> 3110400 | P22: =H22*1.6 -> 69120 | Q22: Direct | R22: Monthly target = 6× monthly salary
A23: 22 | B23: Sudeep Kashyap | C23: TAS037 | D23: 45523 | E23: Digital Marketing Exec | F23: DIGITAL & IT | G23: SALES | H23: 28200 | I23: TAS | J23: =H23*12 -> 338400 | K23: =YEARFRAC(D23,TODAY(),1) -> 1.6067518 | M23: 6 | N23: =H23*M23 -> 169200 | O23: =N23*12 -> 2030400 | P23: =H23*1.6 -> 45120 | Q23: Direct | R23: Monthly target = 6× monthly salary
A24: 23 | B24: Jasmine Jain | C24: TAS040 | D24: 45537 | E24: RM & Trainer | F24: F.P. | G24: SALES | H24: 28200 | I24: TAS | J24: =H24*12 -> 338400 | K24: =YEARFRAC(D24,TODAY(),1) -> 1.5684307 | M24: 6 | N24: =H24*M24 -> 169200 | O24: =N24*12 -> 2030400 | P24: =H24*1.6 -> 45120 | Q24: Direct | R24: Monthly target = 6× monthly salary
A25: 24 | B25: Hira Shrestha | C25: TAS047 | D25: 45600 | E25: Back Office Executive | F25: HEALTH | G25: Claims | H25: 23200 | I25: TIB | J25: =H25*12 -> 278400 | K25: =YEARFRAC(D25,TODAY(),1) -> 1.3959854 | P25: =H25*1.6 -> 37120 | Q25: Support | R25: No sales target
A26: 25 | B26: Nisha Koirala | C26: TAS048 | D26: 45600 | E26: Back Office Executive | F26: HEALTH | G26: Claims | H26: 23200 | I26: TIB | J26: =H26*12 -> 278400 | K26: =YEARFRAC(D26,TODAY(),1) -> 1.3959854 | P26: =H26*1.6 -> 37120 | Q26: Support | R26: No sales target
A27: 26 | B27: Preeti Nag | C27: TAS050 | D27: 45601 | E27: Designer & Video Editor | F27: DIGITAL & IT | G27: SALES | H27: 13286 | I27: TAS | J27: =H27*12 -> 159432 | K27: =YEARFRAC(D27,TODAY(),1) -> 1.3932482 | M27: 6 | N27: =H27*M27 -> 79716 | O27: =N27*12 -> 956592 | P27: =H27*1.6 -> 21257.6 | Q27: Direct | R27: Monthly target = 6× monthly salary
A28: 27 | B28: Jinu Lagachu | C28: TAS052 | D28: 45610 | E28: Relationship Manager | F28: F.P. | G28: SALES | H28: 23200 | I28: TAS | J28: =H28*12 -> 278400 | K28: =YEARFRAC(D28,TODAY(),1) -> 1.3686131 | M28: 6 | N28: =H28*M28 -> 139200 | O28: =N28*12 -> 1670400 | P28: =H28*1.6 -> 37120 | Q28: Direct | R28: Monthly target = 6× monthly salary
A29: 28 | B29: Khushbu Chhajer | C29: TAS054 | D29: 45664 | E29: Sales Manager | F29: LIFE | G29: SALES | H29: 38200 | I29: TIB | J29: =H29*12 -> 458400 | K29: =YEARFRAC(D29,TODAY(),1) -> 1.2219178 | M29: 6 | N29: =H29*M29 -> 229200 | O29: =N29*12 -> 2750400 | P29: =H29*1.6 -> 61120 | Q29: Direct | R29: Monthly target = 6× monthly salary
A30: 29 | B30: Aruna Deka | C30: TAS055 | D30: 45719 | E30: Back Office Executive | F30: OPERATION | G30: Back Office | H30: 16600 | I30: TAS | J30: =H30*12 -> 199200 | K30: =YEARFRAC(D30,TODAY(),1) -> 1.0712329 | P30: =H30*1.6 -> 26560 | Q30: Support | R30: No sales target
A31: 30 | B31: Dipankar Das | C31: TAS058 | D31: 45754 | E31: Outbound Team Leader | F31: HEALTH | G31: SALES | H31: 48200 | I31: TIB | J31: =H31*12 -> 578400 | K31: =YEARFRAC(D31,TODAY(),1) -> 0.97534247 | M31: 6 | N31: =H31*M31 -> 289200 | O31: =N31*12 -> 3470400 | P31: =H31*1.6 -> 77120 | Q31: Direct | R31: Monthly target = 6× monthly salary
A32: 31 | B32: Sweety Sarania | C32: TAS061 | D32: 45763 | E32: Back Office Executive | F32: OPERATION | G32: Back Office | H32: 9842 | I32: TIB | J32: =H32*12 -> 118104 | K32: =YEARFRAC(D32,TODAY(),1) -> 0.95068493 | P32: =H32*1.6 -> 15747.2 | Q32: Support | R32: No sales target
A33: 32 | B33: Tanima Das | C33: TAS059 | D33: 45763 | E33: Tele Calling Executive | F33: OPERATION | G33: SALES | H33: 16209 | I33: TIB | J33: =H33*12 -> 194508 | K33: =YEARFRAC(D33,TODAY(),1) -> 0.95068493 | M33: 6 | N33: =H33*M33 -> 97254 | O33: =N33*12 -> 1167048 | P33: =H33*1.6 -> 25934.4 | Q33: Direct | R33: Monthly target = 6× monthly salary
A34: 33 | B34: Mrinmoy Choudhury | C34: TAS063 | D34: 45810 | E34: Regional Team Expansion Mgr | F34: HEALTH | G34: SALES | H34: 95833 | I34: TIB | J34: =H34*12 -> 1149996 | K34: =YEARFRAC(D34,TODAY(),1) -> 0.82191781 | M34: 23 | N34: =H34*M34 -> 2204159 | O34: =N34*12 -> 26449908 | P34: =H34*1.6 -> 153332.8 | Q34: Area Manager | R34: Monthly target = 20× (salary+15% variable). 15% added for rent/support staff.
A35: 34 | B35: Jumma Ara Begum | C35: TAS064 | D35: 45839 | E35: Senior HR Executive | F35: ADMIN | G35: HR & ADMIN | H35: 32451 | I35: TAS | J35: =H35*12 -> 389412 | K35: =YEARFRAC(D35,TODAY(),1) -> 0.74246575 | P35: =H35*1.6 -> 51921.6 | Q35: Support | R35: No sales target
A36: 35 | B36: Banshika Agarwal | C36: TAS067 | D36: 45854 | E36: Relationship Manager | F36: F.P. | G36: SALES | H36: 13507 | I36: TAS | J36: =H36*12 -> 162084 | K36: =YEARFRAC(D36,TODAY(),1) -> 0.70136986 | M36: 6 | N36: =H36*M36 -> 81042 | O36: =N36*12 -> 972504 | P36: =H36*1.6 -> 21611.2 | Q36: Direct | R36: Monthly target = 6× monthly salary
A37: 36 | B37: Wasbir Ahmed | C37: TAS068 | D37: 45854 | E37: Ops & CS Manager | F37: OPERATION | G37: Back Office | H37: 37897 | I37: TAS | J37: =H37*12 -> 454764 | K37: =YEARFRAC(D37,TODAY(),1) -> 0.70136986 | P37: =H37*1.6 -> 60635.2 | Q37: Support | R37: No sales target
A38: 37 | B38: Ajay Singh | C38: TAS077 | D38: 45873 | E38: MIS & POS Handling | F38: OPERATION | G38: MIS | H38: 17600 | I38: TIB | J38: =H38*12 -> 211200 | K38: =YEARFRAC(D38,TODAY(),1) -> 0.64931507 | P38: =H38*1.6 -> 28160 | Q38: Support | R38: No sales target
A39: 38 | B39: Banajit Bezbaruah | C39: TAS074 | D39: 45873 | E39: Asst. Manager | F39: G.I. | G39: SALES | H39: 30363 | I39: TIB | J39: =H39*12 -> 364356 | K39: =YEARFRAC(D39,TODAY(),1) -> 0.64931507 | M39: 6 | N39: =H39*M39 -> 182178 | O39: =N39*12 -> 2186136 | P39: =H39*1.6 -> 48580.8 | Q39: Direct | R39: Monthly target = 6× monthly salary
A40: 39 | B40: Kshetrimayam AK Singh | C40: TAS083 | D40: 45936 | E40: Ass. Branch Manager | F40: HEALTH | G40: SALES | H40: 44035 | I40: TIB | J40: =H40*12 -> 528420 | K40: =YEARFRAC(D40,TODAY(),1) -> 0.47671233 | M40: 20 | N40: =H40*M40 -> 880700 | O40: =N40*12 -> 10568400 | P40: =H40*1.6 -> 70456 | Q40: POSP | R40: Monthly target = 20× monthly salary
A41: 40 | B41: Shoibam Nara Singh | C41: TAS084 | D41: 45936 | E41: Ass. Branch Manager | F41: HEALTH | G41: SALES | H41: 41534 | I41: TIB | J41: =H41*12 -> 498408 | K41: =YEARFRAC(D41,TODAY(),1) -> 0.47671233 | M41: 20 | N41: =H41*M41 -> 830680 | O41: =N41*12 -> 9968160 | P41: =H41*1.6 -> 66454.4 | Q41: POSP | R41: Monthly target = 20× monthly salary
A42: 41 | B42: Tasdiq Ahmed | C42: TAS081 | D42: 45936 | E42: Relationship Manager | F42: F.P. | G42: SALES | H42: 18009 | I42: TAS | J42: =H42*12 -> 216108 | K42: =YEARFRAC(D42,TODAY(),1) -> 0.47671233 | M42: 6 | N42: =H42*M42 -> 108054 | O42: =N42*12 -> 1296648 | P42: =H42*1.6 -> 28814.4 | Q42: Direct | R42: Monthly target = 6× monthly salary
A43: 42 | B43: Hemanta Saharia | C43: TAS086 | D43: 45943 | E43: Channel Development Mgr | F43: OPERATION | G43: SALES | H43: 66117 | I43: TIB | J43: =H43*12 -> 793404 | K43: =YEARFRAC(D43,TODAY(),1) -> 0.45753425 | M43: 20 | N43: =H43*M43 -> 1322340 | O43: =N43*12 -> 15868080 | P43: =H43*1.6 -> 105787.2 | Q43: POSP | R43: Monthly target = 20× monthly salary
A44: 43 | B44: Juntara Patir | C44: TAS087 | D44: 45965 | E44: Intern | F44: DIGITAL & IT | G44: SALES | H44: 6000 | I44: TAS | J44: =H44*12 -> 72000 | K44: =YEARFRAC(D44,TODAY(),1) -> 0.39726027 | M44: 6 | N44: =H44*M44 -> 36000 | O44: =N44*12 -> 432000 | P44: =H44*1.6 -> 9600 | Q44: Direct | R44: Monthly target = 6× monthly salary
A45: 44 | B45: Naushad Hussain | C45: TAS089 | D45: 45971 | E45: Office Assistant | F45: OPERATION | G45: ADMIN | H45: 15000 | I45: TAS | J45: =H45*12 -> 180000 | K45: =YEARFRAC(D45,TODAY(),1) -> 0.38082192 | P45: =H45*1.6 -> 24000 | Q45: Support | R45: No sales target
A46: 45 | B46: Partha Deb Barman | C46: TAS092 | D46: 45978 | E46: Regional Manager | F46: POSP | G46: SALES | H46: 112008 | I46: TIB | J46: =H46*12 -> 1344096 | K46: =YEARFRAC(D46,TODAY(),1) -> 0.36164384 | M46: 20 | N46: =H46*M46 -> 2240160 | O46: =N46*12 -> 26881920 | P46: =H46*1.6 -> 179212.8 | Q46: POSP | R46: Monthly target = 20× monthly salary
A47: 46 | B47: Purnananda Pathak | C47: TAS090 | D47: 45978 | E47: Accounts Executive | F47: ACCOUNTS | G47: ADMIN | H47: 15308 | I47: TAS | J47: =H47*12 -> 183696 | K47: =YEARFRAC(D47,TODAY(),1) -> 0.36164384 | P47: =H47*1.6 -> 24492.8 | Q47: Support | R47: No sales target
A48: 47 | B48: Hirakjyoti Das | C48: TAS093 | D48: 45980 | E48: Sr. Executive MIS | F48: OPERATION | G48: MIS | H48: 32008 | I48: TIB | J48: =H48*12 -> 384096 | K48: =YEARFRAC(D48,TODAY(),1) -> 0.35616438 | P48: =H48*1.6 -> 51212.8 | Q48: Support | R48: No sales target
A49: 48 | B49: Abir Das | C49: - | D49: 45964 | E49: CDO | F49: OPERATION | G49: SALES | H49: 300000 | I49: TIB | J49: =H49*12 -> 3600000 | K49: =YEARFRAC(D49,TODAY(),1) -> 0.4 | N49: =H49*M49 -> 0 | O49: =N49*12 -> 0 | P49: =H49*1.6 -> 480000 | Q49: Senior Mgmt | R49: Profit Center model
A50: 49 | B50: Karismita Deka | C50: TAS095 | D50: 45992 | E50: Client Mgmt Executive | F50: OPERATION | G50: Back Office | H50: 15008 | I50: TAS | J50: =H50*12 -> 180096 | K50: =YEARFRAC(D50,TODAY(),1) -> 0.32328767 | P50: =H50*1.6 -> 24012.8 | Q50: Support | R50: No sales target
A51: 50 | B51: Sudarshana Gupta | C51: TAS094 | D51: 45992 | E51: Relationship Manager | F51: F.P. | G51: SALES | H51: 28200 | I51: TAS | J51: =H51*12 -> 338400 | K51: =YEARFRAC(D51,TODAY(),1) -> 0.32328767 | M51: 6 | N51: =H51*M51 -> 169200 | O51: =N51*12 -> 2030400 | P51: =H51*1.6 -> 45120 | Q51: Direct | R51: Monthly target = 6× monthly salary
A52: 51 | B52: Anikendu Indra | C52: TAS099 | D52: 45992 | E52: Relationship Manager | F52: POSP | G52: SALES | H52: 20427 | I52: TIB | J52: =H52*12 -> 245124 | K52: =YEARFRAC(D52,TODAY(),1) -> 0.32328767 | M52: 20 | N52: =H52*M52 -> 408540 | O52: =N52*12 -> 4902480 | P52: =H52*1.6 -> 32683.2 | Q52: POSP | R52: Monthly target = 20× monthly salary
A53: 52 | B53: Ashis Das | C53: TAS098 | D53: 45992 | E53: Channel Development Mgr | F53: POSP | G53: SALES | H53: 52009 | I53: TIB | J53: =H53*12 -> 624108 | K53: =YEARFRAC(D53,TODAY(),1) -> 0.32328767 | M53: 20 | N53: =H53*M53 -> 1040180 | O53: =N53*12 -> 12482160 | P53: =H53*1.6 -> 83214.4 | Q53: POSP | R53: Monthly target = 20× monthly salary
A54: 53 | B54: Indranil Roy | C54: TAS102 | D54: 45992 | E54: Channel Development Mgr | F54: POSP | G54: SALES | H54: 67008 | I54: TIB | J54: =H54*12 -> 804096 | K54: =YEARFRAC(D54,TODAY(),1) -> 0.32328767 | M54: 20 | N54: =H54*M54 -> 1340160 | O54: =N54*12 -> 16081920 | P54: =H54*1.6 -> 107212.8 | Q54: POSP | R54: Monthly target = 20× monthly salary
A55: 54 | B55: Leena Das | C55: TAS100 | D55: 45992 | E55: Relationship Manager | F55: POSP | G55: SALES | H55: 23980 | I55: TIB | J55: =H55*12 -> 287760 | K55: =YEARFRAC(D55,TODAY(),1) -> 0.32328767 | M55: 20 | N55: =H55*M55 -> 479600 | O55: =N55*12 -> 5755200 | P55: =H55*1.6 -> 38368 | Q55: POSP | R55: Monthly target = 20× monthly salary
A56: 55 | B56: Mousam Majumdar | C56: TAS096 | D56: 45992 | E56: Relationship Manager | F56: POSP | G56: SALES | H56: 67008 | I56: TIB | J56: =H56*12 -> 804096 | K56: =YEARFRAC(D56,TODAY(),1) -> 0.32328767 | M56: 20 | N56: =H56*M56 -> 1340160 | O56: =N56*12 -> 16081920 | P56: =H56*1.6 -> 107212.8 | Q56: POSP | R56: Monthly target = 20× monthly salary
A57: 56 | B57: Shakeeb Aamer | C57: TAS104 | D57: 45992 | E57: Channel Development Mgr | F57: POSP | G57: SALES | H57: 67008 | I57: TIB | J57: =H57*12 -> 804096 | K57: =YEARFRAC(D57,TODAY(),1) -> 0.32328767 | M57: 20 | N57: =H57*M57 -> 1340160 | O57: =N57*12 -> 16081920 | P57: =H57*1.6 -> 107212.8 | Q57: POSP | R57: Monthly target = 20× monthly salary
A58: 57 | B58: Sukanta Das | C58: TAS101 | D58: 45992 | E58: Relationship Manager | F58: POSP | G58: SALES | H58: 22429 | I58: TIB | J58: =H58*12 -> 269148 | K58: =YEARFRAC(D58,TODAY(),1) -> 0.32328767 | M58: 20 | N58: =H58*M58 -> 448580 | O58: =N58*12 -> 5382960 | P58: =H58*1.6 -> 35886.4 | Q58: POSP | R58: Monthly target = 20× monthly salary
A59: 58 | B59: Kabita Goswami | C59: TAS105 | D59: 45999 | E59: Relationship Manager | F59: OPERATION | G59: SALES | H59: 41008 | I59: TIB | J59: =H59*12 -> 492096 | K59: =YEARFRAC(D59,TODAY(),1) -> 0.30410959 | M59: 6 | N59: =H59*M59 -> 246048 | O59: =N59*12 -> 2952576 | P59: =H59*1.6 -> 65612.8 | Q59: Direct | R59: Monthly target = 6× monthly salary
A60: 59 | B60: Housekeeping (Vendor) | C60: - | E60: Outsourced | F60: ADMIN | G60: Support | H60: 12000 | I60: Vendor | J60: =H60*12 -> 144000 | P60: =H60*1.6 -> 19200 | Q60: Support | R60: No sales target
A61: 60 | B61: Security (Vendor) | C61: - | E61: Outsourced | F61: ADMIN | G61: Support | H61: 15000 | I61: Vendor | J61: =H61*12 -> 180000 | P61: =H61*1.6 -> 24000 | Q61: Support | R61: No sales target
A62: 61 | B62: Office Boy (Vendor) | C62: - | E62: Outsourced | F62: ADMIN | G62: Support | H62: 10000 | I62: Vendor | J62: =H62*12 -> 120000 | P62: =H62*1.6 -> 16000 | Q62: Support | R62: No sales target

Sheet Product Credit Rules
A1: SECTION A: MUTUAL FUND CREDITS
A2: Product | B2: Credit % | C2: Notes
A3: MF SIP (Monthly Business) | B3: 100 | C3: 100% of that month's SIP collection only. NO annualization. Clawback if SIP stopped/redeemed. | D3: RETENTION RULE
A4: MF Lumpsum - Equity | B4: 10 | C4: Low margin on lumpsum equity
A5: MF Lumpsum - Long Term Debt | B5: 7.5 | C5: Medium-term debt funds
A6: MF Lumpsum - Short Term Debt | B6: 5 | C6: Low-margin liquid/ultra-short
A7: MF Debt→Equity via STP Route | B7: 10 | C7: Same as equity LS since converting
A8: FP Route Client SIP | B8: 125 | C8: BONUS: Full FP done + investment data
A9: FP Route Client Health | B9: 125 | C9: BONUS: FP validation required
A10: FP Route Client Term Life | B10: 125 | C10: BONUS: FP validation required
A11: POSP Business (Normal Grade) | B11: 30 | C11: Standard POSP credit
A12: POSP Business (Higher Pay Grade) | B12: 0 | C12: Lower % proportionate to POSP payout
A13: Franchise Business | B13: 15 | C13: Lower margin franchise model
A14: Directors' Business Credit | B14: 30 | C14: Business from Ram/Sangita Shah
A15: NOTE: FP Route 125% requires (1) Complete FP data (2) Maker-Checker verification
A16: SIP CLAWBACK: If any SIP is stopped or redeemed, the amount gets DEBITED from that month's business credit. | C16: Anti-misselling & retention tool. Discourages start-stop behavior.
A17: SECTION B: LIFE INSURANCE CREDITS
A18: Product | B18: Credit %
A19: Life - Regular Pay 10 Years+ | B19: 125
A20: Life - Regular Pay Below 10 Years | B20: 100
A21: Life - ULIP Regular Pay | B21: 25
A22: Life - Single Premium | B22: 10
A24: SECTION C: HEALTH INSURANCE CREDITS
A25: SECTION G: INCENTIVE SLABS — DIRECT SALES TEAM (DST) | B25: Credit % | C25: Formula
A26: Achievement % | B26: Rate % | C26: Multiplier | D26: Status
A27: Below 80% | B27: 0 | C27: 0 | D27: No Incentive
A28: 80-100% | B28: 4 | C28: 1 | D28: Base
A29: 101-110% | B29: 5 | C29: 1.25 | D29: Standard
A30: 111-130% | B30: 6 | C30: 1.5 | D30: Enhanced
A31: 131-150% | B31: 7 | C31: 1.75 | D31: Super
A32: 151%+ | B32: 8 | C32: 2 | D32: Champion
A33: Category | B33: Sub-Category | C33: Credit % | D33: Notes
A34: SECTION H: INCENTIVE SLABS — POSP/SUB-BROKER RM (70/30 base) | B34: Pvt Car | C34: Grid-Based | D34: Varies by insurer grid
A35: Achievement % | B35: Rate % | C35: Multiplier | D35: Status
A36: Below 80% | B36: 0 | C36: 0 | D36: No Incentive
A37: 80-100% | B37: 1.2 | C37: 1 | D37: Base
A38: 101-110% | B38: 1.5 | C38: 1.25 | D38: Standard
A39: 111-130% | B39: 1.8 | C39: 1.5 | D39: Enhanced
A40: 131-150% | B40: 2.1 | C40: 1.75 | D40: Super
A41: 151%+ | B41: 2 | C41: 2 | D41: Champion
A42: NOTE: For margins other than 30%: Scale slab rates by (actual margin/30%). If margin = 20%, multiply DST rates by 20/30. | B42: Liability | C42: 100 | D42: Standard
A43: GMC/GPA | B43: Corporate | C43: 20 | D43: High volume, thin margin
A44: GI Renewal | B44: All Products | C44: 33 | D44: One-third credit for retention
A46: Motor OD/TP splits captured from insurer GRIDs (Shriram, Tata, ICICI, SBI)
A47: TP Only PSU = Non-preferred (not counted for POSP activation)
A49: SECTION E: POSP/SUB-BROKER CREDIT RULES FOR RM/CDM
A50: Scenario | B50: Credit
A51: RM/CDM Self Business (own sourced) | B51: 300%
A52: POSP Normal Grade Business | B52: 30%
A53: POSP Higher Pay Grade Business | B53: Proportionately less
A54: Franchise Business | B54: 15%
A55: Renewal Retention Requirement | B55: >80% to earn incentives
A57: SECTION F: TRAIL SHARING RATES
A58: Source Type | B58: RM Share % | C58: Management Share % | D58: Company Share %
A59: Self-Sourced | B59: 25 | C59: 10 | D59: 65
A60: Assigned + New Business | B60: 15 | C60: 7.5 | D60: 77.5
A61: Assigned + No New Business | B61: 0 | C61: 5 | D61: 95
A62: Office/Walk-in | B62: 10 | C62: 10 | D62: 80
A64: SECTION G: INCENTIVE ACCELERATOR SLABS
A65: Achievement % | B65: Rate % | C65: Multiplier | D65: Status
A66: Below 80% | B66: 0 | C66: 0 | D66: No Incentive
A67: 80-100% | B67: 4 | C67: 1 | D67: Base
A68: 101-110% | B68: 4 | C68: 1 | D68: Standard
A69: 111-130% | B69: 4.6 | C69: 1.15 | D69: Enhanced
A70: 131-150% | B70: 5 | C70: 1.25 | D70: Super
A71: 150%+ | B71: 6 | C71: 1.5 | D71: Champion

Sheet Monthly Incentive Calc
A1: Sl No | B1: Name | C1: Salary | D1: Monthly Target | E1: Month | F1: Life Ins New Biz | G1: Health Ins New Biz | H1: Health Pay Type | I1: GI Motor Pvt Car | J1: GI Motor CV | K1: GI Motor TP Only | L1: GI Non-Motor | M1: GI GMC/GPA | N1: MF SIP Monthly | O1: MF LS Equity | P1: MF LS LT Debt | Q1: MF LS ST Debt | R1: MF STP Debt→Equity | S1: POSP Channel Biz | T1: Franchise Biz | U1: FP Route? | V1: Renewal Retention % | W1: Weighted Business | X1: Achievement % | Y1: Slab | Z1: Incentive Rate | AA1: Incentive Amount | AB1: Total Earning | AC1: Cost Justified | AD1: Performance Status | AE1: SIP Clawback Debit | AF1: Motor Biz Slab Rate | AG1: Channel Payout % | AH1: Company Margin % | AI1: Margin Credit Factor | AJ1: Applicable Slab
A2: 1 | B2: Balbinder Kaur | C2: ='Employee Master'!H2 -> 36017 | D2: ='Employee Master'!N2 -> 216102 | W2: =((IF(U2="Yes",F2*1.25,F2)+IF(U2="Yes",IF(H2="Annual",G2,IF(H2="2-Year",G2/2*1.25,IF(H2="3-Year",G2/3*1.5,IF(H2="Quarterly/HY",G2*0.5,G2))))*1.25,IF(H2="Annual",G2,IF(H2="2-Year",G2/2*1.25,IF(H2="3-Year",G2/3*1.5,IF(H2="Quarterly/HY",G2*0.5,G2)))))+(I2+J2+K2)+(L2+M2*0.2)+IF(U2="Yes",(N2-AE2)*1.25,(N2-AE2))+(O2*0.1+P2*0.075+Q2*0.05+R2*0.1)+(S2*0.3+T2*0.15)))*AI2 -> 0 | X2: =IF(D2=0,0,W2/D2) -> 0 | Y2: =IF(X2<0.8,"Below 80%",IF(X2<=1,"80-100%",IF(X2<=1.1,"101-110%",IF(X2<=1.3,"111-130%",IF(X2<=1.5,"131-150%","150%+"))))) -> Below 80% | Z2: =IF(AJ2="DST",IF(X2<0.8,0,IF(X2<=1,0.04,IF(X2<=1.1,0.05,IF(X2<=1.3,0.06,IF(X2<=1.5,0.07,0.08))))),IF(X2<0.8,0,IF(X2<=1,0.012,IF(X2<=1.1,0.015,IF(X2<=1.3,0.018,IF(X2<=1.5,0.021,0.02)))))) -> 0 | AA2: =W2*Z2 -> 0 | AB2: =C2+AA2 -> 36017 | AC2: =IF(W2>='Employee Master'!P2,"YES","NO") -> NO | AD2: =IF(X2>=1.3,"Star",IF(X2>=1,"High",IF(X2>=0.8,"Meets",IF(X2>=0.6,"Below","Non-Performer")))) -> Non-Performer | AE2: 0 | AF2: =IF((I2+J2+K2)=0,0,IF((I2+J2+K2)<=300000,0.015,IF((I2+J2+K2)<=500000,0.02,0.03))) -> 0 | AG2: 0 | AH2: =1-AG2 -> 1 | AI2: =IF(AH2>=1,1,AH2) -> 1 | AJ2: =IF(AG2=0,"DST","POSP RM") -> DST
A3: 2 | B3: Ajanta Saikia | C3: ='Employee Master'!H4 -> 99751 | D3: ='Employee Master'!N4 -> 598506 | W3: =((IF(U3="Yes",F3*1.25,F3)+IF(U3="Yes",IF(H3="Annual",G3,IF(H3="2-Year",G3/2*1.25,IF(H3="3-Year",G3/3*1.5,IF(H3="Quarterly/HY",G3*0.5,G3))))*1.25,IF(H3="Annual",G3,IF(H3="2-Year",G3/2*1.25,IF(H3="3-Year",G3/3*1.5,IF(H3="Quarterly/HY",G3*0.5,G3)))))+(I3+J3+K3)+(L3+M3*0.2)+IF(U3="Yes",(N3-AE3)*1.25,(N3-AE3))+(O3*0.1+P3*0.075+Q3*0.05+R3*0.1)+(S3*0.3+T3*0.15)))*AI3 -> 0 | X3: =IF(D3=0,0,W3/D3) -> 0 | Y3: =IF(X3<0.8,"Below 80%",IF(X3<=1,"80-100%",IF(X3<=1.1,"101-110%",IF(X3<=1.3,"111-130%",IF(X3<=1.5,"131-150%","150%+"))))) -> Below 80% | Z3: =IF(AJ3="DST",IF(X3<0.8,0,IF(X3<=1,0.04,IF(X3<=1.1,0.05,IF(X3<=1.3,0.06,IF(X3<=1.5,0.07,0.08))))),IF(X3<0.8,0,IF(X3<=1,0.012,IF(X3<=1.1,0.015,IF(X3<=1.3,0.018,IF(X3<=1.5,0.021,0.02)))))) -> 0 | AA3: =W3*Z3 -> 0 | AB3: =C3+AA3 -> 99751 | AC3: =IF(W3>='Employee Master'!P4,"YES","NO") -> NO | AD3: =IF(X3>=1.3,"Star",IF(X3>=1,"High",IF(X3>=0.8,"Meets",IF(X3>=0.6,"Below","Non-Performer")))) -> Non-Performer | AE3: 0 | AF3: =IF((I3+J3+K3)=0,0,IF((I3+J3+K3)<=300000,0.015,IF((I3+J3+K3)<=500000,0.02,0.03))) -> 0 | AG3: 0 | AH3: =1-AG3 -> 1 | AI3: =IF(AH3>=1,1,AH3) -> 1 | AJ3: =IF(AG3=0,"DST","POSP RM") -> DST
A4: 3 | B4: Akash Kumar | C4: ='Employee Master'!H5 -> 22449 | D4: ='Employee Master'!N5 -> 448980 | W4: =((IF(U4="Yes",F4*1.25,F4)+IF(U4="Yes",IF(H4="Annual",G4,IF(H4="2-Year",G4/2*1.25,IF(H4="3-Year",G4/3*1.5,IF(H4="Quarterly/HY",G4*0.5,G4))))*1.25,IF(H4="Annual",G4,IF(H4="2-Year",G4/2*1.25,IF(H4="3-Year",G4/3*1.5,IF(H4="Quarterly/HY",G4*0.5,G4)))))+(I4+J4+K4)+(L4+M4*0.2)+IF(U4="Yes",(N4-AE4)*1.25,(N4-AE4))+(O4*0.1+P4*0.075+Q4*0.05+R4*0.1)+(S4*0.3+T4*0.15)))*AI4 -> 0 | X4: =IF(D4=0,0,W4/D4) -> 0 | Y4: =IF(X4<0.8,"Below 80%",IF(X4<=1,"80-100%",IF(X4<=1.1,"101-110%",IF(X4<=1.3,"111-130%",IF(X4<=1.5,"131-150%","150%+"))))) -> Below 80% | Z4: =IF(AJ4="DST",IF(X4<0.8,0,IF(X4<=1,0.04,IF(X4<=1.1,0.05,IF(X4<=1.3,0.06,IF(X4<=1.5,0.07,0.08))))),IF(X4<0.8,0,IF(X4<=1,0.012,IF(X4<=1.1,0.015,IF(X4<=1.3,0.018,IF(X4<=1.5,0.021,0.02)))))) -> 0 | AA4: =W4*Z4 -> 0 | AB4: =C4+AA4 -> 22449 | AC4: =IF(W4>='Employee Master'!P5,"YES","NO") -> NO | AD4: =IF(X4>=1.3,"Star",IF(X4>=1,"High",IF(X4>=0.8,"Meets",IF(X4>=0.6,"Below","Non-Performer")))) -> Non-Performer | AE4: 0 | AF4: =IF((I4+J4+K4)=0,0,IF((I4+J4+K4)<=300000,0.015,IF((I4+J4+K4)<=500000,0.02,0.03))) -> 0 | AG4: 0 | AH4: =1-AG4 -> 1 | AI4: =IF(AH4>=1,1,AH4) -> 1 | AJ4: =IF(AG4=0,"DST","POSP RM") -> DST
A5: 4 | B5: Jitender Roy | C5: ='Employee Master'!H7 -> 40440 | D5: ='Employee Master'!N7 -> 808800 | W5: =((IF(U5="Yes",F5*1.25,F5)+IF(U5="Yes",IF(H5="Annual",G5,IF(H5="2-Year",G5/2*1.25,IF(H5="3-Year",G5/3*1.5,IF(H5="Quarterly/HY",G5*0.5,G5))))*1.25,IF(H5="Annual",G5,IF(H5="2-Year",G5/2*1.25,IF(H5="3-Year",G5/3*1.5,IF(H5="Quarterly/HY",G5*0.5,G5)))))+(I5+J5+K5)+(L5+M5*0.2)+IF(U5="Yes",(N5-AE5)*1.25,(N5-AE5))+(O5*0.1+P5*0.075+Q5*0.05+R5*0.1)+(S5*0.3+T5*0.15)))*AI5 -> 0 | X5: =IF(D5=0,0,W5/D5) -> 0 | Y5: =IF(X5<0.8,"Below 80%",IF(X5<=1,"80-100%",IF(X5<=1.1,"101-110%",IF(X5<=1.3,"111-130%",IF(X5<=1.5,"131-150%","150%+"))))) -> Below 80% | Z5: =IF(AJ5="DST",IF(X5<0.8,0,IF(X5<=1,0.04,IF(X5<=1.1,0.05,IF(X5<=1.3,0.06,IF(X5<=1.5,0.07,0.08))))),IF(X5<0.8,0,IF(X5<=1,0.012,IF(X5<=1.1,0.015,IF(X5<=1.3,0.018,IF(X5<=1.5,0.021,0.02)))))) -> 0 | AA5: =W5*Z5 -> 0 | AB5: =C5+AA5 -> 40440 | AC5: =IF(W5>='Employee Master'!P7,"YES","NO") -> NO | AD5: =IF(X5>=1.3,"Star",IF(X5>=1,"High",IF(X5>=0.8,"Meets",IF(X5>=0.6,"Below","Non-Performer")))) -> Non-Performer | AE5: 0 | AF5: =IF((I5+J5+K5)=0,0,IF((I5+J5+K5)<=300000,0.015,IF((I5+J5+K5)<=500000,0.02,0.03))) -> 0 | AG5: 0 | AH5: =1-AG5 -> 1 | AI5: =IF(AH5>=1,1,AH5) -> 1 | AJ5: =IF(AG5=0,"DST","POSP RM") -> DST
A6: 5 | B6: Rafiqueddin Ahmed | C6: ='Employee Master'!H8 -> 30000 | D6: ='Employee Master'!N8 -> 180000 | W6: =((IF(U6="Yes",F6*1.25,F6)+IF(U6="Yes",IF(H6="Annual",G6,IF(H6="2-Year",G6/2*1.25,IF(H6="3-Year",G6/3*1.5,IF(H6="Quarterly/HY",G6*0.5,G6))))*1.25,IF(H6="Annual",G6,IF(H6="2-Year",G6/2*1.25,IF(H6="3-Year",G6/3*1.5,IF(H6="Quarterly/HY",G6*0.5,G6)))))+(I6+J6+K6)+(L6+M6*0.2)+IF(U6="Yes",(N6-AE6)*1.25,(N6-AE6))+(O6*0.1+P6*0.075+Q6*0.05+R6*0.1)+(S6*0.3+T6*0.15)))*AI6 -> 0 | X6: =IF(D6=0,0,W6/D6) -> 0 | Y6: =IF(X6<0.8,"Below 80%",IF(X6<=1,"80-100%",IF(X6<=1.1,"101-110%",IF(X6<=1.3,"111-130%",IF(X6<=1.5,"131-150%","150%+"))))) -> Below 80% | Z6: =IF(AJ6="DST",IF(X6<0.8,0,IF(X6<=1,0.04,IF(X6<=1.1,0.05,IF(X6<=1.3,0.06,IF(X6<=1.5,0.07,0.08))))),IF(X6<0.8,0,IF(X6<=1,0.012,IF(X6<=1.1,0.015,IF(X6<=1.3,0.018,IF(X6<=1.5,0.021,0.02)))))) -> 0 | AA6: =W6*Z6 -> 0 | AB6: =C6+AA6 -> 30000 | AC6: =IF(W6>='Employee Master'!P8,"YES","NO") -> NO | AD6: =IF(X6>=1.3,"Star",IF(X6>=1,"High",IF(X6>=0.8,"Meets",IF(X6>=0.6,"Below","Non-Performer")))) -> Non-Performer | AE6: 0 | AF6: =IF((I6+J6+K6)=0,0,IF((I6+J6+K6)<=300000,0.015,IF((I6+J6+K6)<=500000,0.02,0.03))) -> 0 | AG6: 0 | AH6: =1-AG6 -> 1 | AI6: =IF(AH6>=1,1,AH6) -> 1 | AJ6: =IF(AG6=0,"DST","POSP RM") -> DST
A7: 6 | B7: Tamanna Kejriwal | C7: ='Employee Master'!H10 -> 90000 | D7: ='Employee Master'!N10 -> 540000 | W7: =((IF(U7="Yes",F7*1.25,F7)+IF(U7="Yes",IF(H7="Annual",G7,IF(H7="2-Year",G7/2*1.25,IF(H7="3-Year",G7/3*1.5,IF(H7="Quarterly/HY",G7*0.5,G7))))*1.25,IF(H7="Annual",G7,IF(H7="2-Year",G7/2*1.25,IF(H7="3-Year",G7/3*1.5,IF(H7="Quarterly/HY",G7*0.5,G7)))))+(I7+J7+K7)+(L7+M7*0.2)+IF(U7="Yes",(N7-AE7)*1.25,(N7-AE7))+(O7*0.1+P7*0.075+Q7*0.05+R7*0.1)+(S7*0.3+T7*0.15)))*AI7 -> 0 | X7: =IF(D7=0,0,W7/D7) -> 0 | Y7: =IF(X7<0.8,"Below 80%",IF(X7<=1,"80-100%",IF(X7<=1.1,"101-110%",IF(X7<=1.3,"111-130%",IF(X7<=1.5,"131-150%","150%+"))))) -> Below 80% | Z7: =IF(AJ7="DST",IF(X7<0.8,0,IF(X7<=1,0.04,IF(X7<=1.1,0.05,IF(X7<=1.3,0.06,IF(X7<=1.5,0.07,0.08))))),IF(X7<0.8,0,IF(X7<=1,0.012,IF(X7<=1.1,0.015,IF(X7<=1.3,0.018,IF(X7<=1.5,0.021,0.02)))))) -> 0 | AA7: =W7*Z7 -> 0 | AB7: =C7+AA7 -> 90000 | AC7: =IF(W7>='Employee Master'!P10,"YES","NO") -> NO | AD7: =IF(X7>=1.3,"Star",IF(X7>=1,"High",IF(X7>=0.8,"Meets",IF(X7>=0.6,"Below","Non-Performer")))) -> Non-Performer | AE7: 0 | AF7: =IF((I7+J7+K7)=0,0,IF((I7+J7+K7)<=300000,0.015,IF((I7+J7+K7)<=500000,0.02,0.03))) -> 0 | AG7: 0 | AH7: =1-AG7 -> 1 | AI7: =IF(AH7>=1,1,AH7) -> 1 | AJ7: =IF(AG7=0,"DST","POSP RM") -> DST
A8: 7 | B8: Laxman Sharma | C8: ='Employee Master'!H14 -> 43700 | D8: ='Employee Master'!N14 -> 874000 | W8: =((IF(U8="Yes",F8*1.25,F8)+IF(U8="Yes",IF(H8="Annual",G8,IF(H8="2-Year",G8/2*1.25,IF(H8="3-Year",G8/3*1.5,IF(H8="Quarterly/HY",G8*0.5,G8))))*1.25,IF(H8="Annual",G8,IF(H8="2-Year",G8/2*1.25,IF(H8="3-Year",G8/3*1.5,IF(H8="Quarterly/HY",G8*0.5,G8)))))+(I8+J8+K8)+(L8+M8*0.2)+IF(U8="Yes",(N8-AE8)*1.25,(N8-AE8))+(O8*0.1+P8*0.075+Q8*0.05+R8*0.1)+(S8*0.3+T8*0.15)))*AI8 -> 0 | X8: =IF(D8=0,0,W8/D8) -> 0 | Y8: =IF(X8<0.8,"Below 80%",IF(X8<=1,"80-100%",IF(X8<=1.1,"101-110%",IF(X8<=1.3,"111-130%",IF(X8<=1.5,"131-150%","150%+"))))) -> Below 80% | Z8: =IF(AJ8="DST",IF(X8<0.8,0,IF(X8<=1,0.04,IF(X8<=1.1,0.05,IF(X8<=1.3,0.06,IF(X8<=1.5,0.07,0.08))))),IF(X8<0.8,0,IF(X8<=1,0.012,IF(X8<=1.1,0.015,IF(X8<=1.3,0.018,IF(X8<=1.5,0.021,0.02)))))) -> 0 | AA8: =W8*Z8 -> 0 | AB8: =C8+AA8 -> 43700 | AC8: =IF(W8>='Employee Master'!P14,"YES","NO") -> NO | AD8: =IF(X8>=1.3,"Star",IF(X8>=1,"High",IF(X8>=0.8,"Meets",IF(X8>=0.6,"Below","Non-Performer")))) -> Non-Performer | AE8: 0 | AF8: =IF((I8+J8+K8)=0,0,IF((I8+J8+K8)<=300000,0.015,IF((I8+J8+K8)<=500000,0.02,0.03))) -> 0 | AG8: 0 | AH8: =1-AG8 -> 1 | AI8: =IF(AH8>=1,1,AH8) -> 1 | AJ8: =IF(AG8=0,"DST","POSP RM") -> DST
A9: 8 | B9: Bhola Singh | C9: ='Employee Master'!H16 -> 103500 | D9: ='Employee Master'!N16 -> 2380500 | W9: =((IF(U9="Yes",F9*1.25,F9)+IF(U9="Yes",IF(H9="Annual",G9,IF(H9="2-Year",G9/2*1.25,IF(H9="3-Year",G9/3*1.5,IF(H9="Quarterly/HY",G9*0.5,G9))))*1.25,IF(H9="Annual",G9,IF(H9="2-Year",G9/2*1.25,IF(H9="3-Year",G9/3*1.5,IF(H9="Quarterly/HY",G9*0.5,G9)))))+(I9+J9+K9)+(L9+M9*0.2)+IF(U9="Yes",(N9-AE9)*1.25,(N9-AE9))+(O9*0.1+P9*0.075+Q9*0.05+R9*0.1)+(S9*0.3+T9*0.15)))*AI9 -> 0 | X9: =IF(D9=0,0,W9/D9) -> 0 | Y9: =IF(X9<0.8,"Below 80%",IF(X9<=1,"80-100%",IF(X9<=1.1,"101-110%",IF(X9<=1.3,"111-130%",IF(X9<=1.5,"131-150%","150%+"))))) -> Below 80% | Z9: =IF(AJ9="DST",IF(X9<0.8,0,IF(X9<=1,0.04,IF(X9<=1.1,0.05,IF(X9<=1.3,0.06,IF(X9<=1.5,0.07,0.08))))),IF(X9<0.8,0,IF(X9<=1,0.012,IF(X9<=1.1,0.015,IF(X9<=1.3,0.018,IF(X9<=1.5,0.021,0.02)))))) -> 0 | AA9: =W9*Z9 -> 0 | AB9: =C9+AA9 -> 103500 | AC9: =IF(W9>='Employee Master'!P16,"YES","NO") -> NO | AD9: =IF(X9>=1.3,"Star",IF(X9>=1,"High",IF(X9>=0.8,"Meets",IF(X9>=0.6,"Below","Non-Performer")))) -> Non-Performer | AE9: 0 | AF9: =IF((I9+J9+K9)=0,0,IF((I9+J9+K9)<=300000,0.015,IF((I9+J9+K9)<=500000,0.02,0.03))) -> 0 | AG9: 0 | AH9: =1-AG9 -> 1 | AI9: =IF(AH9>=1,1,AH9) -> 1 | AJ9: =IF(AG9=0,"DST","POSP RM") -> DST
A10: 9 | B10: Harshita Jalan | C10: ='Employee Master'!H19 -> 18011 | D10: ='Employee Master'!N19 -> 108066 | W10: =((IF(U10="Yes",F10*1.25,F10)+IF(U10="Yes",IF(H10="Annual",G10,IF(H10="2-Year",G10/2*1.25,IF(H10="3-Year",G10/3*1.5,IF(H10="Quarterly/HY",G10*0.5,G10))))*1.25,IF(H10="Annual",G10,IF(H10="2-Year",G10/2*1.25,IF(H10="3-Year",G10/3*1.5,IF(H10="Quarterly/HY",G10*0.5,G10)))))+(I10+J10+K10)+(L10+M10*0.2)+IF(U10="Yes",(N10-AE10)*1.25,(N10-AE10))+(O10*0.1+P10*0.075+Q10*0.05+R10*0.1)+(S10*0.3+T10*0.15)))*AI10 -> 0 | X10: =IF(D10=0,0,W10/D10) -> 0 | Y10: =IF(X10<0.8,"Below 80%",IF(X10<=1,"80-100%",IF(X10<=1.1,"101-110%",IF(X10<=1.3,"111-130%",IF(X10<=1.5,"131-150%","150%+"))))) -> Below 80% | Z10: =IF(AJ10="DST",IF(X10<0.8,0,IF(X10<=1,0.04,IF(X10<=1.1,0.05,IF(X10<=1.3,0.06,IF(X10<=1.5,0.07,0.08))))),IF(X10<0.8,0,IF(X10<=1,0.012,IF(X10<=1.1,0.015,IF(X10<=1.3,0.018,IF(X10<=1.5,0.021,0.02)))))) -> 0 | AA10: =W10*Z10 -> 0 | AB10: =C10+AA10 -> 18011 | AC10: =IF(W10>='Employee Master'!P19,"YES","NO") -> NO | AD10: =IF(X10>=1.3,"Star",IF(X10>=1,"High",IF(X10>=0.8,"Meets",IF(X10>=0.6,"Below","Non-Performer")))) -> Non-Performer | AE10: 0 | AF10: =IF((I10+J10+K10)=0,0,IF((I10+J10+K10)<=300000,0.015,IF((I10+J10+K10)<=500000,0.02,0.03))) -> 0 | AG10: 0 | AH10: =1-AG10 -> 1 | AI10: =IF(AH10>=1,1,AH10) -> 1 | AJ10: =IF(AG10=0,"DST","POSP RM") -> DST
A11: 10 | B11: Raj Das | C11: ='Employee Master'!H21 -> 27008 | D11: ='Employee Master'!N21 -> 162048 | W11: =((IF(U11="Yes",F11*1.25,F11)+IF(U11="Yes",IF(H11="Annual",G11,IF(H11="2-Year",G11/2*1.25,IF(H11="3-Year",G11/3*1.5,IF(H11="Quarterly/HY",G11*0.5,G11))))*1.25,IF(H11="Annual",G11,IF(H11="2-Year",G11/2*1.25,IF(H11="3-Year",G11/3*1.5,IF(H11="Quarterly/HY",G11*0.5,G11)))))+(I11+J11+K11)+(L11+M11*0.2)+IF(U11="Yes",(N11-AE11)*1.25,(N11-AE11))+(O11*0.1+P11*0.075+Q11*0.05+R11*0.1)+(S11*0.3+T11*0.15)))*AI11 -> 0 | X11: =IF(D11=0,0,W11/D11) -> 0 | Y11: =IF(X11<0.8,"Below 80%",IF(X11<=1,"80-100%",IF(X11<=1.1,"101-110%",IF(X11<=1.3,"111-130%",IF(X11<=1.5,"131-150%","150%+"))))) -> Below 80% | Z11: =IF(AJ11="DST",IF(X11<0.8,0,IF(X11<=1,0.04,IF(X11<=1.1,0.05,IF(X11<=1.3,0.06,IF(X11<=1.5,0.07,0.08))))),IF(X11<0.8,0,IF(X11<=1,0.012,IF(X11<=1.1,0.015,IF(X11<=1.3,0.018,IF(X11<=1.5,0.021,0.02)))))) -> 0 | AA11: =W11*Z11 -> 0 | AB11: =C11+AA11 -> 27008 | AC11: =IF(W11>='Employee Master'!P21,"YES","NO") -> NO | AD11: =IF(X11>=1.3,"Star",IF(X11>=1,"High",IF(X11>=0.8,"Meets",IF(X11>=0.6,"Below","Non-Performer")))) -> Non-Performer | AE11: 0 | AF11: =IF((I11+J11+K11)=0,0,IF((I11+J11+K11)<=300000,0.015,IF((I11+J11+K11)<=500000,0.02,0.03))) -> 0 | AG11: 0 | AH11: =1-AG11 -> 1 | AI11: =IF(AH11>=1,1,AH11) -> 1 | AJ11: =IF(AG11=0,"DST","POSP RM") -> DST
A12: 11 | B12: Vinita Kabra | C12: ='Employee Master'!H22 -> 43200 | D12: ='Employee Master'!N22 -> 259200 | W12: =((IF(U12="Yes",F12*1.25,F12)+IF(U12="Yes",IF(H12="Annual",G12,IF(H12="2-Year",G12/2*1.25,IF(H12="3-Year",G12/3*1.5,IF(H12="Quarterly/HY",G12*0.5,G12))))*1.25,IF(H12="Annual",G12,IF(H12="2-Year",G12/2*1.25,IF(H12="3-Year",G12/3*1.5,IF(H12="Quarterly/HY",G12*0.5,G12)))))+(I12+J12+K12)+(L12+M12*0.2)+IF(U12="Yes",(N12-AE12)*1.25,(N12-AE12))+(O12*0.1+P12*0.075+Q12*0.05+R12*0.1)+(S12*0.3+T12*0.15)))*AI12 -> 0 | X12: =IF(D12=0,0,W12/D12) -> 0 | Y12: =IF(X12<0.8,"Below 80%",IF(X12<=1,"80-100%",IF(X12<=1.1,"101-110%",IF(X12<=1.3,"111-130%",IF(X12<=1.5,"131-150%","150%+"))))) -> Below 80% | Z12: =IF(AJ12="DST",IF(X12<0.8,0,IF(X12<=1,0.04,IF(X12<=1.1,0.05,IF(X12<=1.3,0.06,IF(X12<=1.5,0.07,0.08))))),IF(X12<0.8,0,IF(X12<=1,0.012,IF(X12<=1.1,0.015,IF(X12<=1.3,0.018,IF(X12<=1.5,0.021,0.02)))))) -> 0 | AA12: =W12*Z12 -> 0 | AB12: =C12+AA12 -> 43200 | AC12: =IF(W12>='Employee Master'!P22,"YES","NO") -> NO | AD12: =IF(X12>=1.3,"Star",IF(X12>=1,"High",IF(X12>=0.8,"Meets",IF(X12>=0.6,"Below","Non-Performer")))) -> Non-Performer | AE12: 0 | AF12: =IF((I12+J12+K12)=0,0,IF((I12+J12+K12)<=300000,0.015,IF((I12+J12+K12)<=500000,0.02,0.03))) -> 0 | AG12: 0 | AH12: =1-AG12 -> 1 | AI12: =IF(AH12>=1,1,AH12) -> 1 | AJ12: =IF(AG12=0,"DST","POSP RM") -> DST
A13: 12 | B13: Sudeep Kashyap | C13: ='Employee Master'!H23 -> 28200 | D13: ='Employee Master'!N23 -> 169200 | W13: =((IF(U13="Yes",F13*1.25,F13)+IF(U13="Yes",IF(H13="Annual",G13,IF(H13="2-Year",G13/2*1.25,IF(H13="3-Year",G13/3*1.5,IF(H13="Quarterly/HY",G13*0.5,G13))))*1.25,IF(H13="Annual",G13,IF(H13="2-Year",G13/2*1.25,IF(H13="3-Year",G13/3*1.5,IF(H13="Quarterly/HY",G13*0.5,G13)))))+(I13+J13+K13)+(L13+M13*0.2)+IF(U13="Yes",(N13-AE13)*1.25,(N13-AE13))+(O13*0.1+P13*0.075+Q13*0.05+R13*0.1)+(S13*0.3+T13*0.15)))*AI13 -> 0 | X13: =IF(D13=0,0,W13/D13) -> 0 | Y13: =IF(X13<0.8,"Below 80%",IF(X13<=1,"80-100%",IF(X13<=1.1,"101-110%",IF(X13<=1.3,"111-130%",IF(X13<=1.5,"131-150%","150%+"))))) -> Below 80% | Z13: =IF(AJ13="DST",IF(X13<0.8,0,IF(X13<=1,0.04,IF(X13<=1.1,0.05,IF(X13<=1.3,0.06,IF(X13<=1.5,0.07,0.08))))),IF(X13<0.8,0,IF(X13<=1,0.012,IF(X13<=1.1,0.015,IF(X13<=1.3,0.018,IF(X13<=1.5,0.021,0.02)))))) -> 0 | AA13: =W13*Z13 -> 0 | AB13: =C13+AA13 -> 28200 | AC13: =IF(W13>='Employee Master'!P23,"YES","NO") -> NO | AD13: =IF(X13>=1.3,"Star",IF(X13>=1,"High",IF(X13>=0.8,"Meets",IF(X13>=0.6,"Below","Non-Performer")))) -> Non-Performer | AE13: 0 | AF13: =IF((I13+J13+K13)=0,0,IF((I13+J13+K13)<=300000,0.015,IF((I13+J13+K13)<=500000,0.02,0.03))) -> 0 | AG13: 0 | AH13: =1-AG13 -> 1 | AI13: =IF(AH13>=1,1,AH13) -> 1 | AJ13: =IF(AG13=0,"DST","POSP RM") -> DST
A14: 13 | B14: Jasmine Jain | C14: ='Employee Master'!H24 -> 28200 | D14: ='Employee Master'!N24 -> 169200 | W14: =((IF(U14="Yes",F14*1.25,F14)+IF(U14="Yes",IF(H14="Annual",G14,IF(H14="2-Year",G14/2*1.25,IF(H14="3-Year",G14/3*1.5,IF(H14="Quarterly/HY",G14*0.5,G14))))*1.25,IF(H14="Annual",G14,IF(H14="2-Year",G14/2*1.25,IF(H14="3-Year",G14/3*1.5,IF(H14="Quarterly/HY",G14*0.5,G14)))))+(I14+J14+K14)+(L14+M14*0.2)+IF(U14="Yes",(N14-AE14)*1.25,(N14-AE14))+(O14*0.1+P14*0.075+Q14*0.05+R14*0.1)+(S14*0.3+T14*0.15)))*AI14 -> 0 | X14: =IF(D14=0,0,W14/D14) -> 0 | Y14: =IF(X14<0.8,"Below 80%",IF(X14<=1,"80-100%",IF(X14<=1.1,"101-110%",IF(X14<=1.3,"111-130%",IF(X14<=1.5,"131-150%","150%+"))))) -> Below 80% | Z14: =IF(AJ14="DST",IF(X14<0.8,0,IF(X14<=1,0.04,IF(X14<=1.1,0.05,IF(X14<=1.3,0.06,IF(X14<=1.5,0.07,0.08))))),IF(X14<0.8,0,IF(X14<=1,0.012,IF(X14<=1.1,0.015,IF(X14<=1.3,0.018,IF(X14<=1.5,0.021,0.02)))))) -> 0 | AA14: =W14*Z14 -> 0 | AB14: =C14+AA14 -> 28200 | AC14: =IF(W14>='Employee Master'!P24,"YES","NO") -> NO | AD14: =IF(X14>=1.3,"Star",IF(X14>=1,"High",IF(X14>=0.8,"Meets",IF(X14>=0.6,"Below","Non-Performer")))) -> Non-Performer | AE14: 0 | AF14: =IF((I14+J14+K14)=0,0,IF((I14+J14+K14)<=300000,0.015,IF((I14+J14+K14)<=500000,0.02,0.03))) -> 0 | AG14: 0 | AH14: =1-AG14 -> 1 | AI14: =IF(AH14>=1,1,AH14) -> 1 | AJ14: =IF(AG14=0,"DST","POSP RM") -> DST
A15: 14 | B15: Preeti Nag | C15: ='Employee Master'!H27 -> 13286 | D15: ='Employee Master'!N27 -> 79716 | W15: =((IF(U15="Yes",F15*1.25,F15)+IF(U15="Yes",IF(H15="Annual",G15,IF(H15="2-Year",G15/2*1.25,IF(H15="3-Year",G15/3*1.5,IF(H15="Quarterly/HY",G15*0.5,G15))))*1.25,IF(H15="Annual",G15,IF(H15="2-Year",G15/2*1.25,IF(H15="3-Year",G15/3*1.5,IF(H15="Quarterly/HY",G15*0.5,G15)))))+(I15+J15+K15)+(L15+M15*0.2)+IF(U15="Yes",(N15-AE15)*1.25,(N15-AE15))+(O15*0.1+P15*0.075+Q15*0.05+R15*0.1)+(S15*0.3+T15*0.15)))*AI15 -> 0 | X15: =IF(D15=0,0,W15/D15) -> 0 | Y15: =IF(X15<0.8,"Below 80%",IF(X15<=1,"80-100%",IF(X15<=1.1,"101-110%",IF(X15<=1.3,"111-130%",IF(X15<=1.5,"131-150%","150%+"))))) -> Below 80% | Z15: =IF(AJ15="DST",IF(X15<0.8,0,IF(X15<=1,0.04,IF(X15<=1.1,0.05,IF(X15<=1.3,0.06,IF(X15<=1.5,0.07,0.08))))),IF(X15<0.8,0,IF(X15<=1,0.012,IF(X15<=1.1,0.015,IF(X15<=1.3,0.018,IF(X15<=1.5,0.021,0.02)))))) -> 0 | AA15: =W15*Z15 -> 0 | AB15: =C15+AA15 -> 13286 | AC15: =IF(W15>='Employee Master'!P27,"YES","NO") -> NO | AD15: =IF(X15>=1.3,"Star",IF(X15>=1,"High",IF(X15>=0.8,"Meets",IF(X15>=0.6,"Below","Non-Performer")))) -> Non-Performer | AE15: 0 | AF15: =IF((I15+J15+K15)=0,0,IF((I15+J15+K15)<=300000,0.015,IF((I15+J15+K15)<=500000,0.02,0.03))) -> 0 | AG15: 0 | AH15: =1-AG15 -> 1 | AI15: =IF(AH15>=1,1,AH15) -> 1 | AJ15: =IF(AG15=0,"DST","POSP RM") -> DST
A16: 15 | B16: Jinu Lagachu | C16: ='Employee Master'!H28 -> 23200 | D16: ='Employee Master'!N28 -> 139200 | W16: =((IF(U16="Yes",F16*1.25,F16)+IF(U16="Yes",IF(H16="Annual",G16,IF(H16="2-Year",G16/2*1.25,IF(H16="3-Year",G16/3*1.5,IF(H16="Quarterly/HY",G16*0.5,G16))))*1.25,IF(H16="Annual",G16,IF(H16="2-Year",G16/2*1.25,IF(H16="3-Year",G16/3*1.5,IF(H16="Quarterly/HY",G16*0.5,G16)))))+(I16+J16+K16)+(L16+M16*0.2)+IF(U16="Yes",(N16-AE16)*1.25,(N16-AE16))+(O16*0.1+P16*0.075+Q16*0.05+R16*0.1)+(S16*0.3+T16*0.15)))*AI16 -> 0 | X16: =IF(D16=0,0,W16/D16) -> 0 | Y16: =IF(X16<0.8,"Below 80%",IF(X16<=1,"80-100%",IF(X16<=1.1,"101-110%",IF(X16<=1.3,"111-130%",IF(X16<=1.5,"131-150%","150%+"))))) -> Below 80% | Z16: =IF(AJ16="DST",IF(X16<0.8,0,IF(X16<=1,0.04,IF(X16<=1.1,0.05,IF(X16<=1.3,0.06,IF(X16<=1.5,0.07,0.08))))),IF(X16<0.8,0,IF(X16<=1,0.012,IF(X16<=1.1,0.015,IF(X16<=1.3,0.018,IF(X16<=1.5,0.021,0.02)))))) -> 0 | AA16: =W16*Z16 -> 0 | AB16: =C16+AA16 -> 23200 | AC16: =IF(W16>='Employee Master'!P28,"YES","NO") -> NO | AD16: =IF(X16>=1.3,"Star",IF(X16>=1,"High",IF(X16>=0.8,"Meets",IF(X16>=0.6,"Below","Non-Performer")))) -> Non-Performer | AE16: 0 | AF16: =IF((I16+J16+K16)=0,0,IF((I16+J16+K16)<=300000,0.015,IF((I16+J16+K16)<=500000,0.02,0.03))) -> 0 | AG16: 0 | AH16: =1-AG16 -> 1 | AI16: =IF(AH16>=1,1,AH16) -> 1 | AJ16: =IF(AG16=0,"DST","POSP RM") -> DST
A17: 16 | B17: Khushbu Chhajer | C17: ='Employee Master'!H29 -> 38200 | D17: ='Employee Master'!N29 -> 229200 | W17: =((IF(U17="Yes",F17*1.25,F17)+IF(U17="Yes",IF(H17="Annual",G17,IF(H17="2-Year",G17/2*1.25,IF(H17="3-Year",G17/3*1.5,IF(H17="Quarterly/HY",G17*0.5,G17))))*1.25,IF(H17="Annual",G17,IF(H17="2-Year",G17/2*1.25,IF(H17="3-Year",G17/3*1.5,IF(H17="Quarterly/HY",G17*0.5,G17)))))+(I17+J17+K17)+(L17+M17*0.2)+IF(U17="Yes",(N17-AE17)*1.25,(N17-AE17))+(O17*0.1+P17*0.075+Q17*0.05+R17*0.1)+(S17*0.3+T17*0.15)))*AI17 -> 0 | X17: =IF(D17=0,0,W17/D17) -> 0 | Y17: =IF(X17<0.8,"Below 80%",IF(X17<=1,"80-100%",IF(X17<=1.1,"101-110%",IF(X17<=1.3,"111-130%",IF(X17<=1.5,"131-150%","150%+"))))) -> Below 80% | Z17: =IF(AJ17="DST",IF(X17<0.8,0,IF(X17<=1,0.04,IF(X17<=1.1,0.05,IF(X17<=1.3,0.06,IF(X17<=1.5,0.07,0.08))))),IF(X17<0.8,0,IF(X17<=1,0.012,IF(X17<=1.1,0.015,IF(X17<=1.3,0.018,IF(X17<=1.5,0.021,0.02)))))) -> 0 | AA17: =W17*Z17 -> 0 | AB17: =C17+AA17 -> 38200 | AC17: =IF(W17>='Employee Master'!P29,"YES","NO") -> NO | AD17: =IF(X17>=1.3,"Star",IF(X17>=1,"High",IF(X17>=0.8,"Meets",IF(X17>=0.6,"Below","Non-Performer")))) -> Non-Performer | AE17: 0 | AF17: =IF((I17+J17+K17)=0,0,IF((I17+J17+K17)<=300000,0.015,IF((I17+J17+K17)<=500000,0.02,0.03))) -> 0 | AG17: 0 | AH17: =1-AG17 -> 1 | AI17: =IF(AH17>=1,1,AH17) -> 1 | AJ17: =IF(AG17=0,"DST","POSP RM") -> DST
A18: 17 | B18: Dipankar Das | C18: ='Employee Master'!H31 -> 48200 | D18: ='Employee Master'!N31 -> 289200 | W18: =((IF(U18="Yes",F18*1.25,F18)+IF(U18="Yes",IF(H18="Annual",G18,IF(H18="2-Year",G18/2*1.25,IF(H18="3-Year",G18/3*1.5,IF(H18="Quarterly/HY",G18*0.5,G18))))*1.25,IF(H18="Annual",G18,IF(H18="2-Year",G18/2*1.25,IF(H18="3-Year",G18/3*1.5,IF(H18="Quarterly/HY",G18*0.5,G18)))))+(I18+J18+K18)+(L18+M18*0.2)+IF(U18="Yes",(N18-AE18)*1.25,(N18-AE18))+(O18*0.1+P18*0.075+Q18*0.05+R18*0.1)+(S18*0.3+T18*0.15)))*AI18 -> 0 | X18: =IF(D18=0,0,W18/D18) -> 0 | Y18: =IF(X18<0.8,"Below 80%",IF(X18<=1,"80-100%",IF(X18<=1.1,"101-110%",IF(X18<=1.3,"111-130%",IF(X18<=1.5,"131-150%","150%+"))))) -> Below 80% | Z18: =IF(AJ18="DST",IF(X18<0.8,0,IF(X18<=1,0.04,IF(X18<=1.1,0.05,IF(X18<=1.3,0.06,IF(X18<=1.5,0.07,0.08))))),IF(X18<0.8,0,IF(X18<=1,0.012,IF(X18<=1.1,0.015,IF(X18<=1.3,0.018,IF(X18<=1.5,0.021,0.02)))))) -> 0 | AA18: =W18*Z18 -> 0 | AB18: =C18+AA18 -> 48200 | AC18: =IF(W18>='Employee Master'!P31,"YES","NO") -> NO | AD18: =IF(X18>=1.3,"Star",IF(X18>=1,"High",IF(X18>=0.8,"Meets",IF(X18>=0.6,"Below","Non-Performer")))) -> Non-Performer | AE18: 0 | AF18: =IF((I18+J18+K18)=0,0,IF((I18+J18+K18)<=300000,0.015,IF((I18+J18+K18)<=500000,0.02,0.03))) -> 0 | AG18: 0 | AH18: =1-AG18 -> 1 | AI18: =IF(AH18>=1,1,AH18) -> 1 | AJ18: =IF(AG18=0,"DST","POSP RM") -> DST
A19: 18 | B19: Tanima Das | C19: ='Employee Master'!H33 -> 16209 | D19: ='Employee Master'!N33 -> 97254 | W19: =((IF(U19="Yes",F19*1.25,F19)+IF(U19="Yes",IF(H19="Annual",G19,IF(H19="2-Year",G19/2*1.25,IF(H19="3-Year",G19/3*1.5,IF(H19="Quarterly/HY",G19*0.5,G19))))*1.25,IF(H19="Annual",G19,IF(H19="2-Year",G19/2*1.25,IF(H19="3-Year",G19/3*1.5,IF(H19="Quarterly/HY",G19*0.5,G19)))))+(I19+J19+K19)+(L19+M19*0.2)+IF(U19="Yes",(N19-AE19)*1.25,(N19-AE19))+(O19*0.1+P19*0.075+Q19*0.05+R19*0.1)+(S19*0.3+T19*0.15)))*AI19 -> 0 | X19: =IF(D19=0,0,W19/D19) -> 0 | Y19: =IF(X19<0.8,"Below 80%",IF(X19<=1,"80-100%",IF(X19<=1.1,"101-110%",IF(X19<=1.3,"111-130%",IF(X19<=1.5,"131-150%","150%+"))))) -> Below 80% | Z19: =IF(AJ19="DST",IF(X19<0.8,0,IF(X19<=1,0.04,IF(X19<=1.1,0.05,IF(X19<=1.3,0.06,IF(X19<=1.5,0.07,0.08))))),IF(X19<0.8,0,IF(X19<=1,0.012,IF(X19<=1.1,0.015,IF(X19<=1.3,0.018,IF(X19<=1.5,0.021,0.02)))))) -> 0 | AA19: =W19*Z19 -> 0 | AB19: =C19+AA19 -> 16209 | AC19: =IF(W19>='Employee Master'!P33,"YES","NO") -> NO | AD19: =IF(X19>=1.3,"Star",IF(X19>=1,"High",IF(X19>=0.8,"Meets",IF(X19>=0.6,"Below","Non-Performer")))) -> Non-Performer | AE19: 0 | AF19: =IF((I19+J19+K19)=0,0,IF((I19+J19+K19)<=300000,0.015,IF((I19+J19+K19)<=500000,0.02,0.03))) -> 0 | AG19: 0 | AH19: =1-AG19 -> 1 | AI19: =IF(AH19>=1,1,AH19) -> 1 | AJ19: =IF(AG19=0,"DST","POSP RM") -> DST
A20: 19 | B20: Mrinmoy Choudhury | C20: ='Employee Master'!H34 -> 95833 | D20: ='Employee Master'!N34 -> 2204159 | W20: =((IF(U20="Yes",F20*1.25,F20)+IF(U20="Yes",IF(H20="Annual",G20,IF(H20="2-Year",G20/2*1.25,IF(H20="3-Year",G20/3*1.5,IF(H20="Quarterly/HY",G20*0.5,G20))))*1.25,IF(H20="Annual",G20,IF(H20="2-Year",G20/2*1.25,IF(H20="3-Year",G20/3*1.5,IF(H20="Quarterly/HY",G20*0.5,G20)))))+(I20+J20+K20)+(L20+M20*0.2)+IF(U20="Yes",(N20-AE20)*1.25,(N20-AE20))+(O20*0.1+P20*0.075+Q20*0.05+R20*0.1)+(S20*0.3+T20*0.15)))*AI20 -> 0 | X20: =IF(D20=0,0,W20/D20) -> 0 | Y20: =IF(X20<0.8,"Below 80%",IF(X20<=1,"80-100%",IF(X20<=1.1,"101-110%",IF(X20<=1.3,"111-130%",IF(X20<=1.5,"131-150%","150%+"))))) -> Below 80% | Z20: =IF(AJ20="DST",IF(X20<0.8,0,IF(X20<=1,0.04,IF(X20<=1.1,0.05,IF(X20<=1.3,0.06,IF(X20<=1.5,0.07,0.08))))),IF(X20<0.8,0,IF(X20<=1,0.012,IF(X20<=1.1,0.015,IF(X20<=1.3,0.018,IF(X20<=1.5,0.021,0.02)))))) -> 0 | AA20: =W20*Z20 -> 0 | AB20: =C20+AA20 -> 95833 | AC20: =IF(W20>='Employee Master'!P34,"YES","NO") -> NO | AD20: =IF(X20>=1.3,"Star",IF(X20>=1,"High",IF(X20>=0.8,"Meets",IF(X20>=0.6,"Below","Non-Performer")))) -> Non-Performer | AE20: 0 | AF20: =IF((I20+J20+K20)=0,0,IF((I20+J20+K20)<=300000,0.015,IF((I20+J20+K20)<=500000,0.02,0.03))) -> 0 | AG20: 0 | AH20: =1-AG20 -> 1 | AI20: =IF(AH20>=1,1,AH20) -> 1 | AJ20: =IF(AG20=0,"DST","POSP RM") -> DST
A21: 20 | B21: Banshika Agarwal | C21: ='Employee Master'!H36 -> 13507 | D21: ='Employee Master'!N36 -> 81042 | W21: =((IF(U21="Yes",F21*1.25,F21)+IF(U21="Yes",IF(H21="Annual",G21,IF(H21="2-Year",G21/2*1.25,IF(H21="3-Year",G21/3*1.5,IF(H21="Quarterly/HY",G21*0.5,G21))))*1.25,IF(H21="Annual",G21,IF(H21="2-Year",G21/2*1.25,IF(H21="3-Year",G21/3*1.5,IF(H21="Quarterly/HY",G21*0.5,G21)))))+(I21+J21+K21)+(L21+M21*0.2)+IF(U21="Yes",(N21-AE21)*1.25,(N21-AE21))+(O21*0.1+P21*0.075+Q21*0.05+R21*0.1)+(S21*0.3+T21*0.15)))*AI21 -> 0 | X21: =IF(D21=0,0,W21/D21) -> 0 | Y21: =IF(X21<0.8,"Below 80%",IF(X21<=1,"80-100%",IF(X21<=1.1,"101-110%",IF(X21<=1.3,"111-130%",IF(X21<=1.5,"131-150%","150%+"))))) -> Below 80% | Z21: =IF(AJ21="DST",IF(X21<0.8,0,IF(X21<=1,0.04,IF(X21<=1.1,0.05,IF(X21<=1.3,0.06,IF(X21<=1.5,0.07,0.08))))),IF(X21<0.8,0,IF(X21<=1,0.012,IF(X21<=1.1,0.015,IF(X21<=1.3,0.018,IF(X21<=1.5,0.021,0.02)))))) -> 0 | AA21: =W21*Z21 -> 0 | AB21: =C21+AA21 -> 13507 | AC21: =IF(W21>='Employee Master'!P36,"YES","NO") -> NO | AD21: =IF(X21>=1.3,"Star",IF(X21>=1,"High",IF(X21>=0.8,"Meets",IF(X21>=0.6,"Below","Non-Performer")))) -> Non-Performer | AE21: 0 | AF21: =IF((I21+J21+K21)=0,0,IF((I21+J21+K21)<=300000,0.015,IF((I21+J21+K21)<=500000,0.02,0.03))) -> 0 | AG21: 0 | AH21: =1-AG21 -> 1 | AI21: =IF(AH21>=1,1,AH21) -> 1 | AJ21: =IF(AG21=0,"DST","POSP RM") -> DST
A22: 21 | B22: Banajit Bezbaruah | C22: ='Employee Master'!H39 -> 30363 | D22: ='Employee Master'!N39 -> 182178 | W22: =((IF(U22="Yes",F22*1.25,F22)+IF(U22="Yes",IF(H22="Annual",G22,IF(H22="2-Year",G22/2*1.25,IF(H22="3-Year",G22/3*1.5,IF(H22="Quarterly/HY",G22*0.5,G22))))*1.25,IF(H22="Annual",G22,IF(H22="2-Year",G22/2*1.25,IF(H22="3-Year",G22/3*1.5,IF(H22="Quarterly/HY",G22*0.5,G22)))))+(I22+J22+K22)+(L22+M22*0.2)+IF(U22="Yes",(N22-AE22)*1.25,(N22-AE22))+(O22*0.1+P22*0.075+Q22*0.05+R22*0.1)+(S22*0.3+T22*0.15)))*AI22 -> 0 | X22: =IF(D22=0,0,W22/D22) -> 0 | Y22: =IF(X22<0.8,"Below 80%",IF(X22<=1,"80-100%",IF(X22<=1.1,"101-110%",IF(X22<=1.3,"111-130%",IF(X22<=1.5,"131-150%","150%+"))))) -> Below 80% | Z22: =IF(AJ22="DST",IF(X22<0.8,0,IF(X22<=1,0.04,IF(X22<=1.1,0.05,IF(X22<=1.3,0.06,IF(X22<=1.5,0.07,0.08))))),IF(X22<0.8,0,IF(X22<=1,0.012,IF(X22<=1.1,0.015,IF(X22<=1.3,0.018,IF(X22<=1.5,0.021,0.02)))))) -> 0 | AA22: =W22*Z22 -> 0 | AB22: =C22+AA22 -> 30363 | AC22: =IF(W22>='Employee Master'!P39,"YES","NO") -> NO | AD22: =IF(X22>=1.3,"Star",IF(X22>=1,"High",IF(X22>=0.8,"Meets",IF(X22>=0.6,"Below","Non-Performer")))) -> Non-Performer | AE22: 0 | AF22: =IF((I22+J22+K22)=0,0,IF((I22+J22+K22)<=300000,0.015,IF((I22+J22+K22)<=500000,0.02,0.03))) -> 0 | AG22: 0 | AH22: =1-AG22 -> 1 | AI22: =IF(AH22>=1,1,AH22) -> 1 | AJ22: =IF(AG22=0,"DST","POSP RM") -> DST
A23: 22 | B23: Kshetrimayam AK Singh | C23: ='Employee Master'!H40 -> 44035 | D23: ='Employee Master'!N40 -> 880700 | W23: =((IF(U23="Yes",F23*1.25,F23)+IF(U23="Yes",IF(H23="Annual",G23,IF(H23="2-Year",G23/2*1.25,IF(H23="3-Year",G23/3*1.5,IF(H23="Quarterly/HY",G23*0.5,G23))))*1.25,IF(H23="Annual",G23,IF(H23="2-Year",G23/2*1.25,IF(H23="3-Year",G23/3*1.5,IF(H23="Quarterly/HY",G23*0.5,G23)))))+(I23+J23+K23)+(L23+M23*0.2)+IF(U23="Yes",(N23-AE23)*1.25,(N23-AE23))+(O23*0.1+P23*0.075+Q23*0.05+R23*0.1)+(S23*0.3+T23*0.15)))*AI23 -> 0 | X23: =IF(D23=0,0,W23/D23) -> 0 | Y23: =IF(X23<0.8,"Below 80%",IF(X23<=1,"80-100%",IF(X23<=1.1,"101-110%",IF(X23<=1.3,"111-130%",IF(X23<=1.5,"131-150%","150%+"))))) -> Below 80% | Z23: =IF(AJ23="DST",IF(X23<0.8,0,IF(X23<=1,0.04,IF(X23<=1.1,0.05,IF(X23<=1.3,0.06,IF(X23<=1.5,0.07,0.08))))),IF(X23<0.8,0,IF(X23<=1,0.012,IF(X23<=1.1,0.015,IF(X23<=1.3,0.018,IF(X23<=1.5,0.021,0.02)))))) -> 0 | AA23: =W23*Z23 -> 0 | AB23: =C23+AA23 -> 44035 | AC23: =IF(W23>='Employee Master'!P40,"YES","NO") -> NO | AD23: =IF(X23>=1.3,"Star",IF(X23>=1,"High",IF(X23>=0.8,"Meets",IF(X23>=0.6,"Below","Non-Performer")))) -> Non-Performer | AE23: 0 | AF23: =IF((I23+J23+K23)=0,0,IF((I23+J23+K23)<=300000,0.015,IF((I23+J23+K23)<=500000,0.02,0.03))) -> 0 | AG23: 0 | AH23: =1-AG23 -> 1 | AI23: =IF(AH23>=1,1,AH23) -> 1 | AJ23: =IF(AG23=0,"DST","POSP RM") -> DST
A24: 23 | B24: Shoibam Nara Singh | C24: ='Employee Master'!H41 -> 41534 | D24: ='Employee Master'!N41 -> 830680 | W24: =((IF(U24="Yes",F24*1.25,F24)+IF(U24="Yes",IF(H24="Annual",G24,IF(H24="2-Year",G24/2*1.25,IF(H24="3-Year",G24/3*1.5,IF(H24="Quarterly/HY",G24*0.5,G24))))*1.25,IF(H24="Annual",G24,IF(H24="2-Year",G24/2*1.25,IF(H24="3-Year",G24/3*1.5,IF(H24="Quarterly/HY",G24*0.5,G24)))))+(I24+J24+K24)+(L24+M24*0.2)+IF(U24="Yes",(N24-AE24)*1.25,(N24-AE24))+(O24*0.1+P24*0.075+Q24*0.05+R24*0.1)+(S24*0.3+T24*0.15)))*AI24 -> 0 | X24: =IF(D24=0,0,W24/D24) -> 0 | Y24: =IF(X24<0.8,"Below 80%",IF(X24<=1,"80-100%",IF(X24<=1.1,"101-110%",IF(X24<=1.3,"111-130%",IF(X24<=1.5,"131-150%","150%+"))))) -> Below 80% | Z24: =IF(AJ24="DST",IF(X24<0.8,0,IF(X24<=1,0.04,IF(X24<=1.1,0.05,IF(X24<=1.3,0.06,IF(X24<=1.5,0.07,0.08))))),IF(X24<0.8,0,IF(X24<=1,0.012,IF(X24<=1.1,0.015,IF(X24<=1.3,0.018,IF(X24<=1.5,0.021,0.02)))))) -> 0 | AA24: =W24*Z24 -> 0 | AB24: =C24+AA24 -> 41534 | AC24: =IF(W24>='Employee Master'!P41,"YES","NO") -> NO | AD24: =IF(X24>=1.3,"Star",IF(X24>=1,"High",IF(X24>=0.8,"Meets",IF(X24>=0.6,"Below","Non-Performer")))) -> Non-Performer | AE24: 0 | AF24: =IF((I24+J24+K24)=0,0,IF((I24+J24+K24)<=300000,0.015,IF((I24+J24+K24)<=500000,0.02,0.03))) -> 0 | AG24: 0 | AH24: =1-AG24 -> 1 | AI24: =IF(AH24>=1,1,AH24) -> 1 | AJ24: =IF(AG24=0,"DST","POSP RM") -> DST
A25: 24 | B25: Tasdiq Ahmed | C25: ='Employee Master'!H42 -> 18009 | D25: ='Employee Master'!N42 -> 108054 | W25: =((IF(U25="Yes",F25*1.25,F25)+IF(U25="Yes",IF(H25="Annual",G25,IF(H25="2-Year",G25/2*1.25,IF(H25="3-Year",G25/3*1.5,IF(H25="Quarterly/HY",G25*0.5,G25))))*1.25,IF(H25="Annual",G25,IF(H25="2-Year",G25/2*1.25,IF(H25="3-Year",G25/3*1.5,IF(H25="Quarterly/HY",G25*0.5,G25)))))+(I25+J25+K25)+(L25+M25*0.2)+IF(U25="Yes",(N25-AE25)*1.25,(N25-AE25))+(O25*0.1+P25*0.075+Q25*0.05+R25*0.1)+(S25*0.3+T25*0.15)))*AI25 -> 0 | X25: =IF(D25=0,0,W25/D25) -> 0 | Y25: =IF(X25<0.8,"Below 80%",IF(X25<=1,"80-100%",IF(X25<=1.1,"101-110%",IF(X25<=1.3,"111-130%",IF(X25<=1.5,"131-150%","150%+"))))) -> Below 80% | Z25: =IF(AJ25="DST",IF(X25<0.8,0,IF(X25<=1,0.04,IF(X25<=1.1,0.05,IF(X25<=1.3,0.06,IF(X25<=1.5,0.07,0.08))))),IF(X25<0.8,0,IF(X25<=1,0.012,IF(X25<=1.1,0.015,IF(X25<=1.3,0.018,IF(X25<=1.5,0.021,0.02)))))) -> 0 | AA25: =W25*Z25 -> 0 | AB25: =C25+AA25 -> 18009 | AC25: =IF(W25>='Employee Master'!P42,"YES","NO") -> NO | AD25: =IF(X25>=1.3,"Star",IF(X25>=1,"High",IF(X25>=0.8,"Meets",IF(X25>=0.6,"Below","Non-Performer")))) -> Non-Performer | AE25: 0 | AF25: =IF((I25+J25+K25)=0,0,IF((I25+J25+K25)<=300000,0.015,IF((I25+J25+K25)<=500000,0.02,0.03))) -> 0 | AG25: 0 | AH25: =1-AG25 -> 1 | AI25: =IF(AH25>=1,1,AH25) -> 1 | AJ25: =IF(AG25=0,"DST","POSP RM") -> DST
A26: 25 | B26: Hemanta Saharia | C26: ='Employee Master'!H43 -> 66117 | D26: ='Employee Master'!N43 -> 1322340 | W26: =((IF(U26="Yes",F26*1.25,F26)+IF(U26="Yes",IF(H26="Annual",G26,IF(H26="2-Year",G26/2*1.25,IF(H26="3-Year",G26/3*1.5,IF(H26="Quarterly/HY",G26*0.5,G26))))*1.25,IF(H26="Annual",G26,IF(H26="2-Year",G26/2*1.25,IF(H26="3-Year",G26/3*1.5,IF(H26="Quarterly/HY",G26*0.5,G26)))))+(I26+J26+K26)+(L26+M26*0.2)+IF(U26="Yes",(N26-AE26)*1.25,(N26-AE26))+(O26*0.1+P26*0.075+Q26*0.05+R26*0.1)+(S26*0.3+T26*0.15)))*AI26 -> 0 | X26: =IF(D26=0,0,W26/D26) -> 0 | Y26: =IF(X26<0.8,"Below 80%",IF(X26<=1,"80-100%",IF(X26<=1.1,"101-110%",IF(X26<=1.3,"111-130%",IF(X26<=1.5,"131-150%","150%+"))))) -> Below 80% | Z26: =IF(AJ26="DST",IF(X26<0.8,0,IF(X26<=1,0.04,IF(X26<=1.1,0.05,IF(X26<=1.3,0.06,IF(X26<=1.5,0.07,0.08))))),IF(X26<0.8,0,IF(X26<=1,0.012,IF(X26<=1.1,0.015,IF(X26<=1.3,0.018,IF(X26<=1.5,0.021,0.02)))))) -> 0 | AA26: =W26*Z26 -> 0 | AB26: =C26+AA26 -> 66117 | AC26: =IF(W26>='Employee Master'!P43,"YES","NO") -> NO | AD26: =IF(X26>=1.3,"Star",IF(X26>=1,"High",IF(X26>=0.8,"Meets",IF(X26>=0.6,"Below","Non-Performer")))) -> Non-Performer | AE26: 0 | AF26: =IF((I26+J26+K26)=0,0,IF((I26+J26+K26)<=300000,0.015,IF((I26+J26+K26)<=500000,0.02,0.03))) -> 0 | AG26: 0 | AH26: =1-AG26 -> 1 | AI26: =IF(AH26>=1,1,AH26) -> 1 | AJ26: =IF(AG26=0,"DST","POSP RM") -> DST
A27: 26 | B27: Juntara Patir | C27: ='Employee Master'!H44 -> 6000 | D27: ='Employee Master'!N44 -> 36000 | W27: =((IF(U27="Yes",F27*1.25,F27)+IF(U27="Yes",IF(H27="Annual",G27,IF(H27="2-Year",G27/2*1.25,IF(H27="3-Year",G27/3*1.5,IF(H27="Quarterly/HY",G27*0.5,G27))))*1.25,IF(H27="Annual",G27,IF(H27="2-Year",G27/2*1.25,IF(H27="3-Year",G27/3*1.5,IF(H27="Quarterly/HY",G27*0.5,G27)))))+(I27+J27+K27)+(L27+M27*0.2)+IF(U27="Yes",(N27-AE27)*1.25,(N27-AE27))+(O27*0.1+P27*0.075+Q27*0.05+R27*0.1)+(S27*0.3+T27*0.15)))*AI27 -> 0 | X27: =IF(D27=0,0,W27/D27) -> 0 | Y27: =IF(X27<0.8,"Below 80%",IF(X27<=1,"80-100%",IF(X27<=1.1,"101-110%",IF(X27<=1.3,"111-130%",IF(X27<=1.5,"131-150%","150%+"))))) -> Below 80% | Z27: =IF(AJ27="DST",IF(X27<0.8,0,IF(X27<=1,0.04,IF(X27<=1.1,0.05,IF(X27<=1.3,0.06,IF(X27<=1.5,0.07,0.08))))),IF(X27<0.8,0,IF(X27<=1,0.012,IF(X27<=1.1,0.015,IF(X27<=1.3,0.018,IF(X27<=1.5,0.021,0.02)))))) -> 0 | AA27: =W27*Z27 -> 0 | AB27: =C27+AA27 -> 6000 | AC27: =IF(W27>='Employee Master'!P44,"YES","NO") -> NO | AD27: =IF(X27>=1.3,"Star",IF(X27>=1,"High",IF(X27>=0.8,"Meets",IF(X27>=0.6,"Below","Non-Performer")))) -> Non-Performer | AE27: 0 | AF27: =IF((I27+J27+K27)=0,0,IF((I27+J27+K27)<=300000,0.015,IF((I27+J27+K27)<=500000,0.02,0.03))) -> 0 | AG27: 0 | AH27: =1-AG27 -> 1 | AI27: =IF(AH27>=1,1,AH27) -> 1 | AJ27: =IF(AG27=0,"DST","POSP RM") -> DST
A28: 27 | B28: Partha Deb Barman | C28: ='Employee Master'!H46 -> 112008 | D28: ='Employee Master'!N46 -> 2240160 | W28: =((IF(U28="Yes",F28*1.25,F28)+IF(U28="Yes",IF(H28="Annual",G28,IF(H28="2-Year",G28/2*1.25,IF(H28="3-Year",G28/3*1.5,IF(H28="Quarterly/HY",G28*0.5,G28))))*1.25,IF(H28="Annual",G28,IF(H28="2-Year",G28/2*1.25,IF(H28="3-Year",G28/3*1.5,IF(H28="Quarterly/HY",G28*0.5,G28)))))+(I28+J28+K28)+(L28+M28*0.2)+IF(U28="Yes",(N28-AE28)*1.25,(N28-AE28))+(O28*0.1+P28*0.075+Q28*0.05+R28*0.1)+(S28*0.3+T28*0.15)))*AI28 -> 0 | X28: =IF(D28=0,0,W28/D28) -> 0 | Y28: =IF(X28<0.8,"Below 80%",IF(X28<=1,"80-100%",IF(X28<=1.1,"101-110%",IF(X28<=1.3,"111-130%",IF(X28<=1.5,"131-150%","150%+"))))) -> Below 80% | Z28: =IF(AJ28="DST",IF(X28<0.8,0,IF(X28<=1,0.04,IF(X28<=1.1,0.05,IF(X28<=1.3,0.06,IF(X28<=1.5,0.07,0.08))))),IF(X28<0.8,0,IF(X28<=1,0.012,IF(X28<=1.1,0.015,IF(X28<=1.3,0.018,IF(X28<=1.5,0.021,0.02)))))) -> 0 | AA28: =W28*Z28 -> 0 | AB28: =C28+AA28 -> 112008 | AC28: =IF(W28>='Employee Master'!P46,"YES","NO") -> NO | AD28: =IF(X28>=1.3,"Star",IF(X28>=1,"High",IF(X28>=0.8,"Meets",IF(X28>=0.6,"Below","Non-Performer")))) -> Non-Performer | AE28: 0 | AF28: =IF((I28+J28+K28)=0,0,IF((I28+J28+K28)<=300000,0.015,IF((I28+J28+K28)<=500000,0.02,0.03))) -> 0 | AG28: 0 | AH28: =1-AG28 -> 1 | AI28: =IF(AH28>=1,1,AH28) -> 1 | AJ28: =IF(AG28=0,"DST","POSP RM") -> DST
A29: 28 | B29: Abir Das | C29: ='Employee Master'!H49 -> 300000 | D29: ='Employee Master'!N49 -> 0 | W29: =((IF(U29="Yes",F29*1.25,F29)+IF(U29="Yes",IF(H29="Annual",G29,IF(H29="2-Year",G29/2*1.25,IF(H29="3-Year",G29/3*1.5,IF(H29="Quarterly/HY",G29*0.5,G29))))*1.25,IF(H29="Annual",G29,IF(H29="2-Year",G29/2*1.25,IF(H29="3-Year",G29/3*1.5,IF(H29="Quarterly/HY",G29*0.5,G29)))))+(I29+J29+K29)+(L29+M29*0.2)+IF(U29="Yes",(N29-AE29)*1.25,(N29-AE29))+(O29*0.1+P29*0.075+Q29*0.05+R29*0.1)+(S29*0.3+T29*0.15)))*AI29 -> 0 | X29: =IF(D29=0,0,W29/D29) -> 0 | Y29: =IF(X29<0.8,"Below 80%",IF(X29<=1,"80-100%",IF(X29<=1.1,"101-110%",IF(X29<=1.3,"111-130%",IF(X29<=1.5,"131-150%","150%+"))))) -> Below 80% | Z29: =IF(AJ29="DST",IF(X29<0.8,0,IF(X29<=1,0.04,IF(X29<=1.1,0.05,IF(X29<=1.3,0.06,IF(X29<=1.5,0.07,0.08))))),IF(X29<0.8,0,IF(X29<=1,0.012,IF(X29<=1.1,0.015,IF(X29<=1.3,0.018,IF(X29<=1.5,0.021,0.02)))))) -> 0 | AA29: =W29*Z29 -> 0 | AB29: =C29+AA29 -> 300000 | AC29: =IF(W29>='Employee Master'!P49,"YES","NO") -> NO | AD29: =IF(X29>=1.3,"Star",IF(X29>=1,"High",IF(X29>=0.8,"Meets",IF(X29>=0.6,"Below","Non-Performer")))) -> Non-Performer | AE29: 0 | AF29: =IF((I29+J29+K29)=0,0,IF((I29+J29+K29)<=300000,0.015,IF((I29+J29+K29)<=500000,0.02,0.03))) -> 0 | AG29: 0 | AH29: =1-AG29 -> 1 | AI29: =IF(AH29>=1,1,AH29) -> 1 | AJ29: =IF(AG29=0,"DST","POSP RM") -> DST
A30: 29 | B30: Sudarshana Gupta | C30: ='Employee Master'!H51 -> 28200 | D30: ='Employee Master'!N51 -> 169200 | W30: =((IF(U30="Yes",F30*1.25,F30)+IF(U30="Yes",IF(H30="Annual",G30,IF(H30="2-Year",G30/2*1.25,IF(H30="3-Year",G30/3*1.5,IF(H30="Quarterly/HY",G30*0.5,G30))))*1.25,IF(H30="Annual",G30,IF(H30="2-Year",G30/2*1.25,IF(H30="3-Year",G30/3*1.5,IF(H30="Quarterly/HY",G30*0.5,G30)))))+(I30+J30+K30)+(L30+M30*0.2)+IF(U30="Yes",(N30-AE30)*1.25,(N30-AE30))+(O30*0.1+P30*0.075+Q30*0.05+R30*0.1)+(S30*0.3+T30*0.15)))*AI30 -> 0 | X30: =IF(D30=0,0,W30/D30) -> 0 | Y30: =IF(X30<0.8,"Below 80%",IF(X30<=1,"80-100%",IF(X30<=1.1,"101-110%",IF(X30<=1.3,"111-130%",IF(X30<=1.5,"131-150%","150%+"))))) -> Below 80% | Z30: =IF(AJ30="DST",IF(X30<0.8,0,IF(X30<=1,0.04,IF(X30<=1.1,0.05,IF(X30<=1.3,0.06,IF(X30<=1.5,0.07,0.08))))),IF(X30<0.8,0,IF(X30<=1,0.012,IF(X30<=1.1,0.015,IF(X30<=1.3,0.018,IF(X30<=1.5,0.021,0.02)))))) -> 0 | AA30: =W30*Z30 -> 0 | AB30: =C30+AA30 -> 28200 | AC30: =IF(W30>='Employee Master'!P51,"YES","NO") -> NO | AD30: =IF(X30>=1.3,"Star",IF(X30>=1,"High",IF(X30>=0.8,"Meets",IF(X30>=0.6,"Below","Non-Performer")))) -> Non-Performer | AE30: 0 | AF30: =IF((I30+J30+K30)=0,0,IF((I30+J30+K30)<=300000,0.015,IF((I30+J30+K30)<=500000,0.02,0.03))) -> 0 | AG30: 0 | AH30: =1-AG30 -> 1 | AI30: =IF(AH30>=1,1,AH30) -> 1 | AJ30: =IF(AG30=0,"DST","POSP RM") -> DST
A31: 30 | B31: Anikendu Indra | C31: ='Employee Master'!H52 -> 20427 | D31: ='Employee Master'!N52 -> 408540 | W31: =((IF(U31="Yes",F31*1.25,F31)+IF(U31="Yes",IF(H31="Annual",G31,IF(H31="2-Year",G31/2*1.25,IF(H31="3-Year",G31/3*1.5,IF(H31="Quarterly/HY",G31*0.5,G31))))*1.25,IF(H31="Annual",G31,IF(H31="2-Year",G31/2*1.25,IF(H31="3-Year",G31/3*1.5,IF(H31="Quarterly/HY",G31*0.5,G31)))))+(I31+J31+K31)+(L31+M31*0.2)+IF(U31="Yes",(N31-AE31)*1.25,(N31-AE31))+(O31*0.1+P31*0.075+Q31*0.05+R31*0.1)+(S31*0.3+T31*0.15)))*AI31 -> 0 | X31: =IF(D31=0,0,W31/D31) -> 0 | Y31: =IF(X31<0.8,"Below 80%",IF(X31<=1,"80-100%",IF(X31<=1.1,"101-110%",IF(X31<=1.3,"111-130%",IF(X31<=1.5,"131-150%","150%+"))))) -> Below 80% | Z31: =IF(AJ31="DST",IF(X31<0.8,0,IF(X31<=1,0.04,IF(X31<=1.1,0.05,IF(X31<=1.3,0.06,IF(X31<=1.5,0.07,0.08))))),IF(X31<0.8,0,IF(X31<=1,0.012,IF(X31<=1.1,0.015,IF(X31<=1.3,0.018,IF(X31<=1.5,0.021,0.02)))))) -> 0 | AA31: =W31*Z31 -> 0 | AB31: =C31+AA31 -> 20427 | AC31: =IF(W31>='Employee Master'!P52,"YES","NO") -> NO | AD31: =IF(X31>=1.3,"Star",IF(X31>=1,"High",IF(X31>=0.8,"Meets",IF(X31>=0.6,"Below","Non-Performer")))) -> Non-Performer | AE31: 0 | AF31: =IF((I31+J31+K31)=0,0,IF((I31+J31+K31)<=300000,0.015,IF((I31+J31+K31)<=500000,0.02,0.03))) -> 0 | AG31: 0 | AH31: =1-AG31 -> 1 | AI31: =IF(AH31>=1,1,AH31) -> 1 | AJ31: =IF(AG31=0,"DST","POSP RM") -> DST
A32: 31 | B32: Ashis Das | C32: ='Employee Master'!H53 -> 52009 | D32: ='Employee Master'!N53 -> 1040180 | W32: =((IF(U32="Yes",F32*1.25,F32)+IF(U32="Yes",IF(H32="Annual",G32,IF(H32="2-Year",G32/2*1.25,IF(H32="3-Year",G32/3*1.5,IF(H32="Quarterly/HY",G32*0.5,G32))))*1.25,IF(H32="Annual",G32,IF(H32="2-Year",G32/2*1.25,IF(H32="3-Year",G32/3*1.5,IF(H32="Quarterly/HY",G32*0.5,G32)))))+(I32+J32+K32)+(L32+M32*0.2)+IF(U32="Yes",(N32-AE32)*1.25,(N32-AE32))+(O32*0.1+P32*0.075+Q32*0.05+R32*0.1)+(S32*0.3+T32*0.15)))*AI32 -> 0 | X32: =IF(D32=0,0,W32/D32) -> 0 | Y32: =IF(X32<0.8,"Below 80%",IF(X32<=1,"80-100%",IF(X32<=1.1,"101-110%",IF(X32<=1.3,"111-130%",IF(X32<=1.5,"131-150%","150%+"))))) -> Below 80% | Z32: =IF(AJ32="DST",IF(X32<0.8,0,IF(X32<=1,0.04,IF(X32<=1.1,0.05,IF(X32<=1.3,0.06,IF(X32<=1.5,0.07,0.08))))),IF(X32<0.8,0,IF(X32<=1,0.012,IF(X32<=1.1,0.015,IF(X32<=1.3,0.018,IF(X32<=1.5,0.021,0.02)))))) -> 0 | AA32: =W32*Z32 -> 0 | AB32: =C32+AA32 -> 52009 | AC32: =IF(W32>='Employee Master'!P53,"YES","NO") -> NO | AD32: =IF(X32>=1.3,"Star",IF(X32>=1,"High",IF(X32>=0.8,"Meets",IF(X32>=0.6,"Below","Non-Performer")))) -> Non-Performer | AE32: 0 | AF32: =IF((I32+J32+K32)=0,0,IF((I32+J32+K32)<=300000,0.015,IF((I32+J32+K32)<=500000,0.02,0.03))) -> 0 | AG32: 0 | AH32: =1-AG32 -> 1 | AI32: =IF(AH32>=1,1,AH32) -> 1 | AJ32: =IF(AG32=0,"DST","POSP RM") -> DST
A33: 32 | B33: Indranil Roy | C33: ='Employee Master'!H54 -> 67008 | D33: ='Employee Master'!N54 -> 1340160 | W33: =((IF(U33="Yes",F33*1.25,F33)+IF(U33="Yes",IF(H33="Annual",G33,IF(H33="2-Year",G33/2*1.25,IF(H33="3-Year",G33/3*1.5,IF(H33="Quarterly/HY",G33*0.5,G33))))*1.25,IF(H33="Annual",G33,IF(H33="2-Year",G33/2*1.25,IF(H33="3-Year",G33/3*1.5,IF(H33="Quarterly/HY",G33*0.5,G33)))))+(I33+J33+K33)+(L33+M33*0.2)+IF(U33="Yes",(N33-AE33)*1.25,(N33-AE33))+(O33*0.1+P33*0.075+Q33*0.05+R33*0.1)+(S33*0.3+T33*0.15)))*AI33 -> 0 | X33: =IF(D33=0,0,W33/D33) -> 0 | Y33: =IF(X33<0.8,"Below 80%",IF(X33<=1,"80-100%",IF(X33<=1.1,"101-110%",IF(X33<=1.3,"111-130%",IF(X33<=1.5,"131-150%","150%+"))))) -> Below 80% | Z33: =IF(AJ33="DST",IF(X33<0.8,0,IF(X33<=1,0.04,IF(X33<=1.1,0.05,IF(X33<=1.3,0.06,IF(X33<=1.5,0.07,0.08))))),IF(X33<0.8,0,IF(X33<=1,0.012,IF(X33<=1.1,0.015,IF(X33<=1.3,0.018,IF(X33<=1.5,0.021,0.02)))))) -> 0 | AA33: =W33*Z33 -> 0 | AB33: =C33+AA33 -> 67008 | AC33: =IF(W33>='Employee Master'!P54,"YES","NO") -> NO | AD33: =IF(X33>=1.3,"Star",IF(X33>=1,"High",IF(X33>=0.8,"Meets",IF(X33>=0.6,"Below","Non-Performer")))) -> Non-Performer | AE33: 0 | AF33: =IF((I33+J33+K33)=0,0,IF((I33+J33+K33)<=300000,0.015,IF((I33+J33+K33)<=500000,0.02,0.03))) -> 0 | AG33: 0 | AH33: =1-AG33 -> 1 | AI33: =IF(AH33>=1,1,AH33) -> 1 | AJ33: =IF(AG33=0,"DST","POSP RM") -> DST
A34: 33 | B34: Leena Das | C34: ='Employee Master'!H55 -> 23980 | D34: ='Employee Master'!N55 -> 479600 | W34: =((IF(U34="Yes",F34*1.25,F34)+IF(U34="Yes",IF(H34="Annual",G34,IF(H34="2-Year",G34/2*1.25,IF(H34="3-Year",G34/3*1.5,IF(H34="Quarterly/HY",G34*0.5,G34))))*1.25,IF(H34="Annual",G34,IF(H34="2-Year",G34/2*1.25,IF(H34="3-Year",G34/3*1.5,IF(H34="Quarterly/HY",G34*0.5,G34)))))+(I34+J34+K34)+(L34+M34*0.2)+IF(U34="Yes",(N34-AE34)*1.25,(N34-AE34))+(O34*0.1+P34*0.075+Q34*0.05+R34*0.1)+(S34*0.3+T34*0.15)))*AI34 -> 0 | X34: =IF(D34=0,0,W34/D34) -> 0 | Y34: =IF(X34<0.8,"Below 80%",IF(X34<=1,"80-100%",IF(X34<=1.1,"101-110%",IF(X34<=1.3,"111-130%",IF(X34<=1.5,"131-150%","150%+"))))) -> Below 80% | Z34: =IF(AJ34="DST",IF(X34<0.8,0,IF(X34<=1,0.04,IF(X34<=1.1,0.05,IF(X34<=1.3,0.06,IF(X34<=1.5,0.07,0.08))))),IF(X34<0.8,0,IF(X34<=1,0.012,IF(X34<=1.1,0.015,IF(X34<=1.3,0.018,IF(X34<=1.5,0.021,0.02)))))) -> 0 | AA34: =W34*Z34 -> 0 | AB34: =C34+AA34 -> 23980 | AC34: =IF(W34>='Employee Master'!P55,"YES","NO") -> NO | AD34: =IF(X34>=1.3,"Star",IF(X34>=1,"High",IF(X34>=0.8,"Meets",IF(X34>=0.6,"Below","Non-Performer")))) -> Non-Performer | AE34: 0 | AF34: =IF((I34+J34+K34)=0,0,IF((I34+J34+K34)<=300000,0.015,IF((I34+J34+K34)<=500000,0.02,0.03))) -> 0 | AG34: 0 | AH34: =1-AG34 -> 1 | AI34: =IF(AH34>=1,1,AH34) -> 1 | AJ34: =IF(AG34=0,"DST","POSP RM") -> DST
A35: 34 | B35: Mousam Majumdar | C35: ='Employee Master'!H56 -> 67008 | D35: ='Employee Master'!N56 -> 1340160 | W35: =((IF(U35="Yes",F35*1.25,F35)+IF(U35="Yes",IF(H35="Annual",G35,IF(H35="2-Year",G35/2*1.25,IF(H35="3-Year",G35/3*1.5,IF(H35="Quarterly/HY",G35*0.5,G35))))*1.25,IF(H35="Annual",G35,IF(H35="2-Year",G35/2*1.25,IF(H35="3-Year",G35/3*1.5,IF(H35="Quarterly/HY",G35*0.5,G35)))))+(I35+J35+K35)+(L35+M35*0.2)+IF(U35="Yes",(N35-AE35)*1.25,(N35-AE35))+(O35*0.1+P35*0.075+Q35*0.05+R35*0.1)+(S35*0.3+T35*0.15)))*AI35 -> 0 | X35: =IF(D35=0,0,W35/D35) -> 0 | Y35: =IF(X35<0.8,"Below 80%",IF(X35<=1,"80-100%",IF(X35<=1.1,"101-110%",IF(X35<=1.3,"111-130%",IF(X35<=1.5,"131-150%","150%+"))))) -> Below 80% | Z35: =IF(AJ35="DST",IF(X35<0.8,0,IF(X35<=1,0.04,IF(X35<=1.1,0.05,IF(X35<=1.3,0.06,IF(X35<=1.5,0.07,0.08))))),IF(X35<0.8,0,IF(X35<=1,0.012,IF(X35<=1.1,0.015,IF(X35<=1.3,0.018,IF(X35<=1.5,0.021,0.02)))))) -> 0 | AA35: =W35*Z35 -> 0 | AB35: =C35+AA35 -> 67008 | AC35: =IF(W35>='Employee Master'!P56,"YES","NO") -> NO | AD35: =IF(X35>=1.3,"Star",IF(X35>=1,"High",IF(X35>=0.8,"Meets",IF(X35>=0.6,"Below","Non-Performer")))) -> Non-Performer | AE35: 0 | AF35: =IF((I35+J35+K35)=0,0,IF((I35+J35+K35)<=300000,0.015,IF((I35+J35+K35)<=500000,0.02,0.03))) -> 0 | AG35: 0 | AH35: =1-AG35 -> 1 | AI35: =IF(AH35>=1,1,AH35) -> 1 | AJ35: =IF(AG35=0,"DST","POSP RM") -> DST
A36: 35 | B36: Shakeeb Aamer | C36: ='Employee Master'!H57 -> 67008 | D36: ='Employee Master'!N57 -> 1340160 | W36: =((IF(U36="Yes",F36*1.25,F36)+IF(U36="Yes",IF(H36="Annual",G36,IF(H36="2-Year",G36/2*1.25,IF(H36="3-Year",G36/3*1.5,IF(H36="Quarterly/HY",G36*0.5,G36))))*1.25,IF(H36="Annual",G36,IF(H36="2-Year",G36/2*1.25,IF(H36="3-Year",G36/3*1.5,IF(H36="Quarterly/HY",G36*0.5,G36)))))+(I36+J36+K36)+(L36+M36*0.2)+IF(U36="Yes",(N36-AE36)*1.25,(N36-AE36))+(O36*0.1+P36*0.075+Q36*0.05+R36*0.1)+(S36*0.3+T36*0.15)))*AI36 -> 0 | X36: =IF(D36=0,0,W36/D36) -> 0 | Y36: =IF(X36<0.8,"Below 80%",IF(X36<=1,"80-100%",IF(X36<=1.1,"101-110%",IF(X36<=1.3,"111-130%",IF(X36<=1.5,"131-150%","150%+"))))) -> Below 80% | Z36: =IF(AJ36="DST",IF(X36<0.8,0,IF(X36<=1,0.04,IF(X36<=1.1,0.05,IF(X36<=1.3,0.06,IF(X36<=1.5,0.07,0.08))))),IF(X36<0.8,0,IF(X36<=1,0.012,IF(X36<=1.1,0.015,IF(X36<=1.3,0.018,IF(X36<=1.5,0.021,0.02)))))) -> 0 | AA36: =W36*Z36 -> 0 | AB36: =C36+AA36 -> 67008 | AC36: =IF(W36>='Employee Master'!P57,"YES","NO") -> NO | AD36: =IF(X36>=1.3,"Star",IF(X36>=1,"High",IF(X36>=0.8,"Meets",IF(X36>=0.6,"Below","Non-Performer")))) -> Non-Performer | AE36: 0 | AF36: =IF((I36+J36+K36)=0,0,IF((I36+J36+K36)<=300000,0.015,IF((I36+J36+K36)<=500000,0.02,0.03))) -> 0 | AG36: 0 | AH36: =1-AG36 -> 1 | AI36: =IF(AH36>=1,1,AH36) -> 1 | AJ36: =IF(AG36=0,"DST","POSP RM") -> DST
A37: 36 | B37: Sukanta Das | C37: ='Employee Master'!H58 -> 22429 | D37: ='Employee Master'!N58 -> 448580 | W37: =((IF(U37="Yes",F37*1.25,F37)+IF(U37="Yes",IF(H37="Annual",G37,IF(H37="2-Year",G37/2*1.25,IF(H37="3-Year",G37/3*1.5,IF(H37="Quarterly/HY",G37*0.5,G37))))*1.25,IF(H37="Annual",G37,IF(H37="2-Year",G37/2*1.25,IF(H37="3-Year",G37/3*1.5,IF(H37="Quarterly/HY",G37*0.5,G37)))))+(I37+J37+K37)+(L37+M37*0.2)+IF(U37="Yes",(N37-AE37)*1.25,(N37-AE37))+(O37*0.1+P37*0.075+Q37*0.05+R37*0.1)+(S37*0.3+T37*0.15)))*AI37 -> 0 | X37: =IF(D37=0,0,W37/D37) -> 0 | Y37: =IF(X37<0.8,"Below 80%",IF(X37<=1,"80-100%",IF(X37<=1.1,"101-110%",IF(X37<=1.3,"111-130%",IF(X37<=1.5,"131-150%","150%+"))))) -> Below 80% | Z37: =IF(AJ37="DST",IF(X37<0.8,0,IF(X37<=1,0.04,IF(X37<=1.1,0.05,IF(X37<=1.3,0.06,IF(X37<=1.5,0.07,0.08))))),IF(X37<0.8,0,IF(X37<=1,0.012,IF(X37<=1.1,0.015,IF(X37<=1.3,0.018,IF(X37<=1.5,0.021,0.02)))))) -> 0 | AA37: =W37*Z37 -> 0 | AB37: =C37+AA37 -> 22429 | AC37: =IF(W37>='Employee Master'!P58,"YES","NO") -> NO | AD37: =IF(X37>=1.3,"Star",IF(X37>=1,"High",IF(X37>=0.8,"Meets",IF(X37>=0.6,"Below","Non-Performer")))) -> Non-Performer | AE37: 0 | AF37: =IF((I37+J37+K37)=0,0,IF((I37+J37+K37)<=300000,0.015,IF((I37+J37+K37)<=500000,0.02,0.03))) -> 0 | AG37: 0 | AH37: =1-AG37 -> 1 | AI37: =IF(AH37>=1,1,AH37) -> 1 | AJ37: =IF(AG37=0,"DST","POSP RM") -> DST
A38: 37 | B38: Kabita Goswami | C38: ='Employee Master'!H58 -> 22429 | D38: ='Employee Master'!N58 -> 448580 | W38: 0 | X38: =W38/D38 -> 0 | Y38: =IF(X38<0.8,"Below 80%",IF(X38<=1,"80-100%",IF(X38<=1.1,"101-110%",IF(X38<=1.3,"111-130%",IF(X38<=1.5,"131-150%","150%+"))))) -> Below 80% | Z38: =IF(AJ38="DST",IF(X38<0.8,0,IF(X38<=1,0.04,IF(X38<=1.1,0.05,IF(X38<=1.3,0.06,IF(X38<=1.5,0.07,0.08))))),IF(X38<0.8,0,IF(X38<=1,0.012,IF(X38<=1.1,0.015,IF(X38<=1.3,0.018,IF(X38<=1.5,0.021,0.02)))))) -> 0 | AA38: =W38*Z38 -> 0 | AB38: =C38+AA38 -> 22429 | AC38: =IF(W38>='Employee Master'!P58,"YES","NO") -> NO | AD38: =IF(X38>=1.3,"Star",IF(X38>=1,"High",IF(X38>=0.8,"Meets",IF(X38>=0.6,"Below","Non-Performer")))) -> Non-Performer | AG38: 0 | AH38: =1-AG38 -> 1 | AI38: =IF(AH38>=1,1,AH38) -> 1 | AJ38: =IF(AG38=0,"DST","POSP RM") -> DST

Sheet POSP RM-CDM Incentive
A1: SECTION A: POSP RECRUITMENT INCENTIVE (Quarterly)
A2: POSPs Recruited in Quarter | B2: Per POSP Bonus
A3: 7 | B3: 200
A4: 15 | B4: 300
A5: 20+ | B5: 500
A7: SECTION B: POSP ACTIVATION INCENTIVE (Grade A = min Rs. 20K business)
A8: Active POSPs (Grade A) | B8: Per POSP Bonus
A9: 7 | B9: 300
A10: 11 | B10: 500
A11: 16 | B11: 750
A12: 20+ | B12: 1000
A14: NOTE: Active POSP = minimum Rs. 20,000 business. Motor TP-Only from PSU not counted.
A16: SECTION C: POSP INCENTIVE CALCULATOR
A17: RM/CDM Name | B17: Role | C17: Salary | D17: POSPs Recruited This Qtr | E17: Recruitment Bonus | F17: Active POSPs This Qtr | G17: Activation Bonus | H17: POSP Channel Biz | I17: Self-Business | J17: Total Weighted Biz | K17: Renewal Retention % | L17: Eligible for Incentive | M17: Quarterly POSP Incentive
A18: Partha Deb Barman | E18: =IF(D18<7,0,IF(D18<15,D18*200,IF(D18<20,D18*300,D18*500))) -> 0 | G18: =IF(F18<7,0,IF(F18<11,F18*300,IF(F18<16,F18*500,IF(F18<20,F18*750,F18*1000)))) -> 0 | J18: =H18*0.3+I18*3 -> 0 | L18: =IF(K18>=0.8,"YES","NO") -> NO | M18: =IF(L18="YES",E18+G18,0) -> 0
A19: Hemanta Saharia | E19: =IF(D19<7,0,IF(D19<15,D19*200,IF(D19<20,D19*300,D19*500))) -> 0 | G19: =IF(F19<7,0,IF(F19<11,F19*300,IF(F19<16,F19*500,IF(F19<20,F19*750,F19*1000)))) -> 0 | J19: =H19*0.3+I19*3 -> 0 | L19: =IF(K19>=0.8,"YES","NO") -> NO | M19: =IF(L19="YES",E19+G19,0) -> 0
A20: Indranil Roy | E20: =IF(D20<7,0,IF(D20<15,D20*200,IF(D20<20,D20*300,D20*500))) -> 0 | G20: =IF(F20<7,0,IF(F20<11,F20*300,IF(F20<16,F20*500,IF(F20<20,F20*750,F20*1000)))) -> 0 | J20: =H20*0.3+I20*3 -> 0 | L20: =IF(K20>=0.8,"YES","NO") -> NO | M20: =IF(L20="YES",E20+G20,0) -> 0
A21: Mousam Majumdar | E21: =IF(D21<7,0,IF(D21<15,D21*200,IF(D21<20,D21*300,D21*500))) -> 0 | G21: =IF(F21<7,0,IF(F21<11,F21*300,IF(F21<16,F21*500,IF(F21<20,F21*750,F21*1000)))) -> 0 | J21: =H21*0.3+I21*3 -> 0 | L21: =IF(K21>=0.8,"YES","NO") -> NO | M21: =IF(L21="YES",E21+G21,0) -> 0
A22: Shakeeb Aamer | E22: =IF(D22<7,0,IF(D22<15,D22*200,IF(D22<20,D22*300,D22*500))) -> 0 | G22: =IF(F22<7,0,IF(F22<11,F22*300,IF(F22<16,F22*500,IF(F22<20,F22*750,F22*1000)))) -> 0 | J22: =H22*0.3+I22*3 -> 0 | L22: =IF(K22>=0.8,"YES","NO") -> NO | M22: =IF(L22="YES",E22+G22,0) -> 0
A23: Ashis Das | E23: =IF(D23<7,0,IF(D23<15,D23*200,IF(D23<20,D23*300,D23*500))) -> 0 | G23: =IF(F23<7,0,IF(F23<11,F23*300,IF(F23<16,F23*500,IF(F23<20,F23*750,F23*1000)))) -> 0 | J23: =H23*0.3+I23*3 -> 0 | L23: =IF(K23>=0.8,"YES","NO") -> NO | M23: =IF(L23="YES",E23+G23,0) -> 0
A24: Anikendu Indra | E24: =IF(D24<7,0,IF(D24<15,D24*200,IF(D24<20,D24*300,D24*500))) -> 0 | G24: =IF(F24<7,0,IF(F24<11,F24*300,IF(F24<16,F24*500,IF(F24<20,F24*750,F24*1000)))) -> 0 | J24: =H24*0.3+I24*3 -> 0 | L24: =IF(K24>=0.8,"YES","NO") -> NO | M24: =IF(L24="YES",E24+G24,0) -> 0
A25: Leena Das | E25: =IF(D25<7,0,IF(D25<15,D25*200,IF(D25<20,D25*300,D25*500))) -> 0 | G25: =IF(F25<7,0,IF(F25<11,F25*300,IF(F25<16,F25*500,IF(F25<20,F25*750,F25*1000)))) -> 0 | J25: =H25*0.3+I25*3 -> 0 | L25: =IF(K25>=0.8,"YES","NO") -> NO | M25: =IF(L25="YES",E25+G25,0) -> 0
A26: Sukanta Das | E26: =IF(D26<7,0,IF(D26<15,D26*200,IF(D26<20,D26*300,D26*500))) -> 0 | G26: =IF(F26<7,0,IF(F26<11,F26*300,IF(F26<16,F26*500,IF(F26<20,F26*750,F26*1000)))) -> 0 | J26: =H26*0.3+I26*3 -> 0 | L26: =IF(K26>=0.8,"YES","NO") -> NO | M26: =IF(L26="YES",E26+G26,0) -> 0
A28: SECTION D: PROMOTION CRITERIA
A29: Level | B29: Rating | C29: Annual Target (Lakhs) | D29: NLA/New POSPs | E29: Active POSPs | F29: Promotion
A30: RM | B30: A | C30: 72 | D30: 21 | E30: 86 | F30: Double Promotion
A31: RM | B31: B | C31: 48 | D31: 15 | E31: 66 | F31: Single Promotion
A32: RM | B32: C | C32: 36 | D32: 12 | E32: 56 | F32: No Promotion
A33: RM | B33: D | C33: Below C | D33: - | E33: - | F33: Under Performance
A34: CDM | B34: A | C34: 117 | D34: 21 | E34: 109 | F34: Double Promotion
A35: CDM | B35: B | C35: 78 | D35: 15 | E35: 84 | F35: Single Promotion
A36: CDM | B36: C | C36: 50 | D36: 12 | E36: 60 | F36: No Promotion
A38: SECTION E: PERFORMANCE ALLOWANCE (Monthly)
A39: Rating | B39: Target Achievement | C39: Monthly Allowance
A40: Excellent | B40: 130%+ | C40: 3000
A41: Standard | B41: 100% | C41: 2000
A42: Average | B42: 80% | C42: 0
A43: Under Performance | B43: <80% | C43: 0

Sheet Profit Center P&L
A1: Vertical | B1: Gross Revenue (Prem) | C1: Commission Earned | D1: Credit Against Target | E1: Incentive Paid | F1: Net Profit | G1: Team Size | H1: Revenue per Capita | I1: Profit per Capita | J1: % Contribution
A2: LIFE | D2: 0 | E2: 0 | F2: =C2-E2 -> 0 | H2: =IF(G2=0,0,B2/G2) -> 0 | I2: =IF(G2=0,0,F2/G2) -> 0 | J2: 0
A3: HEALTH | D3: 0 | E3: 0 | F3: =C3-E3 -> 0 | H3: =IF(G3=0,0,B3/G3) -> 0 | I3: =IF(G3=0,0,F3/G3) -> 0 | J3: 0
A4: G.I. | D4: 0 | E4: 0 | F4: =C4-E4 -> 0 | H4: =IF(G4=0,0,B4/G4) -> 0 | I4: =IF(G4=0,0,F4/G4) -> 0 | J4: 0
A5: F.P. | D5: 0 | E5: 0 | F5: =C5-E5 -> 0 | H5: =IF(G5=0,0,B5/G5) -> 0 | I5: =IF(G5=0,0,F5/G5) -> 0 | J5: 0
A6: OPERATION | D6: 0 | E6: 0 | F6: =C6-E6 -> 0 | H6: =IF(G6=0,0,B6/G6) -> 0 | I6: =IF(G6=0,0,F6/G6) -> 0 | J6: 0
A7: DEMAT | D7: 0 | E7: 0 | F7: =C7-E7 -> 0 | H7: =IF(G7=0,0,B7/G7) -> 0 | I7: =IF(G7=0,0,F7/G7) -> 0 | J7: 0
A8: POSP | D8: 0 | E8: 0 | F8: =C8-E8 -> 0 | H8: =IF(G8=0,0,B8/G8) -> 0 | I8: =IF(G8=0,0,F8/G8) -> 0 | J8: 0
A9: DIGITAL & IT | D9: 0 | E9: 0 | F9: =C9-E9 -> 0 | H9: =IF(G9=0,0,B9/G9) -> 0 | I9: =IF(G9=0,0,F9/G9) -> 0 | J9: 0
A10: ADMIN | D10: 0 | E10: 0 | F10: =C10-E10 -> 0 | H10: =IF(G10=0,0,B10/G10) -> 0 | I10: =IF(G10=0,0,F10/G10) -> 0 | J10: 0
A11: ACCOUNTS | D11: 0 | E11: 0 | F11: =C11-E11 -> 0 | H11: =IF(G11=0,0,B11/G11) -> 0 | I11: =IF(G11=0,0,F11/G11) -> 0 | J11: 0
A12: TOTAL

Sheet Hiring ROI Calculator
A1: HIRING ROI CALCULATOR
A3: Scenario 1: Average Sales RM
A4: Annual CTC | B4: 600000
A5: Month 1 | B5: 50000 | C5: =B5-600000/12 -> 0
A6: Month 2-3 (avg) | B6: 75000 | C6: =B6-600000/12 -> 25000
A7: Month 4-6 (avg) | B7: 100000 | C7: =B7-600000/12 -> 50000
A8: Year 2 | B8: 150000 | C8: =B8-600000/12 -> 100000
A9: Break-even (months) | B9: 3-4
A10: Year 1 ROI | B10: 45%
A12: Scenario 2: High Performer RM
A13: Annual CTC | B13: 600000
A14: Month 1 | B14: 80000 | C14: =B14-600000/12 -> 30000
A15: Month 2-3 (avg) | B15: 120000 | C15: =B15-600000/12 -> 70000
A16: Month 4-6 (avg) | B16: 180000 | C16: =B16-600000/12 -> 130000
A17: Year 2 | B17: 250000 | C17: =B17-600000/12 -> 200000
A18: Break-even (months) | B18: 3-4
A19: Year 1 ROI | B19: 45%
A21: Scenario 3: Kolkata Expansion
A22: Annual CTC | B22: 4500000
A23: Month 1 | B23: 150000 | C23: =B23-4500000/12 -> -225000
A24: Month 2-3 (avg) | B24: 250000 | C24: =B24-4500000/12 -> -125000
A25: Month 4-6 (avg) | B25: 400000 | C25: =B25-4500000/12 -> 25000
A26: Year 2 | B26: 600000 | C26: =B26-4500000/12 -> 225000
A27: Break-even (months) | B27: 3-4
A28: Year 1 ROI | B28: 45%

Sheet GI Margin Reference
A1: Insurer | B1: Product | C1: Discount % | D1: Payout % | E1: Net Margin % | F1: Policy Type | G1: Preferred
A2: Shriram | B2: Private Car Petrol | C2: 85 | D2: 21 | E2: 15 | F2: OD+TP | G2: Yes
A3: Shriram | B3: GCCV LCV | C3: 85 | D3: 44 | E3: 8 | F3: OD+TP | G3: Yes
A4: Shriram | B4: Two Wheeler | C4: 60 | D4: 18 | E4: 12 | F4: OD+TP | G4: Yes
A5: Shriram | B5: TP Only | C5: 75 | D5: 8 | E5: 17 | F5: TP | G5: No
A6: TATA AIG | B6: Private Car | C6: 70 | D6: 18 | E6: 12 | F6: OD+TP | G6: Yes
A7: TATA AIG | B7: CV | C7: 80 | D7: 40 | E7: 8 | F7: OD+TP | G7: Yes
A8: TATA AIG | B8: Two Wheeler | C8: 65 | D8: 16 | E8: 10 | F8: OD+TP | G8: Yes
A9: TATA AIG | B9: TP Only | C9: 70 | D9: 8 | E9: 15 | F9: TP | G9: No
A10: ICICI Lombard | B10: Private Car | C10: 70 | D10: 17 | E10: 13 | F10: OD+TP | G10: Yes
A11: ICICI Lombard | B11: CV | C11: 75 | D11: 38 | E11: 10 | F11: OD+TP | G11: Yes
A12: ICICI Lombard | B12: Two Wheeler | C12: 60 | D12: 15 | E12: 12 | F12: OD+TP | G12: Yes
A13: ICICI Lombard | B13: TP Only | C13: 68 | D13: 7 | E13: 16 | F13: TP | G13: No
... A21: Axis Bank | B21: Health Group | C21: 20 | D21: 15 | E21: 70 | F21: GMC | G21: Yes

Sheet Maker-Checker FP Log
A1: Date | B1: Client Name | C1: RM Name | D1: FP Data Complete? | E1: Investment Details? | F1: Risk Profile Done? | G1: Goal Planning Done? | H1: Reporting Manager | I1: Manager Verification | J1: Verification Date | K1: 125% Credit Eligible? | L1: Remarks
A2: 46082 | B2: Raj Kummar | C2: Vinita Kabra | D2: 2026-03-01 | E2: Raj Kummar | F2: Vinita Kabra | G2: Yes | H2: Tamanna Kejriwal | I2: Verified | J2: 46083 | K2: =IF(AND(D2="Yes",E2="Yes",F2="Yes",G2="Yes",I2="Verified"),"YES","NO") -> NO
A3: 46086 | B3: Priya Sharma | C3: Sudarshana Gupta | D3: 2026-03-05 | E3: Priya Sharma | F3: Sudarshana Gupta | G3: Yes | H3: Tamanna Kejriwal | I3: Pending | K3: =IF(AND(D3="Yes",E3="Yes",F3="Yes",G3="Yes",I3="Verified"),"YES","NO") -> NO
A4: 46089 | B4: Arjun Mehta | C4: Jasmine Jain | D4: 2026-03-08 | E4: Arjun Mehta | F4: Jasmine Jain | G4: Yes | H4: Tamanna Kejriwal | I4: Verified | J4: 46090 | K4: =IF(AND(D4="Yes",E4="Yes",F4="Yes",G4="Yes",I4="Verified"),"YES","NO") -> NO
A5: 46093 | B5: Sneha Das | C5: Banshika Agarwal | D5: 2026-03-12 | E5: Sneha Das | F5: Banshika Agarwal | G5: Partial | H5: Tamanna Kejriwal | I5: Rejected | J5: 46094 | K5: =IF(AND(D5="Yes",E5="Yes",F5="Yes",G5="Yes",I5="Verified"),"YES","NO") -> NO
A6: 46096 | B6: Ravi Singh | C6: Jinu Lagachu | D6: 2026-03-15 | E6: Ravi Singh | F6: Jinu Lagachu | G6: Yes | H6: Tamanna Kejriwal | I6: Verified | J6: 46097 | K6: =IF(AND(D6="Yes",E6="Yes",F6="Yes",G6="Yes",I6="Verified"),"YES","NO") -> NO

Sheet Promotion & Career
A1: CAREER PROGRESSION LADDER
A3: Designation | B3: Criteria | C3: CTC Range | D3: Typical Progression | E3: Key Responsibility
A4: Intern | B4: Fresh graduate | C4: 6000 | D4: 0-3 months | E4: Training & Mentoring
A5: Executive | B5: Sales Executive | C5: 22000 | D5: 3-6 months | E5: Market Exposure
A6: Senior Executive | B6: Proven Sales Track | C6: 35000 | D6: 1-2 years | E6: Client Management
A7: Relationship Manager | B7: Consistent High Performer | C7: 50000 | D7: 2-4 years | E7: Portfolio Building
A8: Area Manager | B8: Excellent Track Record | C8: 80000 | D8: 4-6 years | E8: Team Leadership
A9: Branch Manager | B9: Strategic Leadership | C9: 120000 | D9: 6+ years | E9: Branch P&L
A10: Regional Manager | B10: Multi-branch Leadership | C10: 150000 | D10: 8+ years | E10: Regional Growth
A11: Senior Regional Manager | B11: Strategic Leadership | C11: 200000 | D11: 10+ years | E11: Network Expansion
A12: CDM (Channel Dev Mgr) | B12: POSP Network Building | C12: 100000 | D12: Specialized Track | E12: Franchise Development

Sheet 5-Year Projection
A1: Metric | B1: FY27 | C1: FY28 | D1: FY29 | E1: FY30 | F1: FY31 | G1: CAGR %
A2: Gross Premium Income (Cr) | B2: 25 | C2: 32.5 | D2: 42.25 | E2: 54.92 | F2: 71.4 | G2: Target: 30%+ ROI
A3: Team Size | B3: 65 | C3: 80 | D3: 100 | E3: 120 | F3: 140 | G3: Expansion target
A4: Revenue per Capita (Lakhs) | B4: 38.5 | C4: 40.6 | D4: 42.3 | E4: 45.8 | F4: 51 | G4: Productivity target
A5: Profit Before Incentive (Cr) | B5: 8 | C5: 10.5 | D5: 13.8 | E5: 17.9 | F5: 23.3 | G5: 45% margin target
A6: Incentive Payout % of Gross | B6: 15 | C6: 14.5 | D6: 14 | E6: 13.5 | F6: 13 | G6: Efficiency improvement

Sheet Admin Controls
A1: ADMIN CONTROLS & ACCESS MATRIX
A3: USER ROLE | B3: VIEW ACCESS | C3: EDIT ACCESS | D3: APPROVAL RIGHTS
A4: Admin | B4: All Sheets | C4: All Sheets | D4: All Changes
A5: Finance | B5: P&L, Incentive, Trail | C5: P&L, Salary | D5: Yes
A6: HR Manager | B6: Employee Master, Promo | C6: Employee Master | D6: Yes
A7: Sales Manager | B7: Monthly Incentive, Trail | C7: Own Department | D7: Own Team
A8: Sales Executive | B8: Own Performance, Trail | C8: Own Inputs | D8: No
A9: HR | B9: All Employee Data | C9: Employee Master | D9: No
A12: AUDIT LOG TEMPLATE
A13: Date | B13: User | C13: Sheet | D13: Cell Reference | E13: Old Value | F13: New Value | G13: Reason

Sheet Terms & Conditions
A1: TRUSTNER GROUP - INCENTIVE FRAMEWORK TERMS & CONDITIONS
A3: SECTION 1: TARGET STRUCTURE
A4: Category | B4: Target Formula | C4: Notes
A5: Direct Sales / FP Team | B5: 6× Monthly Salary (Monthly Target) | C5: Monthly target = Salary × 6
A6: CDM / RM handling POSP | B6: 20× Monthly Salary (Monthly Target) | C6: Higher target - POSP channel volume required for profitability
A7: Area Managers | B7: 20× (Salary + 15% Variable) Monthly | C7: 15% added as proxy for office rent, support staff where actuals unavailable
A8: HO/RO Shared Facility | B8: +15% of total cost as variable expenses | C8: Applied to Area Managers & above where rental/support details not available
A9: POSP with Higher Payouts | B9: Target adjusted upward proportionately | C9: If POSP payout is higher, target increases to maintain profitability
A10: Support / Back Office | B10: No sales target | C10: Eligible for support bonus based on department performance
A12: SECTION 2: MF SIP CREDIT & CLAWBACK
A13: Rule | B13: Detail
A14: SECTION 8: PRODUCT TIER SYSTEM | B14: 100% of that month's SIP business ONLY | C14: No annualization (not Monthly × 12)
A15: • Tier 1 (>30% commission): 100% credit for DST, proportionate for channel | B15: Company earns ~0.5% trail on MF = ~₹500 on ₹10K SIP. After GST & expenses, margin is thin.
A16: • Tier 2 (15-30%): 75% credit for DST | B16: If any SIP is stopped or redeemed, the amount is DEBITED from that month's weighted business
A17: • Tier 3 (<15%): 50% credit for DST | B17: Anti-misselling tool. Discourages start-stop behavior by agents/RMs.
A18: • Channel business: Credit = Company margin % × Tier credit | B18: Approx 3-4% on credited business (not on annualized value)
A20: SECTION 9: MARGIN-BASED INCENTIVE RULES
A21: • DST incentive slabs: 4-8%, multiplier 1.0-2.0x | B21: Incentive Rule | C21: Reference
A22: • POSP RM slabs (70/30): 1.2-2.0%, multiplier 1.0-2.0x | B22: Follow TATA AIG Sitara-style payout slabs | C22: Cannot pay flat 3-4% on motor - margins vary by product
A23: • Target adjustment: (30%/margin%) × base target | B23: Slab-based: Target+upto ₹3L = 1.5%, ₹3L-5L = 2%, ₹5L+ = 3% | C23: Based on basic premium above target, paid quarterly
A24: • Lower margin = lower incentive, proportionally scaled | B24: 15% credit only. Lower incentive rate proportionate to margin.
A25: POSP - Normal Payout Grade | B25: 30% credit. Standard incentive slabs apply.
A26: SECTION 10: TRAIL ON INCREMENTAL AUM ONLY | B26: Proportionately LESS incentive. Higher POSP payout = lower company margin = lower RM incentive.
A27: • Starting/handed-over AUM: Zero trail | B27: Incentive is proportionate to company earnings. Person working with higher-margin products earns more than one working with high-payout POSPs.
A28: • Incremental AUM, existing client: 15% trail share
A29: • Incremental AUM, new PAN: 25% trail share
A30: • Sub-broker managed: 30% of eligible rate × margin factor | B30: Included in Target Base
A31: • Franchise: 10% of eligible rate | B31: Yes - full CTC
A32: • SIP clawback continues to apply | B32: Yes - monthly rental of branch office
A33: Support Staff Cost | B33: Yes - back office, admin at branch
A34: Sales Team under AM | B34: Yes - all team member costs
A35: HO/RO Facility Share | B35: 15% of direct reporting's cost attributed as facilities charge
A36: Target Calculation | B36: 20× Total Cost (all above components combined)
A38: SECTION 5: PROFIT CENTER APPROACH (Senior Management)
A39: Level | B39: Bonus % | C39: Calculated On
A40: L2 (Vertical Head) | B40: 8-12% | C40: Actual vertical profit AFTER all costs including attrition
A41: L3 (Zonal Head) | B41: 5-8% | C41: Actual vertical profit AFTER all costs including attrition
A42: L4 (Regional Manager) | B42: 3-5% | C42: Actual vertical profit AFTER all costs including attrition
A43: L5 (Branch Manager) | B43: 2-4% | C43: Actual vertical profit AFTER all costs including attrition
A44: Attrition Cost | B44: 100% to hiring manager if exit <3 months, 50% if 3-6 months
A46: SECTION 6: GENERAL RULES
A47: Rule | B47: Detail
A48: System-Driven | B48: All calculations are automatic. Only Super Admin (Ram Shah & Sangita Shah) can override.
A49: Two Criteria Mandatory | B49: Minimum 2 criteria must be met for quarterly/yearly incentive qualification
A50: Active POSP Definition | B50: Minimum ₹20,000 business. Motor TP-Only from PSU insurers NOT counted.
A51: Renewal Retention | B51: >80% renewal retention required for RM/CDM to earn incentives
A52: FP Route 125% Credit | B52: Requires: (1) Complete Financial Plan data (2) Maker-Checker verification by Super Admin
A53: Directors' Business | B53: Business from Ram/Sangita Shah credited at 30% to handling RM
A54: Firm's Code Business | B54: Double credit in target AND incentives (per TATA AIA Sitara reference)
A55: Performance Allowance | B55: Excellent (130%+) = ₹3,000/month, Standard (100%) = ₹2,000/month, Below = NIL
A57: SECTION 7: LISTED COMPANY COMPLIANCE
A58: Requirement | B58: Implementation
A59: Audit Trail | B59: Every override/change logged with date, user, old value, new value, reason
A60: Maker-Checker | B60: All FP Route 125% credits require dual verification
A61: Role-Based Access | B61: Admin/Finance/HR/Sales Manager/Executive - tiered access matrix
A62: SEBI/IRDAI Ready | B62: Framework designed for regulatory audit compliance
A63: Board Governance | B63: Quarterly incentive reports to Board with P&L impact analysis
A65: Document Version: 2.1 | Effective: FY 2026-27 | Approved by: Ram Shah, Director
A66: Trustner Group reserves the right to modify terms with/without prior notice.

Sheet ESOP & Phantom Stock
A1: TRUSTNER GROUP — ESOP & PHANTOM STOCK PLAN
A3: SECTION A: PLAN PARAMETERS
A4: Parameter | B4: Value | C4: Notes
A5: Total ESOP Pool (% of equity) | B5: 5.0% | C5: SEBI compliant; Board-approved pool. Source: SEBI SBEB Regulations 2021
A6: Pre-IPO Company Valuation (₹ Cr) | B6: 50 | C6: Estimated pre-money. Update annually with auditor sign-off.
A7: Total Shares Outstanding | B7: 1000000 | C7: Notional for phantom stock calculation
A8: ESOP Pool Shares | B8: =B7*B5 -> 50000 | C8: Auto-calculated from pool %
A9: Price per Phantom Unit (₹) | B9: =B6*10000000/B7 -> 500 | C9: Valuation ÷ shares. Updates with revaluation.
A10: Vesting Schedule | B10: 4 years | C10: 25% per year after 1-year cliff
A11: Cliff Period | B11: 1 year | C11: No vesting before 12 months of service
A12: Exercise Window Post-Vesting | B12: 5 years | C12: Must exercise within 5 years of vesting
A13: Accelerated Vesting on IPO | B13: 100% | C13: All unvested units vest on IPO listing date
A14: Good Leaver Treatment | B14: Pro-rata vested | C14: Vested units retained; unvested forfeited
A15: Bad Leaver Treatment | B15: Full forfeiture | C15: All units (vested + unvested) forfeited
A16: Lock-in Post Exercise | B16: 1 year | C16: SEBI minimum for listed entity post-IPO
A17: Settlement Mode (Pre-IPO) | B17: Cash (Phantom) | C17: Cash-settled at latest valuation; no actual shares until listing
A18: Settlement Mode (Post-IPO) | B18: Equity (ESOP) | C18: Converted to actual ESOP on listing
A19: Tax Event | B19: On exercise/allotment | C19: Perquisite tax as per IT Act. Source: Section 17(2)(vi)
A22: SECTION B: ELIGIBILITY & ALLOCATION MATRIX
A23: Level | B23: Designation | C23: Eligible? | D23: Phantom Units (Annual Grant) | E23: Year 1 Vest | F23: Year 2 Vest | G23: Year 3 Vest | H23: Year 4 Vest
A24: L1 | B24: Director / Promoter | C24: No | D24: 0 | E24: 0 | F24: 0 | G24: 0 | H24: 0
A25: L2 | B25: CDO / Vertical Head | C25: Yes | D25: 5000 | E25: =D24*0 -> 0 | F25: =D24*0.25 -> 0 | G25: =D24*0.25 -> 0 | H25: =D24*0.25 -> 0
A26: L3 | B26: Regional Manager / Sales Head | C26: Yes | D26: 3000 | E26: =D25*0 -> 0 | F26: =D25*0.25 -> 1250 | G26: =D25*0.25 -> 1250 | H26: =D25*0.25 -> 1250
A27: L4 | B27: Area Manager / CDM | C27: Yes | D27: 2000 | E27: =D26*0 -> 0 | F27: =D26*0.25 -> 750 | G27: =D26*0.25 -> 750 | H27: =D26*0.25 -> 750
A28: L5 | B28: Sr. RM / Team Leader | C28: Yes | D28: 1000 | E28: =D27*0 -> 0 | F28: =D27*0.25 -> 500 | G28: =D27*0.25 -> 500 | H28: =D27*0.25 -> 500
A29: L6 | B29: RM / Executive (2+ yrs) | C29: Yes | D29: 500 | E29: =D28*0 -> 0 | F29: =D28*0.25 -> 250 | G29: =D28*0.25 -> 250 | H29: =D28*0.25 -> 250
A30: L7 | B30: Support / Back Office (3+ yrs) | C30: Yes | D30: 250 | E30: =D29*0 -> 0 | F30: =D29*0.25 -> 125 | G30: =D29*0.25 -> 125 | H30: =D29*0.25 -> 125
A31: L8 | B31: New Joinee (<1 yr) | C31: No | D31: 0 | E31: 0 | F31: 0 | G31: 0 | H31: 0
A33: SECTION C: INDIVIDUAL VESTING & VALUE CALCULATOR
A34: Employee Name | B34: Level | C34: Grant Date | D34: Units Granted | E34: Unit Price (₹) | F34: Year 1 (Cliff) | G34: Year 2 Vested | H34: Year 3 Vested | I34: Year 4 Vested | J34: Total Vested Value (₹)
A35: Abir Das | B35: L2 | C35: 2026-04-01 | D35: 5000 | E35: =$B$9 -> 500 | F35: 0 | G35: =D35*0.25 -> 1250 | H35: =D35*0.25 -> 1250 | I35: =D35*0.25 -> 1250 | J35: =(F35+G35+H35+I35)*E35 -> 1875000
A36: Partha Deb Barman | B36: L3 | C36: 2026-04-01 | D36: 3000 | E36: =$B$9 -> 500 | F36: 0 | G36: =D36*0.25 -> 750 | H36: =D36*0.25 -> 750 | I36: =D36*0.25 -> 750 | J36: =(F36+G36+H36+I36)*E36 -> 1125000
A37: Bhola Singh | B37: L4 | C37: 2026-04-01 | D37: 2000 | E37: =$B$9 -> 500 | F37: 0 | G37: =D37*0.25 -> 500 | H37: =D37*0.25 -> 500 | I37: =D37*0.25 -> 500 | J37: =(F37+G37+H37+I37)*E37 -> 750000
A38: Tamanna Kejriwal | B38: L4 | C38: 2026-04-01 | D38: 2000 | E38: =$B$9 -> 500 | F38: 0 | G38: =D38*0.25 -> 500 | H38: =D38*0.25 -> 500 | I38: =D38*0.25 -> 500 | J38: =(F38+G38+H38+I38)*E38 -> 750000
A39: Mrinmoy Choudhury | B39: L4 | C39: 2026-04-01 | D39: 2000 | E39: =$B$9 -> 500 | F39: 0 | G39: =D39*0.25 -> 500 | H39: =D39*0.25 -> 500 | I39: =D39*0.25 -> 500 | J39: =(F39+G39+H39+I39)*E39 -> 750000
A40: Ajanta Saikia | B40: L5 | C40: 2026-04-01 | D40: 1000 | E40: =$B$9 -> 500 | F40: 0 | G40: =D40*0.25 -> 250 | H40: =D40*0.25 -> 250 | I40: =D40*0.25 -> 250 | J40: =(F40+G40+H40+I40)*E40 -> 375000
A41: Hemanta Saharia | B41: L5 | C41: 2026-04-01 | D41: 1000 | E41: =$B$9 -> 500 | F41: 0 | G41: =D41*0.25 -> 250 | H41: =D41*0.25 -> 250 | I41: =D41*0.25 -> 250 | J41: =(F41+G41+H41+I41)*E41 -> 375000
A42: Indranil Roy | B42: L5 | C42: 2026-04-01 | D42: 1000 | E42: =$B$9 -> 500 | F42: 0 | G42: =D42*0.25 -> 250 | H42: =D42*0.25 -> 250 | I42: =D42*0.25 -> 250 | J42: =(F42+G42+H42+I42)*E42 -> 375000
A43: Dipankar Das | B43: L6 | C43: 2026-04-01 | D43: 500 | E43: =$B$9 -> 500 | F43: 0 | G43: =D43*0.25 -> 125 | H43: =D43*0.25 -> 125 | I43: =D43*0.25 -> 125 | J43: =(F43+G43+H43+I43)*E43 -> 187500
A44: Vinita Kabra | B44: L6 | C44: 2026-04-01 | D44: 500 | E44: =$B$9 -> 500 | F44: 0 | G44: =D44*0.25 -> 125 | H44: =D44*0.25 -> 125 | I44: =D44*0.25 -> 125 | J44: =(F44+G44+H44+I44)*E44 -> 187500
A45: TOTAL POOL UTILIZATION | D45: =SUM(D35:D44) -> 18000 | J45: =SUM(J35:J44) -> 6750000
A46: POOL REMAINING | D46: =$B$8-D45 -> 32000
A48: NOTE: On IPO (target 2030), all unvested phantom units convert to ESOPs and vest immediately. Pre-IPO cash settlement at latest Board-approved valuation.

Sheet Balanced Scorecard
A1: TRUSTNER GROUP — BALANCED SCORECARD
A3: DIMENSION WEIGHTS (must sum to 100%)
A4: Dimension | B4: Weight | C4: Sales Roles | D4: Manager Roles | E4: Support Roles
A5: Financial | B5: 0.4 | C5: 0.5 | D5: 0.35 | E5: 0.2
A6: Customer | B6: 0.25 | C6: 0.2 | D6: 0.25 | E6: 0.3
A7: Process | B7: 0.2 | C7: 0.15 | D7: 0.25 | E7: 0.3
A8: Learning & Growth | B8: 0.15 | C8: 0.15 | D8: 0.15 | E8: 0.2
A9: TOTAL | B9: =SUM(B5:B8) -> 1 | C9: =SUM(C5:C8) -> 1 | D9: =SUM(D5:D8) -> 1 | E9: =SUM(E5:E8) -> 1
A12: DETAILED KPI FRAMEWORK
A13: Dimension | B13: KPI | C13: Measure | D13: Target (100%) | E13: Stretch (120%) | F13: Weight | G13: Actual | H13: Score | I13: Weighted Score
A14: Financial | B14: Revenue vs Target | C14: ₹ Monthly Weighted Business ÷ Monthly Target | D14: 100% | E14: 130% | F14: 0.15 | H14: 0 | I14: =H14*F14 -> 0
A15: Financial | B15: Profit Contribution | C15: Vertical P&L Profit % | D15: 10% | E15: 20% | F15: 0.1 | H15: 0 | I15: =H15*F15 -> 0
A16: Financial | B16: Cost-to-Income Ratio | C16: Total cost ÷ Revenue | D16: <35% | E16: <25% | F16: 0.08 | H16: 0 | I16: =H16*F16 -> 0
A17: Financial | B17: New Business Growth | C17: YoY new premium growth % | D17: 20% | E17: 40% | F17: 0.07 | H17: 0 | I17: =H17*F17 -> 0
A18: Customer | B18: Client NPS Score | C18: Net Promoter Score (survey) | D18: 50 | E18: 75 | F18: 0.08 | H18: 0 | I18: =H18*F18 -> 0
A19: Customer | B19: Client Retention Rate | C19: Renewals retained ÷ Total due | D19: 80% | E19: 95% | F19: 0.07 | H19: 0 | I19: =H19*F19 -> 0
A20: Customer | B20: Complaint Resolution | C20: % resolved within SLA | D20: 90% | E20: 100% | F20: 0.05 | H20: 0 | I20: =H20*F20 -> 0
A21: Customer | B21: Cross-sell Ratio | C21: Avg products per client | D21: 1.5 | E21: 2.5 | F21: 0.05 | H21: 0 | I21: =H21*F21 -> 0
A22: Process | B22: Policy Issuance TAT | C22: Avg days from proposal to issuance | D22: 3 days | E22: 1 day | F22: 0.06 | H22: 0 | I22: =H22*F22 -> 0
A23: Process | B23: Documentation Accuracy | C23: % error-free submissions | D23: 95% | E23: 100% | F23: 0.05 | H23: 0 | I23: =H23*F23 -> 0
A24: Process | B24: KYC Compliance Score | C24: % KYC complete & current | D24: 100% | E24: 100% | F24: 0.05 | H24: 0 | I24: =H24*F24 -> 0
A25: Process | B25: Mis-selling Incidents | C25: Count of validated complaints | D25: 0 | E25: 0 | F25: 0.04 | H25: 0 | I25: =H25*F25 -> 0
... A29: Learning & Growth | B29: Digital Adoption | C29: % transactions via platform | D29: 70% | E29: 90% | F29: 0.02 | H29: 0 | I29: =H29*F29 -> 0
A30: COMPOSITE SCORE | F30: =SUM(F14:F29) -> 1 | I30: =SUM(I14:I29) -> 0
A32: COMPLIANCE SCORECARD MULTIPLIER
A33: Compliance Factor | B33: Status | C33: Multiplier
A34: Zero mis-selling complaints | B34: Yes | C34: 1
A35: KYC 100% compliant | B35: Yes | C35: 1
A36: No regulatory observations | B36: Yes | C36: 1
A37: Audit score > 90% | B37: Yes | C37: 1
A38: Timely MIS submission | B38: Yes | C38: 1
A39: FINAL COMPLIANCE MULTIPLIER | C39: =IF(COUNTIF(B34:B38,"No")>0,0.8,IF(COUNTIF(B34:B38,"Yes")=5,1.1,1)) -> 1.1
A41: FINAL ADJUSTED INCENTIVE | C41: =I30*C39 -> 0 | E41: ← Composite Score × Compliance Multiplier = Final Payout Factor

Sheet Deferred Bonus
A1: TRUSTNER GROUP — DEFERRED BONUS & CLAWBACK STRUCTURE
A3: SECTION A: DEFERRED BONUS RULES
A4: Parameter | B4: Value | C4: Applicability
A5: Immediate Payout % | B5: 60% | C5: Paid within 30 days of quarter-end
A6: Deferred Payout % | B6: 40% | C6: Held for 2 years, released in equal halves
A7: Deferred Tranche 1 | B7: 20% | C7: Released after Year 1 if no clawback trigger
A8: Deferred Tranche 2 | B8: 20% | C8: Released after Year 2 if no clawback trigger
A9: Eligible Levels | B9: L2 to L4 | C9: CDO, Vertical Heads, Regional Managers, Area Managers
A10: Minimum Bonus to Defer | B10: ₹50,000 | C10: Below this, full amount paid immediately
A13: SECTION B: CLAWBACK TRIGGERS
A14: Trigger Event | B14: Clawback % | C14: Applied To | D14: Authority
A15: Vertical underperforms vs prior year | B15: 50% | C15: Deferred balance | D15: Board / Super Admin
A16: Compliance breach / regulatory penalty | B16: 100% | C16: Deferred balance | D16: Board / Super Admin
A17: Mis-selling proven against team | B17: 100% | C17: Deferred balance | D17: Super Admin
A18: Voluntary resignation before deferral release | B18: 100% | C18: Unvested deferred balance | D18: Automatic
A19: Team attrition >30% in deferral period | B19: 25% | C19: Deferred balance | D19: HR Committee
A20: Fraud / embezzlement | B20: 100% | C20: ALL (immediate + deferred) | D20: Board + Legal
A21: Client complaint upheld by regulator | B21: 50% | C21: Deferred balance | D21: Compliance Officer
A24: SECTION C: DEFERRED BONUS CALCULATOR
A25: Employee | B25: Level | C25: Gross Bonus (₹) | D25: Immediate 60% (₹) | E25: Deferred 40% (₹) | F25: Tranche 1 (Yr 1) | G25: Tranche 2 (Yr 2) | H25: Clawback Trigger? | I25: Clawback % | J25: Net Deferred Payout (₹)
A26: Abir Das | B26: L2 | C26: 0 | D26: =IF(C26<50000,C26,C26*0.6) -> 0 | E26: =IF(C26<50000,0,C26*0.4) -> 0 | F26: =E26*0.5 -> 0 | G26: =E26*0.5 -> 0 | H26: No | I26: 0 | J26: =E26*(1-I26) -> 0
A27: Partha Deb Barman | B27: L3 | C27: 0 | D27: =IF(C27<50000,C27,C27*0.6) -> 0 | E27: =IF(C27<50000,0,C27*0.4) -> 0 | F27: =E27*0.5 -> 0 | G27: =E27*0.5 -> 0 | H27: No | I27: 0 | J27: =E27*(1-I27) -> 0
A28: Bhola Singh | B28: L4 | C28: 0 | D28: =IF(C28<50000,C28,C28*0.6) -> 0 | E28: =IF(C28<50000,0,C28*0.4) -> 0 | F28: =E28*0.5 -> 0 | G28: =E28*0.5 -> 0 | H28: No | I28: 0 | J28: =E28*(1-I28) -> 0
A29: Tamanna Kejriwal | B29: L4 | C29: 0 | D29: =IF(C29<50000,C29,C29*0.6) -> 0 | E29: =IF(C29<50000,0,C29*0.4) -> 0 | F29: =E29*0.5 -> 0 | G29: =E29*0.5 -> 0 | H29: No | I29: 0 | J29: =E29*(1-I29) -> 0
A30: Mrinmoy Choudhury | B30: L4 | C30: 0 | D30: =IF(C30<50000,C30,C30*0.6) -> 0 | E30: =IF(C30<50000,0,C30*0.4) -> 0 | F30: =E30*0.5 -> 0 | G30: =E30*0.5 -> 0 | H30: No | I30: 0 | J30: =E30*(1-I30) -> 0
A31: Ajanta Saikia | B31: L5 | C31: 0 | D31: =IF(C31<50000,C31,C31*0.6) -> 0 | E31: =IF(C31<50000,0,C31*0.4) -> 0 | F31: =E31*0.5 -> 0 | G31: =E31*0.5 -> 0 | H31: No | I31: 0 | J31: =E31*(1-I31) -> 0
A32: Hemanta Saharia | B32: L5 | C32: 0 | D32: =IF(C32<50000,C32,C32*0.6) -> 0 | E32: =IF(C32<50000,0,C32*0.4) -> 0 | F32: =E32*0.5 -> 0 | G32: =E32*0.5 -> 0 | H32: No | I32: 0 | J32: =E32*(1-I32) -> 0
A33: TOTAL | C33: =SUM(C26:C32) -> 0 | D33: =SUM(D26:D32) -> 0 | E33: =SUM(E26:E32) -> 0 | F33: =SUM(F26:F32) -> 0 | G33: =SUM(G26:G32) -> 0 | J33: =SUM(J26:J32) -> 0

Sheet CLV Bonus
A1: TRUSTNER GROUP — CUSTOMER LIFETIME VALUE (CLV) BONUS
A3: SECTION A: CLV TIER STRUCTURE
A4: Tier | B4: Client Book CLV (₹) | C4: Annual Bonus (₹) | D4: Frequency | E4: Eligibility | F4: Rationale
A5: Bronze | B5: ₹1L – ₹5L cumulative premium | C5: 5000 | D5: Annual | E5: All RMs, 1+ year tenure | F5: Rewards early relationship building
A6: Silver | B6: ₹5L – ₹15L cumulative premium | C6: 15000 | D6: Annual | E6: All RMs, 1+ year tenure | F6: Growing multi-product relationships
A7: Gold | B7: ₹15L – ₹30L cumulative premium | C7: 35000 | D7: Annual | E7: All RMs, 2+ year tenure | F7: High-value advisory relationships
A8: Platinum | B8: ₹30L – ₹50L cumulative premium | C8: 60000 | D8: Annual | E8: Senior RMs, 2+ year tenure | F8: Premium client management
A9: Diamond | B9: ₹50L+ cumulative premium | C9: 100000 | D9: Annual | E9: Top performers, 3+ year tenure | F9: Elite relationship managers — wealth advisory level
A12: SECTION B: CLV CALCULATION RULES
A13: Component | B13: Included in CLV? | C13: Calculation
A14: Life Insurance Premium (all years) | B14: Yes | C14: Cumulative annual premium paid by client across all policies
A15: Health Insurance Premium (all years) | B15: Yes | C15: Cumulative annual premium including renewals
A16: GI Premium (all years) | B16: Yes | C16: Motor + Non-Motor + GMC cumulative
A17: MF AUM (current) | B17: Yes | C17: Current AUM at NAV (not purchase value)
A18: MF SIP (annualized) | B18: Yes | C18: Monthly SIP × 12 for current running SIPs only
A19: Demat AUM | B19: Yes | C19: Current portfolio value
A20: Loan Products (if any) | B20: No | C20: Not counted — different vertical
A21: Lapsed / Surrendered Policies | B21: Deducted | C21: Surrender value deducted from CLV
A22: Stopped SIPs | B22: Deducted | C22: Annualized stopped SIP deducted from CLV
A25: SECTION C: RM-WISE CLV BONUS CALCULATOR
A26: RM Name | B26: Life Cum (₹) | C26: Health Cum (₹) | D26: GI Cum (₹) | E26: MF AUM (₹) | F26: Total CLV (₹) | G26: Tier | H26: Annual Bonus (₹) | I26: Tenure Check
A27: Balbinder Kaur | B27: 0 | C27: 0 | D27: 0 | E27: 0 | F27: =SUM(B27:E27) -> 0 | G27: =IF(F27>=5000000,"Diamond",IF(F27>=3000000,"Platinum",IF(F27>=1500000,"Gold",IF(F27>=500000,"Silver",IF(F27>=100000,"Bronze","Below Threshold"))))) -> Below Threshold | H27: =IF(G27="Diamond",100000,IF(G27="Platinum",60000,IF(G27="Gold",35000,IF(G27="Silver",15000,IF(G27="Bronze",5000,0))))) -> 0 | I27: OK
A28: Ajanta Saikia | B28: 0 | C28: 0 | D28: 0 | E28: 0 | F28: =SUM(B28:E28) -> 0 | G28: =IF(F28>=5000000,"Diamond",IF(F28>=3000000,"Platinum",IF(F28>=1500000,"Gold",IF(F28>=500000,"Silver",IF(F28>=100000,"Bronze","Below Threshold"))))) -> Below Threshold | H28: =IF(G28="Diamond",100000,IF(G28="Platinum",60000,IF(G28="Gold",35000,IF(G28="Silver",15000,IF(G28="Bronze",5000,0))))) -> 0 | I28: OK
A29: Akash Kumar | B29: 0 | C29: 0 | D29: 0 | E29: 0 | F29: =SUM(B29:E29) -> 0 | G29: =IF(F29>=5000000,"Diamond",IF(F29>=3000000,"Platinum",IF(F29>=1500000,"Gold",IF(F29>=500000,"Silver",IF(F29>=100000,"Bronze","Below Threshold"))))) -> Below Threshold | H29: =IF(G29="Diamond",100000,IF(G29="Platinum",60000,IF(G29="Gold",35000,IF(G29="Silver",15000,IF(G29="Bronze",5000,0))))) -> 0 | I29: OK
A30: Jitender Roy | B30: 0 | C30: 0 | D30: 0 | E30: 0 | F30: =SUM(B30:E30) -> 0 | G30: =IF(F30>=5000000,"Diamond",IF(F30>=3000000,"Platinum",IF(F30>=1500000,"Gold",IF(F30>=500000,"Silver",IF(F30>=100000,"Bronze","Below Threshold"))))) -> Below Threshold | H30: =IF(G30="Diamond",100000,IF(G30="Platinum",60000,IF(G30="Gold",35000,IF(G30="Silver",15000,IF(G30="Bronze",5000,0))))) -> 0 | I30: OK
A31: Rafiqueddin Ahmed | B31: 0 | C31: 0 | D31: 0 | E31: 0 | F31: =SUM(B31:E31) -> 0 | G31: =IF(F31>=5000000,"Diamond",IF(F31>=3000000,"Platinum",IF(F31>=1500000,"Gold",IF(F31>=500000,"Silver",IF(F31>=100000,"Bronze","Below Threshold"))))) -> Below Threshold | H31: =IF(G31="Diamond",100000,IF(G31="Platinum",60000,IF(G31="Gold",35000,IF(G31="Silver",15000,IF(G31="Bronze",5000,0))))) -> 0 | I31: OK
A32: Tamanna Kejriwal | B32: 0 | C32: 0 | D32: 0 | E32: 0 | F32: =SUM(B32:E32) -> 0 | G32: =IF(F32>=5000000,"Diamond",IF(F32>=3000000,"Platinum",IF(F32>=1500000,"Gold",IF(F32>=500000,"Silver",IF(F32>=100000,"Bronze","Below Threshold"))))) -> Below Threshold | H32: =IF(G32="Diamond",100000,IF(G32="Platinum",60000,IF(G32="Gold",35000,IF(G32="Silver",15000,IF(G32="Bronze",5000,0))))) -> 0 | I32: OK
A33: Laxman Sharma | B33: 0 | C33: 0 | D33: 0 | E33: 0 | F33: =SUM(B33:E33) -> 0 | G33: =IF(F33>=5000000,"Diamond",IF(F33>=3000000,"Platinum",IF(F33>=1500000,"Gold",IF(F33>=500000,"Silver",IF(F33>=100000,"Bronze","Below Threshold"))))) -> Below Threshold | H33: =IF(G33="Diamond",100000,IF(G33="Platinum",60000,IF(G33="Gold",35000,IF(G33="Silver",15000,IF(G33="Bronze",5000,0))))) -> 0 | I33: OK
A34: Bhola Singh | B34: 0 | C34: 0 | D34: 0 | E34: 0 | F34: =SUM(B34:E34) -> 0 | G34: =IF(F34>=5000000,"Diamond",IF(F34>=3000000,"Platinum",IF(F34>=1500000,"Gold",IF(F34>=500000,"Silver",IF(F34>=100000,"Bronze","Below Threshold"))))) -> Below Threshold | H34: =IF(G34="Diamond",100000,IF(G34="Platinum",60000,IF(G34="Gold",35000,IF(G34="Silver",15000,IF(G34="Bronze",5000,0))))) -> 0 | I34: OK
A35: Harshita Jalan | B35: 0 | C35: 0 | D35: 0 | E35: 0 | F35: =SUM(B35:E35) -> 0 | G35: =IF(F35>=5000000,"Diamond",IF(F35>=3000000,"Platinum",IF(F35>=1500000,"Gold",IF(F35>=500000,"Silver",IF(F35>=100000,"Bronze","Below Threshold"))))) -> Below Threshold | H35: =IF(G35="Diamond",100000,IF(G35="Platinum",60000,IF(G35="Gold",35000,IF(G35="Silver",15000,IF(G35="Bronze",5000,0))))) -> 0 | I35: OK
A36: Raj Das | B36: 0 | C36: 0 | D36: 0 | E36: 0 | F36: =SUM(B36:E36) -> 0 | G36: =IF(F36>=5000000,"Diamond",IF(F36>=3000000,"Platinum",IF(F36>=1500000,"Gold",IF(F36>=500000,"Silver",IF(F36>=100000,"Bronze","Below Threshold"))))) -> Below Threshold | H36: =IF(G36="Diamond",100000,IF(G36="Platinum",60000,IF(G36="Gold",35000,IF(G36="Silver",15000,IF(G36="Bronze",5000,0))))) -> 0 | I36: OK
A37: Vinita Kabra | B37: 0 | C37: 0 | D37: 0 | E37: 0 | F37: =SUM(B37:E37) -> 0 | G37: =IF(F37>=5000000,"Diamond",IF(F37>=3000000,"Platinum",IF(F37>=1500000,"Gold",IF(F37>=500000,"Silver",IF(F37>=100000,"Bronze","Below Threshold"))))) -> Below Threshold | H37: =IF(G37="Diamond",100000,IF(G37="Platinum",60000,IF(G37="Gold",35000,IF(G37="Silver",15000,IF(G37="Bronze",5000,0))))) -> 0 | I37: OK
A38: Sudeep Kashyap | B38: 0 | C38: 0 | D38: 0 | E38: 0 | F38: =SUM(B38:E38) -> 0 | G38: =IF(F38>=5000000,"Diamond",IF(F38>=3000000,"Platinum",IF(F38>=1500000,"Gold",IF(F38>=500000,"Silver",IF(F38>=100000,"Bronze","Below Threshold"))))) -> Below Threshold | H38: =IF(G38="Diamond",100000,IF(G38="Platinum",60000,IF(G38="Gold",35000,IF(G38="Silver",15000,IF(G38="Bronze",5000,0))))) -> 0 | I38: OK
... A46: Banshika Agarwal | B46: 0 | C46: 0 | D46: 0 | E46: 0 | F46: =SUM(B46:E46) -> 0 | G46: =IF(F46>=5000000,"Diamond",IF(F46>=3000000,"Platinum",IF(F46>=1500000,"Gold",IF(F46>=500000,"Silver",IF(F46>=100000,"Bronze","Below Threshold"))))) -> Below Threshold | H46: =IF(G46="Diamond",100000,IF(G46="Platinum",60000,IF(G46="Gold",35000,IF(G46="Silver",15000,IF(G46="Bronze",5000,0))))) -> 0 | I46: OK
A47: TOTAL CLV BONUS PAYOUT | H47: =SUM(H27:H46) -> 0
A50: SECTION D: TEAM BUILDING BONUS (Managers)
A51: Manager | B51: Team Size | C51: Team Retention % | D51: Team Target Ach % | E51: Qualifies? | F51: Bonus (₹) | G51: Notes
A52: Abir Das | B52: 0 | C52: 0 | D52: 0 | E52: =IF(AND(C52>=0.9,D52>=1),"YES","NO") -> NO | F52: =IF(E52="YES",50000,0) -> 0 | G52: Team retention >90% AND collective target >100%
A53: Partha Deb Barman | B53: 0 | C53: 0 | D53: 0 | E53: =IF(AND(C53>=0.9,D53>=1),"YES","NO") -> NO | F53: =IF(E53="YES",50000,0) -> 0 | G53: Team retention >90% AND collective target >100%
A54: Bhola Singh | B54: 0 | C54: 0 | D54: 0 | E54: =IF(AND(C54>=0.9,D54>=1),"YES","NO") -> NO | F54: =IF(E54="YES",50000,0) -> 0 | G54: Team retention >90% AND collective target >100%
A55: Tamanna Kejriwal | B55: 0 | C55: 0 | D55: 0 | E55: =IF(AND(C55>=0.9,D55>=1),"YES","NO") -> NO | F55: =IF(E55="YES",50000,0) -> 0 | G55: Team retention >90% AND collective target >100%
A56: Mrinmoy Choudhury | B56: 0 | C56: 0 | D56: 0 | E56: =IF(AND(C56>=0.9,D56>=1),"YES","NO") -> NO | F56: =IF(E56="YES",50000,0) -> 0 | G56: Team retention >90% AND collective target >100%
A57: Ajanta Saikia | B57: 0 | C57: 0 | D57: 0 | E57: =IF(AND(C57>=0.9,D57>=1),"YES","NO") -> NO | F57: =IF(E57="YES",50000,0) -> 0 | G57: Team retention >90% AND collective target >100%
A58: Hemanta Saharia | B58: 0 | C58: 0 | D58: 0 | E58: =IF(AND(C58>=0.9,D58>=1),"YES","NO") -> NO | F58: =IF(E58="YES",50000,0) -> 0 | G58: Team retention >90% AND collective target >100%
A59: Dipankar Das | B59: 0 | C59: 0 | D59: 0 | E59: =IF(AND(C59>=0.9,D59>=1),"YES","NO") -> NO | F59: =IF(E59="YES",50000,0) -> 0 | G59: Team retention >90% AND collective target >100%
