Workbook

Sheet Employee Master
A1: Name | B1: Code | C1: DOJ | D1: Designation | E1: Department | F1: Job Resp | G1: Gross Salary | H1: Entity | I1: Annual CTC | J1: Tenure (Years) | K1: Level Code | L1: Target Multiplier | M1: Monthly Target | N1: Annual Target | O1: Cost Recovery Min
A2: Balbinder Kaur | B2: TAS001 | C2: 41334 | D2: Inhouse Sales Manager | E2: OPERATION | F2: SALES | G2: 36017 | H2: TAS | I2: =G2*12 -> 432204 | J2: =IF(ISBLANK(C2),"",YEARFRAC(C2,TODAY())) -> 13.077778 | K2: =IFERROR(VLOOKUP(D2,$A$19:$C$200,2,0),"L6") -> L6 | L2: =IFERROR(VLOOKUP(D2,$A$19:$C$200,3,0),0) -> 0 | M2: =G2*L2 -> 0 | N2: =M2*12 -> 0 | O2: =G2*1.6 -> 57627.2
A3: Pranab Kumar Barman | B3: TAS002 | C3: 41897 | D3: Office Assistant | E3: OPERATION | F3: ADMIN | G3: 21429 | H3: TAS | I3: =G3*12 -> 257148 | J3: =IF(ISBLANK(C3),"",YEARFRAC(C3,TODAY())) -> 11.538889 | K3: =IFERROR(VLOOKUP(D3,$A$19:$C$200,2,0),"L6") -> L6 | L3: =IFERROR(VLOOKUP(D3,$A$19:$C$200,3,0),0) -> 0 | M3: =G3*L3 -> 0 | N3: =M3*12 -> 0 | O3: =G3*1.6 -> 34286.4
A4: Ajanta Saikia | B4: TAS003 | C4: 43496 | D4: Field Force Multiplier | E4: LIFE | F4: SALES | G4: 99751 | H4: TIB | I4: =G4*12 -> 1197012 | J4: =IF(ISBLANK(C4),"",YEARFRAC(C4,TODAY())) -> 7.1638889 | K4: =IFERROR(VLOOKUP(D4,$A$19:$C$200,2,0),"L6") -> L6 | L4: =IFERROR(VLOOKUP(D4,$A$19:$C$200,3,0),0) -> 0 | M4: =G4*L4 -> 0 | N4: =M4*12 -> 0 | O4: =G4*1.6 -> 159601.6
A5: Akash Kumar | B5: TAS004 | C5: 44075 | D5: Executive | E5: HEALTH | F5: SALES | G5: 22449 | H5: TIB | I5: =G5*12 -> 269388 | J5: =IF(ISBLANK(C5),"",YEARFRAC(C5,TODAY())) -> 5.5777778 | K5: =IFERROR(VLOOKUP(D5,$A$19:$C$200,2,0),"L6") -> L6 | L5: =IFERROR(VLOOKUP(D5,$A$19:$C$200,3,0),0) -> 0 | M5: =G5*L5 -> 0 | N5: =M5*12 -> 0 | O5: =G5*1.6 -> 35918.4
A6: Nipa Das | B6: TAS005 | C6: 44151 | D6: Back Office Executive | E6: OPERATION | F6: Back Office | G6: 22263 | H6: TAS | I6: =G6*12 -> 267156 | J6: =IF(ISBLANK(C6),"",YEARFRAC(C6,TODAY())) -> 5.3694444 | K6: =IFERROR(VLOOKUP(D6,$A$19:$C$200,2,0),"L6") -> L6 | L6: =IFERROR(VLOOKUP(D6,$A$19:$C$200,3,0),0) -> 0 | M6: =G6*L6 -> 0 | N6: =M6*12 -> 0 | O6: =G6*1.6 -> 35620.8
A7: Jitender Roy | B7: TAS006 | C7: 44383 | D7: Relationship Manager | E7: HEALTH | F7: SALES | G7: 40440 | H7: TIB | I7: =G7*12 -> 485280 | J7: =IF(ISBLANK(C7),"",YEARFRAC(C7,TODAY())) -> 4.7305556 | K7: =IFERROR(VLOOKUP(D7,$A$19:$C$200,2,0),"L6") -> L6 | L7: =IFERROR(VLOOKUP(D7,$A$19:$C$200,3,0),0) -> 0 | M7: =G7*L7 -> 0 | N7: =M7*12 -> 0 | O7: =G7*1.6 -> 64704
A8: Rafiqueddin Ahmed | B8: TAS051 | C8: 44386 | D8: Mentor | E8: OPERATION | F8: SALES | G8: 30000 | H8: TAS | I8: =G8*12 -> 360000 | J8: =IF(ISBLANK(C8),"",YEARFRAC(C8,TODAY())) -> 4.7222222 | K8: =IFERROR(VLOOKUP(D8,$A$19:$C$200,2,0),"L6") -> L6 | L8: =IFERROR(VLOOKUP(D8,$A$19:$C$200,3,0),0) -> 0 | M8: =G8*L8 -> 0 | N8: =M8*12 -> 0 | O8: =G8*1.6 -> 48000
A9: Pranita Saikia | B9: TAS008 | C9: 44406 | D9: Back Office Executive | E9: G.I. | F9: Back Office | G9: 34500 | H9: TIB | I9: =G9*12 -> 414000 | J9: =IF(ISBLANK(C9),"",YEARFRAC(C9,TODAY())) -> 4.6666667 | K9: =IFERROR(VLOOKUP(D9,$A$19:$C$200,2,0),"L6") -> L6 | L9: =IFERROR(VLOOKUP(D9,$A$19:$C$200,3,0),0) -> 0 | M9: =G9*L9 -> 0 | N9: =M9*12 -> 0 | O9: =G9*1.6 -> 55200
A10: Tamanna Kejriwal | B10: TAS009 | C10: 44734 | D10: Sales Head | E10: F.P. | F10: SALES | G10: 90000 | H10: TAS | I10: =G10*12 -> 1080000 | J10: =IF(ISBLANK(C10),"",YEARFRAC(C10,TODAY())) -> 3.7694444 | K10: =IFERROR(VLOOKUP(D10,$A$19:$C$200,2,0),"L6") -> L6 | L10: =IFERROR(VLOOKUP(D10,$A$19:$C$200,3,0),0) -> 0 | M10: =G10*L10 -> 0 | N10: =M10*12 -> 0 | O10: =G10*1.6 -> 144000
A11: Shivani Kumari | B11: TAS013 | C11: 44805 | D11: Back Office Executive | E11: OPERATION | F11: Back Office | G11: 16749 | H11: TAS | I11: =G11*12 -> 200988 | J11: =IF(ISBLANK(C11),"",YEARFRAC(C11,TODAY())) -> 3.5777778 | K11: =IFERROR(VLOOKUP(D11,$A$19:$C$200,2,0),"L6") -> L6 | L11: =IFERROR(VLOOKUP(D11,$A$19:$C$200,3,0),0) -> 0 | M11: =G11*L11 -> 0 | N11: =M11*12 -> 0 | O11: =G11*1.6 -> 26798.4
A12: Rinjima Pathak Das | B12: TAS014 | C12: 44929 | D12: HR Manager | E12: ADMIN | F12: HR & ADMIN | G12: 46876 | H12: TIB | I12: =G12*12 -> 562512 | J12: =IF(ISBLANK(C12),"",YEARFRAC(C12,TODAY())) -> 3.2388889 | K12: =IFERROR(VLOOKUP(D12,$A$19:$C$200,2,0),"L6") -> L6 | L12: =IFERROR(VLOOKUP(D12,$A$19:$C$200,3,0),0) -> 0 | M12: =G12*L12 -> 0 | N12: =M12*12 -> 0 | O12: =G12*1.6 -> 75001.6
A13: Nayanjyoti Handique | B13: TAS016 | C13: 44977 | D13: Operation Manager | E13: HEALTH | F13: Claims | G13: 29700 | H13: TIB | I13: =G13*12 -> 356400 | J13: =IF(ISBLANK(C13),"",YEARFRAC(C13,TODAY())) -> 3.1083333 | K13: =IFERROR(VLOOKUP(D13,$A$19:$C$200,2,0),"L6") -> L6 | L13: =IFERROR(VLOOKUP(D13,$A$19:$C$200,3,0),0) -> 0 | M13: =G13*L13 -> 0 | N13: =M13*12 -> 0 | O13: =G13*1.6 -> 47520
... A59: Kabita Goswami | B59: TAS105 | C59: 45999 | D59: Relationship Manager | E59: OPERATION | F59: SALES | G59: 41008 | H59: TIB | I59: =G59*12 -> 492096 | J59: =IF(ISBLANK(C59),"",YEARFRAC(C59,TODAY())) -> 0.30833333 | K59: =IFERROR(VLOOKUP(D59,$A$19:$C$200,2,0),"L6") -> L6 | L59: =IFERROR(VLOOKUP(D59,$A$19:$C$200,3,0),0) -> 0 | M59: =G59*L59 -> 0 | N59: =M59*12 -> 0 | O59: =G59*1.6 -> 65612.8
A60: Housekeeping (Vendor) | B60: - | D60: Outsourced | E60: ADMIN | F60: Support | G60: 12000 | H60: Vendor | I60: =G60*12 -> 144000 | K60: =IFERROR(VLOOKUP(D60,$A$19:$C$200,2,0),"L6") -> L6 | L60: =IFERROR(VLOOKUP(D60,$A$19:$C$200,3,0),0) -> 0 | M60: =G60*L60 -> 0 | N60: =M60*12 -> 0 | O60: =G60*1.6 -> 19200
A61: Security (Vendor) | B61: - | D61: Outsourced | E61: ADMIN | F61: Support | G61: 15000 | H61: Vendor | I61: =G61*12 -> 180000 | K61: =IFERROR(VLOOKUP(D61,$A$19:$C$200,2,0),"L6") -> L6 | L61: =IFERROR(VLOOKUP(D61,$A$19:$C$200,3,0),0) -> 0 | M61: =G61*L61 -> 0 | N61: =M61*12 -> 0 | O61: =G61*1.6 -> 24000
A62: Office Boy (Vendor) | B62: - | D62: Outsourced | E62: ADMIN | F62: Support | G62: 10000 | H62: Vendor | I62: =G62*12 -> 120000 | K62: =IFERROR(VLOOKUP(D62,$A$19:$C$200,2,0),"L6") -> L6 | L62: =IFERROR(VLOOKUP(D62,$A$19:$C$200,3,0),0) -> 0 | M62: =G62*L62 -> 0 | N62: =M62*12 -> 0 | O62: =G62*1.6 -> 16000

Sheet Incentive Slabs
A1: Achievement % | B1: Min | C1: Max | D1: Base Rate | E1: Multiplier | F1: Status
A2: <80% | B2: 0 | C2: 80 | D2: 0 | E2: 0 | F2: No Incentive
A3: 80-100% | B3: 80 | C3: 100 | D3: 0.04 | E3: 1 | F3: Base
A4: 101-110% | B4: 101 | C4: 110 | D4: 0.04 | E4: 1 | F4: Standard
A5: 111-130% | B5: 111 | C5: 130 | D5: 0.046 | E5: 1.15 | F5: Enhanced
A6: 131-150% | B6: 131 | C6: 150 | D6: 0.05 | E6: 1.25 | F6: Super
A7: 150%+ | B7: 150 | C7: 999999 | D7: 0.06 | E7: 1.5 | F7: Champion
A10: Product Credit Table
A11: Product Type | B11: Credit %
A12: Life 10 Pay+ | B12: 1.25
A13: Life Below 10 Pay | B13: 1
A14: Life ULIP Regular | B14: 0.25
A15: Life Single Premium | B15: 0.1
A16: Health Insurance | B16: 1
A17: General Insurance | B17: 0.5
A18: MF SIP (annualized) | B18: 0.5
A19: MF Lumpsum | B19: 1
A20: Loans/LS | B20: 0.05
A21: Business from Directors | B21: 0.3
A24: Trail Sharing Rates
A25: Source Type | B25: RM % | C25: Mgmt % | D25: Company %
A26: Self-sourced | B26: 0.25 | C26: 0.15 | D26: 0.6
A27: Assigned + New Business | B27: 0.15 | C27: 0.1 | D27: 0.75
A28: Assigned + No New Business | B28: 0 | C28: 0.05 | D28: 0.95
A29: Office/Walk-in | B29: 0.1 | C29: 0.1 | D29: 0.8

Sheet Monthly Incentive Calculator
A1: Employee Name | B1: Salary | C1: Monthly Target | D1: Month | E1: Life Ins Biz | F1: Health Ins Biz | G1: GI Biz | H1: MF SIP Biz | I1: MF Lumpsum Biz | J1: Other Biz | K1: Weighted Business | L1: Achievement % | M1: Slab Applied | N1: Incentive Rate | O1: Incentive Amount | P1: Total Earning | Q1: Cost Justified | R1: Performance Status
A2: Balbinder Kaur | B2: 36017 | C2: =B2*2 -> 72034 | K2: =E2*1.25+F2+G2*0.5+H2*0.5+I2+J2 -> 0 | L2: =IF(C2=0,0,K2/C2) -> 0 | M2: =IF(L2<0.8,"No Incentive",IF(L2<1,"Base",IF(L2<1.11,"Standard",IF(L2<1.31,"Enhanced",IF(L2<1.51,"Super","Champion"))))) -> No Incentive | N2: =IF(L2<0.8,0,IF(L2<1,0.04,IF(L2<1.11,0.04,IF(L2<1.31,0.046,IF(L2<1.51,0.05,0.06))))) -> 0 | O2: =K2*N2 -> 0 | P2: =B2+O2 -> 36017 | Q2: =IF(K2>=(B2*1.6),"YES","NO") -> NO | R2: =IF(L2<0.8,"Below Target",IF(L2<1,"At Target",IF(L2<1.3,"Above Target","Excellent"))) -> Below Target
A3: Ajanta Saikia | B3: 99751 | C3: =B3*2 -> 199502 | K3: =E3*1.25+F3+G3*0.5+H3*0.5+I3+J3 -> 0 | L3: =IF(C3=0,0,K3/C3) -> 0 | M3: =IF(L3<0.8,"No Incentive",IF(L3<1,"Base",IF(L3<1.11,"Standard",IF(L3<1.31,"Enhanced",IF(L3<1.51,"Super","Champion"))))) -> No Incentive | N3: =IF(L3<0.8,0,IF(L3<1,0.04,IF(L3<1.11,0.04,IF(L3<1.31,0.046,IF(L3<1.51,0.05,0.06))))) -> 0 | O3: =K3*N3 -> 0 | P3: =B3+O3 -> 99751 | Q3: =IF(K3>=(B3*1.6),"YES","NO") -> NO | R3: =IF(L3<0.8,"Below Target",IF(L3<1,"At Target",IF(L3<1.3,"Above Target","Excellent"))) -> Below Target
A4: Akash Kumar | B4: 22449 | C4: =B4*2 -> 44898 | K4: =E4*1.25+F4+G4*0.5+H4*0.5+I4+J4 -> 0 | L4: =IF(C4=0,0,K4/C4) -> 0 | M4: =IF(L4<0.8,"No Incentive",IF(L4<1,"Base",IF(L4<1.11,"Standard",IF(L4<1.31,"Enhanced",IF(L4<1.51,"Super","Champion"))))) -> No Incentive | N4: =IF(L4<0.8,0,IF(L4<1,0.04,IF(L4<1.11,0.04,IF(L4<1.31,0.046,IF(L4<1.51,0.05,0.06))))) -> 0 | O4: =K4*N4 -> 0 | P4: =B4+O4 -> 22449 | Q4: =IF(K4>=(B4*1.6),"YES","NO") -> NO | R4: =IF(L4<0.8,"Below Target",IF(L4<1,"At Target",IF(L4<1.3,"Above Target","Excellent"))) -> Below Target
A5: Jitender Roy | B5: 40440 | C5: =B5*2 -> 80880 | K5: =E5*1.25+F5+G5*0.5+H5*0.5+I5+J5 -> 0 | L5: =IF(C5=0,0,K5/C5) -> 0 | M5: =IF(L5<0.8,"No Incentive",IF(L5<1,"Base",IF(L5<1.11,"Standard",IF(L5<1.31,"Enhanced",IF(L5<1.51,"Super","Champion"))))) -> No Incentive | N5: =IF(L5<0.8,0,IF(L5<1,0.04,IF(L5<1.11,0.04,IF(L5<1.31,0.046,IF(L5<1.51,0.05,0.06))))) -> 0 | O5: =K5*N5 -> 0 | P5: =B5+O5 -> 40440 | Q5: =IF(K5>=(B5*1.6),"YES","NO") -> NO | R5: =IF(L5<0.8,"Below Target",IF(L5<1,"At Target",IF(L5<1.3,"Above Target","Excellent"))) -> Below Target
A6: Rafiqueddin Ahmed | B6: 30000 | C6: =B6*2 -> 60000 | K6: =E6*1.25+F6+G6*0.5+H6*0.5+I6+J6 -> 0 | L6: =IF(C6=0,0,K6/C6) -> 0 | M6: =IF(L6<0.8,"No Incentive",IF(L6<1,"Base",IF(L6<1.11,"Standard",IF(L6<1.31,"Enhanced",IF(L6<1.51,"Super","Champion"))))) -> No Incentive | N6: =IF(L6<0.8,0,IF(L6<1,0.04,IF(L6<1.11,0.04,IF(L6<1.31,0.046,IF(L6<1.51,0.05,0.06))))) -> 0 | O6: =K6*N6 -> 0 | P6: =B6+O6 -> 30000 | Q6: =IF(K6>=(B6*1.6),"YES","NO") -> NO | R6: =IF(L6<0.8,"Below Target",IF(L6<1,"At Target",IF(L6<1.3,"Above Target","Excellent"))) -> Below Target
A7: Tamanna Kejriwal | B7: 90000 | C7: =B7*2 -> 180000 | K7: =E7*1.25+F7+G7*0.5+H7*0.5+I7+J7 -> 0 | L7: =IF(C7=0,0,K7/C7) -> 0 | M7: =IF(L7<0.8,"No Incentive",IF(L7<1,"Base",IF(L7<1.11,"Standard",IF(L7<1.31,"Enhanced",IF(L7<1.51,"Super","Champion"))))) -> No Incentive | N7: =IF(L7<0.8,0,IF(L7<1,0.04,IF(L7<1.11,0.04,IF(L7<1.31,0.046,IF(L7<1.51,0.05,0.06))))) -> 0 | O7: =K7*N7 -> 0 | P7: =B7+O7 -> 90000 | Q7: =IF(K7>=(B7*1.6),"YES","NO") -> NO | R7: =IF(L7<0.8,"Below Target",IF(L7<1,"At Target",IF(L7<1.3,"Above Target","Excellent"))) -> Below Target
A8: Laxman Sharma | B8: 43700 | C8: =B8*2 -> 87400 | K8: =E8*1.25+F8+G8*0.5+H8*0.5+I8+J8 -> 0 | L8: =IF(C8=0,0,K8/C8) -> 0 | M8: =IF(L8<0.8,"No Incentive",IF(L8<1,"Base",IF(L8<1.11,"Standard",IF(L8<1.31,"Enhanced",IF(L8<1.51,"Super","Champion"))))) -> No Incentive | N8: =IF(L8<0.8,0,IF(L8<1,0.04,IF(L8<1.11,0.04,IF(L8<1.31,0.046,IF(L8<1.51,0.05,0.06))))) -> 0 | O8: =K8*N8 -> 0 | P8: =B8+O8 -> 43700 | Q8: =IF(K8>=(B8*1.6),"YES","NO") -> NO | R8: =IF(L8<0.8,"Below Target",IF(L8<1,"At Target",IF(L8<1.3,"Above Target","Excellent"))) -> Below Target
A9: Bhola Singh | B9: 103500 | C9: =B9*2 -> 207000 | K9: =E9*1.25+F9+G9*0.5+H9*0.5+I9+J9 -> 0 | L9: =IF(C9=0,0,K9/C9) -> 0 | M9: =IF(L9<0.8,"No Incentive",IF(L9<1,"Base",IF(L9<1.11,"Standard",IF(L9<1.31,"Enhanced",IF(L9<1.51,"Super","Champion"))))) -> No Incentive | N9: =IF(L9<0.8,0,IF(L9<1,0.04,IF(L9<1.11,0.04,IF(L9<1.31,0.046,IF(L9<1.51,0.05,0.06))))) -> 0 | O9: =K9*N9 -> 0 | P9: =B9+O9 -> 103500 | Q9: =IF(K9>=(B9*1.6),"YES","NO") -> NO | R9: =IF(L9<0.8,"Below Target",IF(L9<1,"At Target",IF(L9<1.3,"Above Target","Excellent"))) -> Below Target
A10: Harshita Jalan | B10: 18011 | C10: =B10*2 -> 36022 | K10: =E10*1.25+F10+G10*0.5+H10*0.5+I10+J10 -> 0 | L10: =IF(C10=0,0,K10/C10) -> 0 | M10: =IF(L10<0.8,"No Incentive",IF(L10<1,"Base",IF(L10<1.11,"Standard",IF(L10<1.31,"Enhanced",IF(L10<1.51,"Super","Champion"))))) -> No Incentive | N10: =IF(L10<0.8,0,IF(L10<1,0.04,IF(L10<1.11,0.04,IF(L10<1.31,0.046,IF(L10<1.51,0.05,0.06))))) -> 0 | O10: =K10*N10 -> 0 | P10: =B10+O10 -> 18011 | Q10: =IF(K10>=(B10*1.6),"YES","NO") -> NO | R10: =IF(L10<0.8,"Below Target",IF(L10<1,"At Target",IF(L10<1.3,"Above Target","Excellent"))) -> Below Target
A11: Raj Das | B11: 27008 | C11: =B11*2 -> 54016 | K11: =E11*1.25+F11+G11*0.5+H11*0.5+I11+J11 -> 0 | L11: =IF(C11=0,0,K11/C11) -> 0 | M11: =IF(L11<0.8,"No Incentive",IF(L11<1,"Base",IF(L11<1.11,"Standard",IF(L11<1.31,"Enhanced",IF(L11<1.51,"Super","Champion"))))) -> No Incentive | N11: =IF(L11<0.8,0,IF(L11<1,0.04,IF(L11<1.11,0.04,IF(L11<1.31,0.046,IF(L11<1.51,0.05,0.06))))) -> 0 | O11: =K11*N11 -> 0 | P11: =B11+O11 -> 27008 | Q11: =IF(K11>=(B11*1.6),"YES","NO") -> NO | R11: =IF(L11<0.8,"Below Target",IF(L11<1,"At Target",IF(L11<1.3,"Above Target","Excellent"))) -> Below Target
A12: Vinita Kabra | B12: 43200 | C12: =B12*2 -> 86400 | K12: =E12*1.25+F12+G12*0.5+H12*0.5+I12+J12 -> 0 | L12: =IF(C12=0,0,K12/C12) -> 0 | M12: =IF(L12<0.8,"No Incentive",IF(L12<1,"Base",IF(L12<1.11,"Standard",IF(L12<1.31,"Enhanced",IF(L12<1.51,"Super","Champion"))))) -> No Incentive | N12: =IF(L12<0.8,0,IF(L12<1,0.04,IF(L12<1.11,0.04,IF(L12<1.31,0.046,IF(L12<1.51,0.05,0.06))))) -> 0 | O12: =K12*N12 -> 0 | P12: =B12+O12 -> 43200 | Q12: =IF(K12>=(B12*1.6),"YES","NO") -> NO | R12: =IF(L12<0.8,"Below Target",IF(L12<1,"At Target",IF(L12<1.3,"Above Target","Excellent"))) -> Below Target
A13: Sudeep Kashyap | B13: 28200 | C13: =B13*2 -> 56400 | K13: =E13*1.25+F13+G13*0.5+H13*0.5+I13+J13 -> 0 | L13: =IF(C13=0,0,K13/C13) -> 0 | M13: =IF(L13<0.8,"No Incentive",IF(L13<1,"Base",IF(L13<1.11,"Standard",IF(L13<1.31,"Enhanced",IF(L13<1.51,"Super","Champion"))))) -> No Incentive | N13: =IF(L13<0.8,0,IF(L13<1,0.04,IF(L13<1.11,0.04,IF(L13<1.31,0.046,IF(L13<1.51,0.05,0.06))))) -> 0 | O13: =K13*N13 -> 0 | P13: =B13+O13 -> 28200 | Q13: =IF(K13>=(B13*1.6),"YES","NO") -> NO | R13: =IF(L13<0.8,"Below Target",IF(L13<1,"At Target",IF(L13<1.3,"Above Target","Excellent"))) -> Below Target
... A38: Kabita Goswami | B38: 41008 | C38: =B38*2 -> 82016 | K38: =E38*1.25+F38+G38*0.5+H38*0.5+I38+J38 -> 0 | L38: =IF(C38=0,0,K38/C38) -> 0 | M38: =IF(L38<0.8,"No Incentive",IF(L38<1,"Base",IF(L38<1.11,"Standard",IF(L38<1.31,"Enhanced",IF(L38<1.51,"Super","Champion"))))) -> No Incentive | N38: =IF(L38<0.8,0,IF(L38<1,0.04,IF(L38<1.11,0.04,IF(L38<1.31,0.046,IF(L38<1.51,0.05,0.06))))) -> 0 | O38: =K38*N38 -> 0 | P38: =B38+O38 -> 41008 | Q38: =IF(K38>=(B38*1.6),"YES","NO") -> NO | R38: =IF(L38<0.8,"Below Target",IF(L38<1,"At Target",IF(L38<1.3,"Above Target","Excellent"))) -> Below Target

Sheet Trail Income Model
A1: Employee Name | B1: Total AUM | C1: Trail Rate % | D1: Annual Trail Commission | E1: Source Type | F1: Incremental Business | G1: Effective Base for Sharing | H1: RM Share % | I1: RM Annual Trail | J1: RM Monthly Trail | K1: Mgmt Share % | L1: Mgmt Annual Trail | M1: Company Share % | N1: Company Annual Trail
A2: Balbinder Kaur | C2: 0.005 | D2: =B2*C2 -> 0 | G2: =IF(E2="Self-sourced",D2,IF(E2="Assigned + New Business",D2+F2,IF(E2="Assigned + No New Business",D2,D2+F2))) -> 0 | H2: =IFERROR(VLOOKUP(E2,'Incentive Slabs'!$A$25:$D$28,2,0),0) -> 0 | I2: =G2*C2*H2 -> 0 | J2: =I2/12 -> 0 | K2: =IFERROR(VLOOKUP(E2,'Incentive Slabs'!$A$25:$D$28,3,0),0) -> 0 | L2: =G2*C2*K2 -> 0 | M2: =IFERROR(VLOOKUP(E2,'Incentive Slabs'!$A$25:$D$28,4,0),0) -> 0 | N2: =G2*C2*M2 -> 0
A3: Ajanta Saikia | C3: 0.005 | D3: =B3*C3 -> 0 | G3: =IF(E3="Self-sourced",D3,IF(E3="Assigned + New Business",D3+F3,IF(E3="Assigned + No New Business",D3,D3+F3))) -> 0 | H3: =IFERROR(VLOOKUP(E3,'Incentive Slabs'!$A$25:$D$28,2,0),0) -> 0 | I3: =G3*C3*H3 -> 0 | J3: =I3/12 -> 0 | K3: =IFERROR(VLOOKUP(E3,'Incentive Slabs'!$A$25:$D$28,3,0),0) -> 0 | L3: =G3*C3*K3 -> 0 | M3: =IFERROR(VLOOKUP(E3,'Incentive Slabs'!$A$25:$D$28,4,0),0) -> 0 | N3: =G3*C3*M3 -> 0
A4: Akash Kumar | C4: 0.005 | D4: =B4*C4 -> 0 | G4: =IF(E4="Self-sourced",D4,IF(E4="Assigned + New Business",D4+F4,IF(E4="Assigned + No New Business",D4,D4+F4))) -> 0 | H4: =IFERROR(VLOOKUP(E4,'Incentive Slabs'!$A$25:$D$28,2,0),0) -> 0 | I4: =G4*C4*H4 -> 0 | J4: =I4/12 -> 0 | K4: =IFERROR(VLOOKUP(E4,'Incentive Slabs'!$A$25:$D$28,3,0),0) -> 0 | L4: =G4*C4*K4 -> 0 | M4: =IFERROR(VLOOKUP(E4,'Incentive Slabs'!$A$25:$D$28,4,0),0) -> 0 | N4: =G4*C4*M4 -> 0
A5: Jitender Roy | C5: 0.005 | D5: =B5*C5 -> 0 | G5: =IF(E5="Self-sourced",D5,IF(E5="Assigned + New Business",D5+F5,IF(E5="Assigned + No New Business",D5,D5+F5))) -> 0 | H5: =IFERROR(VLOOKUP(E5,'Incentive Slabs'!$A$25:$D$28,2,0),0) -> 0 | I5: =G5*C5*H5 -> 0 | J5: =I5/12 -> 0 | K5: =IFERROR(VLOOKUP(E5,'Incentive Slabs'!$A$25:$D$28,3,0),0) -> 0 | L5: =G5*C5*K5 -> 0 | M5: =IFERROR(VLOOKUP(E5,'Incentive Slabs'!$A$25:$D$28,4,0),0) -> 0 | N5: =G5*C5*M5 -> 0
A6: Rafiqueddin Ahmed | C6: 0.005 | D6: =B6*C6 -> 0 | G6: =IF(E6="Self-sourced",D6,IF(E6="Assigned + New Business",D6+F6,IF(E6="Assigned + No New Business",D6,D6+F6))) -> 0 | H6: =IFERROR(VLOOKUP(E6,'Incentive Slabs'!$A$25:$D$28,2,0),0) -> 0 | I6: =G6*C6*H6 -> 0 | J6: =I6/12 -> 0 | K6: =IFERROR(VLOOKUP(E6,'Incentive Slabs'!$A$25:$D$28,3,0),0) -> 0 | L6: =G6*C6*K6 -> 0 | M6: =IFERROR(VLOOKUP(E6,'Incentive Slabs'!$A$25:$D$28,4,0),0) -> 0 | N6: =G6*C6*M6 -> 0
A7: Tamanna Kejriwal | C7: 0.005 | D7: =B7*C7 -> 0 | G7: =IF(E7="Self-sourced",D7,IF(E7="Assigned + New Business",D7+F7,IF(E7="Assigned + No New Business",D7,D7+F7))) -> 0 | H7: =IFERROR(VLOOKUP(E7,'Incentive Slabs'!$A$25:$D$28,2,0),0) -> 0 | I7: =G7*C7*H7 -> 0 | J7: =I7/12 -> 0 | K7: =IFERROR(VLOOKUP(E7,'Incentive Slabs'!$A$25:$D$28,3,0),0) -> 0 | L7: =G7*C7*K7 -> 0 | M7: =IFERROR(VLOOKUP(E7,'Incentive Slabs'!$A$25:$D$28,4,0),0) -> 0 | N7: =G7*C7*M7 -> 0
A8: Laxman Sharma | C8: 0.005 | D8: =B8*C8 -> 0 | G8: =IF(E8="Self-sourced",D8,IF(E8="Assigned + New Business",D8+F8,IF(E8="Assigned + No New Business",D8,D8+F8))) -> 0 | H8: =IFERROR(VLOOKUP(E8,'Incentive Slabs'!$A$25:$D$28,2,0),0) -> 0 | I8: =G8*C8*H8 -> 0 | J8: =I8/12 -> 0 | K8: =IFERROR(VLOOKUP(E8,'Incentive Slabs'!$A$25:$D$28,3,0),0) -> 0 | L8: =G8*C8*K8 -> 0 | M8: =IFERROR(VLOOKUP(E8,'Incentive Slabs'!$A$25:$D$28,4,0),0) -> 0 | N8: =G8*C8*M8 -> 0
A9: Bhola Singh | C9: 0.005 | D9: =B9*C9 -> 0 | G9: =IF(E9="Self-sourced",D9,IF(E9="Assigned + New Business",D9+F9,IF(E9="Assigned + No New Business",D9,D9+F9))) -> 0 | H9: =IFERROR(VLOOKUP(E9,'Incentive Slabs'!$A$25:$D$28,2,0),0) -> 0 | I9: =G9*C9*H9 -> 0 | J9: =I9/12 -> 0 | K9: =IFERROR(VLOOKUP(E9,'Incentive Slabs'!$A$25:$D$28,3,0),0) -> 0 | L9: =G9*C9*K9 -> 0 | M9: =IFERROR(VLOOKUP(E9,'Incentive Slabs'!$A$25:$D$28,4,0),0) -> 0 | N9: =G9*C9*M9 -> 0
A10: Harshita Jalan | C10: 0.005 | D10: =B10*C10 -> 0 | G10: =IF(E10="Self-sourced",D10,IF(E10="Assigned + New Business",D10+F10,IF(E10="Assigned + No New Business",D10,D10+F10))) -> 0 | H10: =IFERROR(VLOOKUP(E10,'Incentive Slabs'!$A$25:$D$28,2,0),0) -> 0 | I10: =G10*C10*H10 -> 0 | J10: =I10/12 -> 0 | K10: =IFERROR(VLOOKUP(E10,'Incentive Slabs'!$A$25:$D$28,3,0),0) -> 0 | L10: =G10*C10*K10 -> 0 | M10: =IFERROR(VLOOKUP(E10,'Incentive Slabs'!$A$25:$D$28,4,0),0) -> 0 | N10: =G10*C10*M10 -> 0
A11: Raj Das | C11: 0.005 | D11: =B11*C11 -> 0 | G11: =IF(E11="Self-sourced",D11,IF(E11="Assigned + New Business",D11+F11,IF(E11="Assigned + No New Business",D11,D11+F11))) -> 0 | H11: =IFERROR(VLOOKUP(E11,'Incentive Slabs'!$A$25:$D$28,2,0),0) -> 0 | I11: =G11*C11*H11 -> 0 | J11: =I11/12 -> 0 | K11: =IFERROR(VLOOKUP(E11,'Incentive Slabs'!$A$25:$D$28,3,0),0) -> 0 | L11: =G11*C11*K11 -> 0 | M11: =IFERROR(VLOOKUP(E11,'Incentive Slabs'!$A$25:$D$28,4,0),0) -> 0 | N11: =G11*C11*M11 -> 0

Sheet Profit Center P&L
A1: Vertical | B1: Monthly Revenue | C1: Vertical Head Salary | D1: Team Salary | E1: Team Incentives | F1: Other Variable Costs | G1: Attrition Cost | H1: TOTAL COST | I1: GROSS PROFIT | J1: Cost-to-Income % | K1: Profit Center Head Bonus Rate | L1: Head's Profit Bonus | M1: Health Status
A2: Life Insurance | C2: =SUMIFS('Employee Master'!$G$2:$G$100,'Employee Master'!$E$2:$E$100,A2,'Employee Master'!$F$2:$F$100,"SALES") -> 0 | D2: =SUMIF('Employee Master'!$E$2:$E$100,A2,'Employee Master'!$G$2:$G$100) -> 0 | H2: =C2+D2+E2+F2+G2 -> 0 | I2: =IF(B2=0,0,B2-H2) -> 0 | J2: =IF(B2=0,0,H2/B2) -> 0 | K2: 0.02 | L2: =IF(I2>0,I2*K2,0) -> 0 | M2: =IF(J2<0.25,"Healthy",IF(J2<0.35,"Warning","Critical")) -> Healthy
A3: Health Insurance | C3: =SUMIFS('Employee Master'!$G$2:$G$100,'Employee Master'!$E$2:$E$100,A3,'Employee Master'!$F$2:$F$100,"SALES") -> 0 | D3: =SUMIF('Employee Master'!$E$2:$E$100,A3,'Employee Master'!$G$2:$G$100) -> 0 | H3: =C3+D3+E3+F3+G3 -> 0 | I3: =IF(B3=0,0,B3-H3) -> 0 | J3: =IF(B3=0,0,H3/B3) -> 0 | K3: 0.02 | L3: =IF(I3>0,I3*K3,0) -> 0 | M3: =IF(J3<0.25,"Healthy",IF(J3<0.35,"Warning","Critical")) -> Healthy
A4: General Insurance | C4: =SUMIFS('Employee Master'!$G$2:$G$100,'Employee Master'!$E$2:$E$100,A4,'Employee Master'!$F$2:$F$100,"SALES") -> 0 | D4: =SUMIF('Employee Master'!$E$2:$E$100,A4,'Employee Master'!$G$2:$G$100) -> 0 | H4: =C4+D4+E4+F4+G4 -> 0 | I4: =IF(B4=0,0,B4-H4) -> 0 | J4: =IF(B4=0,0,H4/B4) -> 0 | K4: 0.02 | L4: =IF(I4>0,I4*K4,0) -> 0 | M4: =IF(J4<0.25,"Healthy",IF(J4<0.35,"Warning","Critical")) -> Healthy
A5: Financial Planning | C5: =SUMIFS('Employee Master'!$G$2:$G$100,'Employee Master'!$E$2:$E$100,A5,'Employee Master'!$F$2:$F$100,"SALES") -> 0 | D5: =SUMIF('Employee Master'!$E$2:$E$100,A5,'Employee Master'!$G$2:$G$100) -> 0 | H5: =C5+D5+E5+F5+G5 -> 0 | I5: =IF(B5=0,0,B5-H5) -> 0 | J5: =IF(B5=0,0,H5/B5) -> 0 | K5: 0.02 | L5: =IF(I5>0,I5*K5,0) -> 0 | M5: =IF(J5<0.25,"Healthy",IF(J5<0.35,"Warning","Critical")) -> Healthy
A6: POSP Channel | C6: =SUMIFS('Employee Master'!$G$2:$G$100,'Employee Master'!$E$2:$E$100,A6,'Employee Master'!$F$2:$F$100,"SALES") -> 0 | D6: =SUMIF('Employee Master'!$E$2:$E$100,A6,'Employee Master'!$G$2:$G$100) -> 0 | H6: =C6+D6+E6+F6+G6 -> 0 | I6: =IF(B6=0,0,B6-H6) -> 0 | J6: =IF(B6=0,0,H6/B6) -> 0 | K6: 0.02 | L6: =IF(I6>0,I6*K6,0) -> 0 | M6: =IF(J6<0.25,"Healthy",IF(J6<0.35,"Warning","Critical")) -> Healthy
A7: Operations | C7: =SUMIFS('Employee Master'!$G$2:$G$100,'Employee Master'!$E$2:$E$100,A7,'Employee Master'!$F$2:$F$100,"SALES") -> 0 | D7: =SUMIF('Employee Master'!$E$2:$E$100,A7,'Employee Master'!$G$2:$G$100) -> 0 | H7: =C7+D7+E7+F7+G7 -> 0 | I7: =IF(B7=0,0,B7-H7) -> 0 | J7: =IF(B7=0,0,H7/B7) -> 0 | K7: 0.02 | L7: =IF(I7>0,I7*K7,0) -> 0 | M7: =IF(J7<0.25,"Healthy",IF(J7<0.35,"Warning","Critical")) -> Healthy
A8: Admin & Accounts | C8: =SUMIFS('Employee Master'!$G$2:$G$100,'Employee Master'!$E$2:$E$100,A8,'Employee Master'!$F$2:$F$100,"SALES") -> 0 | D8: =SUMIF('Employee Master'!$E$2:$E$100,A8,'Employee Master'!$G$2:$G$100) -> 0 | H8: =C8+D8+E8+F8+G8 -> 0 | I8: =IF(B8=0,0,B8-H8) -> 0 | J8: =IF(B8=0,0,H8/B8) -> 0 | K8: 0.02 | L8: =IF(I8>0,I8*K8,0) -> 0 | M8: =IF(J8<0.25,"Healthy",IF(J8<0.35,"Warning","Critical")) -> Healthy
A9: Digital & IT | C9: =SUMIFS('Employee Master'!$G$2:$G$100,'Employee Master'!$E$2:$E$100,A9,'Employee Master'!$F$2:$F$100,"SALES") -> 47486 | D9: =SUMIF('Employee Master'!$E$2:$E$100,A9,'Employee Master'!$G$2:$G$100) -> 47486 | H9: =C9+D9+E9+F9+G9 -> 94972 | I9: =IF(B9=0,0,B9-H9) -> 0 | J9: =IF(B9=0,0,H9/B9) -> 0 | K9: 0.02 | L9: =IF(I9>0,I9*K9,0) -> 0 | M9: =IF(J9<0.25,"Healthy",IF(J9<0.35,"Warning","Critical")) -> Healthy
A10: Training | C10: =SUMIFS('Employee Master'!$G$2:$G$100,'Employee Master'!$E$2:$E$100,A10,'Employee Master'!$F$2:$F$100,"SALES") -> 0 | D10: =SUMIF('Employee Master'!$E$2:$E$100,A10,'Employee Master'!$G$2:$G$100) -> 0 | H10: =C10+D10+E10+F10+G10 -> 0 | I10: =IF(B10=0,0,B10-H10) -> 0 | J10: =IF(B10=0,0,H10/B10) -> 0 | K10: 0.02 | L10: =IF(I10>0,I10*K10,0) -> 0 | M10: =IF(J10<0.25,"Healthy",IF(J10<0.35,"Warning","Critical")) -> Healthy
C11: =SUMIFS('Employee Master'!$G$2:$G$100,'Employee Master'!$E$2:$E$100,A11,'Employee Master'!$F$2:$F$100,"SALES") -> 0 | D11: =SUMIF('Employee Master'!$E$2:$E$100,A11,'Employee Master'!$G$2:$G$100) -> 0 | H11: =C11+D11+E11+F11+G11 -> 0 | I11: =IF(B11=0,0,B11-H11) -> 0 | J11: =IF(B11=0,0,H11/B11) -> 0 | L11: =IF(I11>0,I11*K11,0) -> 0 | M11: =IF(J11<0.25,"Healthy",IF(J11<0.35,"Warning","Critical")) -> Healthy

Sheet Hiring ROI Calculator
A1: Parameter | B1: Kolkata Example | C1: Team 2 | D1: Team 3 | E1: Team 4 | F1: Team 5
A2: Candidate Name | B2: Kolkata Lead
A3: Location | B3: 100000 | C3: 80000 | D3: 75000 | E3: 90000 | F3: 110000
A4: Leader Salary/month | B4: 5 | C4: 4 | D4: 6 | E4: 3 | F4: 5
A5: Team Size | B5: 30000 | C5: 35000 | D5: 28000 | E5: 40000 | F5: 32000
A6: Avg Team Salary | B6: 200000 | C6: 250000 | D6: 150000 | E6: 300000 | F6: 180000
A7: Setup Cost | B7: 3 | C7: 3 | D7: 4 | E7: 2 | F7: 3
A8: Grace Period (months) | B8: 800000 | C8: 600000 | D8: 900000 | E8: 500000 | F8: 750000
A9: Expected Monthly Revenue | B9: 0.2 | C9: 0.25 | D9: 0.18 | E9: 0.3 | F9: 0.22
A10: Company Revenue Share % | B10: 0.2
B11: =IF(OR(ISBLANK(B3),ISBLANK(B4),ISBLANK(B5)),0,B3+(B4*B5)) -> 250000 | C11: =IF(OR(ISBLANK(C3),ISBLANK(C4),ISBLANK(C5)),0,C3+(C4*C5)) -> 220000 | D11: =IF(OR(ISBLANK(D3),ISBLANK(D4),ISBLANK(D5)),0,D3+(D4*D5)) -> 243000 | E11: =IF(OR(ISBLANK(E3),ISBLANK(E4),ISBLANK(E5)),0,E3+(E4*E5)) -> 210000 | F11: =IF(OR(ISBLANK(F3),ISBLANK(F4),ISBLANK(F5)),0,F3+(F4*F5)) -> 270000
A12: Monthly Team Cost | B12: =IF(OR(ISBLANK(B11),ISBLANK(B6),ISBLANK(B7)),-1,B11+(IF(B7=0,0,B6/B7))) -> 316666.67 | C12: =IF(OR(ISBLANK(C11),ISBLANK(C6),ISBLANK(C7)),-1,C11+(IF(C7=0,0,C6/C7))) -> 303333.33 | D12: =IF(OR(ISBLANK(D11),ISBLANK(D6),ISBLANK(D7)),-1,D11+(IF(D7=0,0,D6/D7))) -> 280500 | E12: =IF(OR(ISBLANK(E11),ISBLANK(E6),ISBLANK(E7)),-1,E11+(IF(E7=0,0,E6/E7))) -> 360000 | F12: =IF(OR(ISBLANK(F11),ISBLANK(F6),ISBLANK(F7)),-1,F11+(IF(F7=0,0,F6/F7))) -> 330000
A13: Total Monthly Burn | B13: =IF(ISBLANK(B12),-1,B12*6) -> 1900000 | C13: =IF(ISBLANK(C12),-1,C12*6) -> 1820000 | D13: =IF(ISBLANK(D12),-1,D12*6) -> 1683000 | E13: =IF(ISBLANK(E12),-1,E12*6) -> 2160000 | F13: =IF(ISBLANK(F12),-1,F12*6) -> 1980000
A14: 6-Month Investment | B14: =IF(ISBLANK(B12),-1,B12*12) -> 3800000 | C14: =IF(ISBLANK(C12),-1,C12*12) -> 3640000 | D14: =IF(ISBLANK(D12),-1,D12*12) -> 3366000 | E14: =IF(ISBLANK(E12),-1,E12*12) -> 4320000 | F14: =IF(ISBLANK(F12),-1,F12*12) -> 3960000
A15: 12-Month Investment | B15: =IF(OR(ISBLANK(B8),ISBLANK(B9)),0,B8*B9) -> 160000 | C15: =IF(OR(ISBLANK(C8),ISBLANK(C9)),0,C8*C9) -> 150000 | D15: =IF(OR(ISBLANK(D8),ISBLANK(D9)),0,D8*D9) -> 162000 | E15: =IF(OR(ISBLANK(E8),ISBLANK(E9)),0,E8*E9) -> 150000 | F15: =IF(OR(ISBLANK(F8),ISBLANK(F9)),0,F8*F9) -> 165000
A16: Monthly Net Revenue | B16: =IF(OR(ISBLANK(B15),ISBLANK(B12)),-1,B15-B12) -> -156666.67 | C16: =IF(OR(ISBLANK(C15),ISBLANK(C12)),-1,C15-C12) -> -153333.33 | D16: =IF(OR(ISBLANK(D15),ISBLANK(D12)),-1,D15-D12) -> -118500 | E16: =IF(OR(ISBLANK(E15),ISBLANK(E12)),-1,E15-E12) -> -210000 | F16: =IF(OR(ISBLANK(F15),ISBLANK(F12)),-1,F15-F12) -> -165000
A17: Monthly Profit | B17: =IF(OR(B16<=0,ISBLANK(B16)),999,B13/B16) -> 999 | C17: =IF(OR(C16<=0,ISBLANK(C16)),999,C13/C16) -> 999 | D17: =IF(OR(D16<=0,ISBLANK(D16)),999,D13/D16) -> 999 | E17: =IF(OR(E16<=0,ISBLANK(E16)),999,E13/E16) -> 999 | F17: =IF(OR(F16<=0,ISBLANK(F16)),999,F13/F16) -> 999
A18: Breakeven Months | B18: =IF(ISBLANK(B17),"Error",IF(B17<=6,"Healthy",IF(B17<=12,"Warning","Critical"))) -> Critical | C18: =IF(ISBLANK(C17),"Error",IF(C17<=6,"Healthy",IF(C17<=12,"Warning","Critical"))) -> Critical | D18: =IF(ISBLANK(D17),"Error",IF(D17<=6,"Healthy",IF(D17<=12,"Warning","Critical"))) -> Critical | E18: =IF(ISBLANK(E17),"Error",IF(E17<=6,"Healthy",IF(E17<=12,"Warning","Critical"))) -> Critical | F18: =IF(ISBLANK(F17),"Error",IF(F17<=6,"Healthy",IF(F17<=12,"Warning","Critical"))) -> Critical
A19: ROI Status | B19: =IF(C16<100000,"Healthy",IF(C16<50000,"Warning","Critical")) -> Healthy

Sheet Promotion Criteria
A1: Current Level | B1: Next Level | C1: Min Tenure (Yrs) | D1: Target Achievement % | E1: Additional Requirements | F1: Salary Jump %
A2: L6 | B2: L5 | C2: 2 | D2: 0.8 | E2: Consistent performance | F2: 0.1
A3: L5 | B3: L4 | C3: 3 | D3: 0.9 | E3: Team management skills | F3: 0.15
A4: L4 | B4: L3 | C4: 3 | D4: 0.95 | E4: Leadership & strategic thinking | F4: 0.2
A5: L3 | B5: L2 | C5: 4 | D5: 1 | E5: Cross-functional expertise | F5: 0.25
A6: L2 | B6: L1 | C6: 5 | D6: 1.1 | E6: Business development acumen | F6: 0.3

Sheet 5-Year Projection
A1: Parameter | B1: FY27 | C1: FY28 | D1: FY29 | E1: FY30 | F1: FY31
A2: Sales Headcount | B2: 45 | C2: 90 | D2: 126 | E2: 176 | F2: 246
A3: Support Headcount | B3: 32 | C3: 42 | D3: 54 | E3: 70 | F3: 91
A4: Outsourced Staff | B4: 3 | C4: 4 | D4: 5 | E4: 7 | F4: 9
A5: Total Headcount | B5: =B2+B3+B4 -> 80 | C5: =C2+C3+C4 -> 136 | D5: =D2+D3+D4 -> 185 | E5: =E2+E3+E4 -> 253 | F5: =F2+F3+F4 -> 346
A6: Avg Salary | B6: 35000 | C6: 38500 | D6: 42350 | E6: 46585 | F6: 51243
A7: Annual Fixed Cost (12 months) | B7: =B5*B6*12 -> 33600000 | C7: =C5*C6*12 -> 62832000 | D7: =D5*D6*12 -> 94017000 | E7: =E5*E6*12 -> 141432060 | F7: =F5*F6*12 -> 212760936
A8: Revenue Target (30% CTI) | B8: =B7/0.3 -> 112000000 | C8: =C7/0.3 -> 209440000 | D8: =D7/0.3 -> 313390000 | E8: =E7/0.3 -> 471440200 | F8: =F7/0.3 -> 709203120
A9: Variable Cost (8% of revenue) | B9: =B8*0.08 -> 8960000 | C9: =C8*0.08 -> 16755200 | D9: =D8*0.08 -> 25071200 | E9: =E8*0.08 -> 37715216 | F9: =F8*0.08 -> 56736250
A10: Total Cost | B10: =B7+B9 -> 42560000 | C10: =C7+C9 -> 79587200 | D10: =D7+D9 -> 119088200 | E10: =E7+E9 -> 179147276 | F10: =F7+F9 -> 2.6949719e+08
A11: Net Profit | B11: =B8-B10 -> 69440000 | C11: =C8-C10 -> 129852800 | D11: =D8-D10 -> 194301800 | E11: =E8-E10 -> 292292924 | F11: =F8-F10 -> 4.3970593e+08
A12: ROI % | B12: =IF(B10=0,0,B11/B10) -> 1.6315789 | C12: =IF(C10=0,0,C11/C10) -> 1.6315789 | D12: =IF(D10=0,0,D11/D10) -> 1.6315789 | E12: =IF(E10=0,0,E11/E10) -> 1.6315789 | F12: =IF(F10=0,0,F11/F10) -> 1.6315789
A13: Revenue per Employee | B13: =IF(B5=0,0,B8/B5) -> 1400000 | C13: =IF(C5=0,0,C8/C5) -> 1540000 | D13: =IF(D5=0,0,D8/D5) -> 1694000 | E13: =IF(E5=0,0,E8/E5) -> 1863400 | F13: =IF(F5=0,0,F8/F5) -> 2049720

Sheet Org Cost Dashboard
A1: TRUSTNER GROUP - ORGANIZATION COST DASHBOARD
A3: Headcount by Entity
A4: Entity | B4: Count | C4: % of Total
A5: TIB | B5: =COUNTIF('Employee Master'!$H$2:$H$100,"TIB") -> 33 | C5: =IF(SUM($B$5:$B$7)=0,0,B5/SUM($B$5:$B$7)) -> 0.54098361
A6: TAS | B6: =COUNTIF('Employee Master'!$H$2:$H$100,"TAS") -> 25 | C6: =IF(SUM($B$5:$B$7)=0,0,B6/SUM($B$5:$B$7)) -> 0.40983607
A7: Vendor | B7: =COUNTIF('Employee Master'!$H$2:$H$100,"Vendor") -> 3 | C7: =IF(SUM($B$5:$B$7)=0,0,B7/SUM($B$5:$B$7)) -> 0.049180328
A9: Total Monthly Payroll
A10: Total Monthly Payroll | B10: =SUM('Employee Master'!$G$2:$G$100) -> 2419683
A11: Annual Payroll | B11: =B10*12 -> 29036196
A13: Department-wise Cost Breakdown
A14: Department | B14: Headcount | C14: Total Salary | D14: % of Payroll
A15: LIFE | B15: =COUNTIF('Employee Master'!$E$2:$E$100,"LIFE") -> 3 | C15: =SUMIF('Employee Master'!$E$2:$E$100,"LIFE",'Employee Master'!$G$2:$G$100) -> 181651 | D15: =IF($B$11=0,0,C15/$B$11) -> 0.0062560192
A16: HEALTH | B16: =COUNTIF('Employee Master'!$E$2:$E$100,"HEALTH") -> 9 | C16: =SUMIF('Employee Master'!$E$2:$E$100,"HEALTH",'Employee Master'!$G$2:$G$100) -> 368591 | D16: =IF($B$11=0,0,C16/$B$11) -> 0.01269419
A17: G.I. | B17: =COUNTIF('Employee Master'!$E$2:$E$100,"G.I.") -> 4 | C17: =SUMIF('Employee Master'!$E$2:$E$100,"G.I.",'Employee Master'!$G$2:$G$100) -> 184054 | D17: =IF($B$11=0,0,C17/$B$11) -> 0.006338778
A18: F.P. | B18: =COUNTIF('Employee Master'!$E$2:$E$100,"F.P.") -> 7 | C18: =SUMIF('Employee Master'!$E$2:$E$100,"F.P.",'Employee Master'!$G$2:$G$100) -> 244316 | D18: =IF($B$11=0,0,C18/$B$11) -> 0.0084141876
A19: DEMAT | B19: =COUNTIF('Employee Master'!$E$2:$E$100,"DEMAT") -> 1 | C19: =SUMIF('Employee Master'!$E$2:$E$100,"DEMAT",'Employee Master'!$G$2:$G$100) -> 27008 | D19: =IF($B$11=0,0,C19/$B$11) -> 0.00093014939
A20: POSP | B20: =COUNTIF('Employee Master'!$E$2:$E$100,"POSP") -> 8 | C20: =SUMIF('Employee Master'!$E$2:$E$100,"POSP",'Employee Master'!$G$2:$G$100) -> 431877 | D20: =IF($B$11=0,0,C20/$B$11) -> 0.014873746
A21: OPERATION | B21: =COUNTIF('Employee Master'!$E$2:$E$100,"OPERATION") -> 19 | C21: =SUMIF('Employee Master'!$E$2:$E$100,"OPERATION",'Employee Master'!$G$2:$G$100) -> 749065 | D21: =IF($B$11=0,0,C21/$B$11) -> 0.025797629
A22: ADMIN | B22: =COUNTIF('Employee Master'!$E$2:$E$100,"ADMIN") -> 5 | C22: =SUMIF('Employee Master'!$E$2:$E$100,"ADMIN",'Employee Master'!$G$2:$G$100) -> 116327 | D22: =IF($B$11=0,0,C22/$B$11) -> 0.0040062755
A23: ACCOUNTS | B23: =COUNTIF('Employee Master'!$E$2:$E$100,"ACCOUNTS") -> 2 | C23: =SUMIF('Employee Master'!$E$2:$E$100,"ACCOUNTS",'Employee Master'!$G$2:$G$100) -> 69308 | D23: =IF($B$11=0,0,C23/$B$11) -> 0.0023869518
A24: DIGITAL & IT | B24: =COUNTIF('Employee Master'!$E$2:$E$100,"DIGITAL & IT") -> 3 | C24: =SUMIF('Employee Master'!$E$2:$E$100,"DIGITAL & IT",'Employee Master'!$G$2:$G$100) -> 47486 | D24: =IF($B$11=0,0,C24/$B$11) -> 0.0016354071
A27: Sales vs Support Cost Ratio
A28: Total Sales Cost | B28: =SUMIF('Employee Master'!$F$2:$F$100,"SALES",'Employee Master'!$G$2:$G$100) -> 1866054
A29: Total Support Cost | B29: =SUMIF('Employee Master'!$F$2:$F$100,"<>SALES",'Employee Master'!$G$2:$G$100) -> 553629
A30: Sales/Support Ratio | B30: =IF(B29=0,0,B28/B29) -> 3.3705857
A32: Top 10 Highest Paid Employees
A33: Rank | B33: Name | C33: Designation | D33: Monthly Salary

Sheet Admin & Controls
A1: ADMIN & CONTROLS - ACCESS CONTROL MATRIX
A2: Role | B2: View Data | C2: Edit Salary | D2: Edit Target | E2: Edit Incentive | F2: Approve Bonus
A3: CEO/MD | B3: Yes | C3: Yes | D3: Yes | E3: Yes | F3: Yes
A4: CFO | B4: Yes | C4: Yes | D4: No | E4: Yes | F4: Yes
A5: HR Manager | B5: Yes | C5: Yes | D5: No | E5: No | F5: No
A6: Dept Head | B6: Own Dept | C6: No | D6: Yes | E6: No | F6: No
A7: Finance Team | B7: Yes | C7: No | D7: No | E7: No | F7: No
A10: AUDIT LOG TEMPLATE
A11: Date | B11: Employee | C11: Parameter | D11: Old Value | E11: New Value | F11: Changed By | G11: Approved By | H11: Reason
A12: 46110
